Workbook

Sheet Cover
B3: Configuration Parameters
B5: Generated: | C5: June 05, 2026
B6: Solution: | C6: Tmpnaegu_A5
B7: Customer: | C7: [Customer Name]
B8: Version: | C8: 1.0
B9: Status: | C9: Draft
C12: eoframework.org

Sheet All Parameters (Read Only)
A1: Total Parameters | B1: Categories | C1: Required | D1: Confidential/Secret
A2: 119 | B2: 11 | C2: 119 | D2: 28
A4: Parameter Name | B4: Category | C4: Production | D4: Test | E4: DR | F4: Description | G4: Required | H4: Data Type | I4: Validation Rules | J4: Security Level | K4: Owner Team | L4: Dependencies | M4: Notes | N4: Last Updated
A5: =IF('Project'!A3="","",'Project'!A3) | B5: Project | C5: =IF('Project'!B3="","",'Project'!B3) | D5: =IF('Project'!C3="","",'Project'!C3) | E5: =IF('Project'!D3="","",'Project'!D3) | F5: =IF('Project'!E3="","",'Project'!E3) | G5: =IF('Project'!F3="","",'Project'!F3) | H5: =IF('Project'!G3="","",'Project'!G3) | I5: =IF('Project'!H3="","",'Project'!H3) | J5: =IF('Project'!I3="","",'Project'!I3) | ... N5: =IF('Project'!M3="","",'Project'!M3)
A6: =IF('Project'!A4="","",'Project'!A4) | B6: Project | C6: =IF('Project'!B4="","",'Project'!B4) | D6: =IF('Project'!C4="","",'Project'!C4) | E6: =IF('Project'!D4="","",'Project'!D4) | F6: =IF('Project'!E4="","",'Project'!E4) | G6: =IF('Project'!F4="","",'Project'!F4) | H6: =IF('Project'!G4="","",'Project'!G4) | I6: =IF('Project'!H4="","",'Project'!H4) | J6: =IF('Project'!I4="","",'Project'!I4) | ... N6: =IF('Project'!M4="","",'Project'!M4)
A7: =IF('Project'!A5="","",'Project'!A5) | B7: Project | C7: =IF('Project'!B5="","",'Project'!B5) | D7: =IF('Project'!C5="","",'Project'!C5) | E7: =IF('Project'!D5="","",'Project'!D5) | F7: =IF('Project'!E5="","",'Project'!E5) | G7: =IF('Project'!F5="","",'Project'!F5) | H7: =IF('Project'!G5="","",'Project'!G5) | I7: =IF('Project'!H5="","",'Project'!H5) | J7: =IF('Project'!I5="","",'Project'!I5) | ... N7: =IF('Project'!M5="","",'Project'!M5)
A8: =IF('Project'!A6="","",'Project'!A6) | B8: Project | C8: =IF('Project'!B6="","",'Project'!B6) | D8: =IF('Project'!C6="","",'Project'!C6) | E8: =IF('Project'!D6="","",'Project'!D6) | F8: =IF('Project'!E6="","",'Project'!E6) | G8: =IF('Project'!F6="","",'Project'!F6) | H8: =IF('Project'!G6="","",'Project'!G6) | I8: =IF('Project'!H6="","",'Project'!H6) | J8: =IF('Project'!I6="","",'Project'!I6) | ... N8: =IF('Project'!M6="","",'Project'!M6)
A9: =IF('Project'!A7="","",'Project'!A7) | B9: Project | C9: =IF('Project'!B7="","",'Project'!B7) | D9: =IF('Project'!C7="","",'Project'!C7) | E9: =IF('Project'!D7="","",'Project'!D7) | F9: =IF('Project'!E7="","",'Project'!E7) | G9: =IF('Project'!F7="","",'Project'!F7) | H9: =IF('Project'!G7="","",'Project'!G7) | I9: =IF('Project'!H7="","",'Project'!H7) | J9: =IF('Project'!I7="","",'Project'!I7) | ... N9: =IF('Project'!M7="","",'Project'!M7)
A10: =IF('Project'!A8="","",'Project'!A8) | B10: Project | C10: =IF('Project'!B8="","",'Project'!B8) | D10: =IF('Project'!C8="","",'Project'!C8) | E10: =IF('Project'!D8="","",'Project'!D8) | F10: =IF('Project'!E8="","",'Project'!E8) | G10: =IF('Project'!F8="","",'Project'!F8) | H10: =IF('Project'!G8="","",'Project'!G8) | I10: =IF('Project'!H8="","",'Project'!H8) | J10: =IF('Project'!I8="","",'Project'!I8) | ... N10: =IF('Project'!M8="","",'Project'!M8)
A11: =IF('Project'!A9="","",'Project'!A9) | B11: Project | C11: =IF('Project'!B9="","",'Project'!B9) | D11: =IF('Project'!C9="","",'Project'!C9) | E11: =IF('Project'!D9="","",'Project'!D9) | F11: =IF('Project'!E9="","",'Project'!E9) | G11: =IF('Project'!F9="","",'Project'!F9) | H11: =IF('Project'!G9="","",'Project'!G9) | I11: =IF('Project'!H9="","",'Project'!H9) | J11: =IF('Project'!I9="","",'Project'!I9) | ... N11: =IF('Project'!M9="","",'Project'!M9)
A12: =IF('Networking'!A3="","",'Networking'!A3) | B12: Networking | C12: =IF('Networking'!B3="","",'Networking'!B3) | D12: =IF('Networking'!C3="","",'Networking'!C3) | E12: =IF('Networking'!D3="","",'Networking'!D3) | F12: =IF('Networking'!E3="","",'Networking'!E3) | G12: =IF('Networking'!F3="","",'Networking'!F3) | H12: =IF('Networking'!G3="","",'Networking'!G3) | I12: =IF('Networking'!H3="","",'Networking'!H3) | J12: =IF('Networking'!I3="","",'Networking'!I3) | ... N12: =IF('Networking'!M3="","",'Networking'!M3)
A13: =IF('Networking'!A4="","",'Networking'!A4) | B13: Networking | C13: =IF('Networking'!B4="","",'Networking'!B4) | D13: =IF('Networking'!C4="","",'Networking'!C4) | E13: =IF('Networking'!D4="","",'Networking'!D4) | F13: =IF('Networking'!E4="","",'Networking'!E4) | G13: =IF('Networking'!F4="","",'Networking'!F4) | H13: =IF('Networking'!G4="","",'Networking'!G4) | I13: =IF('Networking'!H4="","",'Networking'!H4) | J13: =IF('Networking'!I4="","",'Networking'!I4) | ... N13: =IF('Networking'!M4="","",'Networking'!M4)
A14: =IF('Networking'!A5="","",'Networking'!A5) | B14: Networking | C14: =IF('Networking'!B5="","",'Networking'!B5) | D14: =IF('Networking'!C5="","",'Networking'!C5) | E14: =IF('Networking'!D5="","",'Networking'!D5) | F14: =IF('Networking'!E5="","",'Networking'!E5) | G14: =IF('Networking'!F5="","",'Networking'!F5) | H14: =IF('Networking'!G5="","",'Networking'!G5) | I14: =IF('Networking'!H5="","",'Networking'!H5) | J14: =IF('Networking'!I5="","",'Networking'!I5) | ... N14: =IF('Networking'!M5="","",'Networking'!M5)
A15: =IF('Networking'!A6="","",'Networking'!A6) | B15: Networking | C15: =IF('Networking'!B6="","",'Networking'!B6) | D15: =IF('Networking'!C6="","",'Networking'!C6) | E15: =IF('Networking'!D6="","",'Networking'!D6) | F15: =IF('Networking'!E6="","",'Networking'!E6) | G15: =IF('Networking'!F6="","",'Networking'!F6) | H15: =IF('Networking'!G6="","",'Networking'!G6) | I15: =IF('Networking'!H6="","",'Networking'!H6) | J15: =IF('Networking'!I6="","",'Networking'!I6) | ... N15: =IF('Networking'!M6="","",'Networking'!M6)
A16: =IF('Networking'!A7="","",'Networking'!A7) | B16: Networking | C16: =IF('Networking'!B7="","",'Networking'!B7) | D16: =IF('Networking'!C7="","",'Networking'!C7) | E16: =IF('Networking'!D7="","",'Networking'!D7) | F16: =IF('Networking'!E7="","",'Networking'!E7) | G16: =IF('Networking'!F7="","",'Networking'!F7) | H16: =IF('Networking'!G7="","",'Networking'!G7) | I16: =IF('Networking'!H7="","",'Networking'!H7) | J16: =IF('Networking'!I7="","",'Networking'!I7) | ... N16: =IF('Networking'!M7="","",'Networking'!M7)
A17: =IF('Networking'!A8="","",'Networking'!A8) | B17: Networking | C17: =IF('Networking'!B8="","",'Networking'!B8) | D17: =IF('Networking'!C8="","",'Networking'!C8) | E17: =IF('Networking'!D8="","",'Networking'!D8) | F17: =IF('Networking'!E8="","",'Networking'!E8) | G17: =IF('Networking'!F8="","",'Networking'!F8) | H17: =IF('Networking'!G8="","",'Networking'!G8) | I17: =IF('Networking'!H8="","",'Networking'!H8) | J17: =IF('Networking'!I8="","",'Networking'!I8) | ... N17: =IF('Networking'!M8="","",'Networking'!M8)
A18: =IF('Networking'!A9="","",'Networking'!A9) | B18: Networking | C18: =IF('Networking'!B9="","",'Networking'!B9) | D18: =IF('Networking'!C9="","",'Networking'!C9) | E18: =IF('Networking'!D9="","",'Networking'!D9) | F18: =IF('Networking'!E9="","",'Networking'!E9) | G18: =IF('Networking'!F9="","",'Networking'!F9) | H18: =IF('Networking'!G9="","",'Networking'!G9) | I18: =IF('Networking'!H9="","",'Networking'!H9) | J18: =IF('Networking'!I9="","",'Networking'!I9) | ... N18: =IF('Networking'!M9="","",'Networking'!M9)
A19: =IF('Networking'!A10="","",'Networking'!A10) | B19: Networking | C19: =IF('Networking'!B10="","",'Networking'!B10) | D19: =IF('Networking'!C10="","",'Networking'!C10) | E19: =IF('Networking'!D10="","",'Networking'!D10) | F19: =IF('Networking'!E10="","",'Networking'!E10) | G19: =IF('Networking'!F10="","",'Networking'!F10) | H19: =IF('Networking'!G10="","",'Networking'!G10) | I19: =IF('Networking'!H10="","",'Networking'!H10) | J19: =IF('Networking'!I10="","",'Networking'!I10) | ... N19: =IF('Networking'!M10="","",'Networking'!M10)
A20: =IF('Networking'!A11="","",'Networking'!A11) | B20: Networking | C20: =IF('Networking'!B11="","",'Networking'!B11) | D20: =IF('Networking'!C11="","",'Networking'!C11) | E20: =IF('Networking'!D11="","",'Networking'!D11) | F20: =IF('Networking'!E11="","",'Networking'!E11) | G20: =IF('Networking'!F11="","",'Networking'!F11) | H20: =IF('Networking'!G11="","",'Networking'!G11) | I20: =IF('Networking'!H11="","",'Networking'!H11) | J20: =IF('Networking'!I11="","",'Networking'!I11) | ... N20: =IF('Networking'!M11="","",'Networking'!M11)
A21: =IF('Networking'!A12="","",'Networking'!A12) | B21: Networking | C21: =IF('Networking'!B12="","",'Networking'!B12) | D21: =IF('Networking'!C12="","",'Networking'!C12) | E21: =IF('Networking'!D12="","",'Networking'!D12) | F21: =IF('Networking'!E12="","",'Networking'!E12) | G21: =IF('Networking'!F12="","",'Networking'!F12) | H21: =IF('Networking'!G12="","",'Networking'!G12) | I21: =IF('Networking'!H12="","",'Networking'!H12) | J21: =IF('Networking'!I12="","",'Networking'!I12) | ... N21: =IF('Networking'!M12="","",'Networking'!M12)
A22: =IF('Networking'!A13="","",'Networking'!A13) | B22: Networking | C22: =IF('Networking'!B13="","",'Networking'!B13) | D22: =IF('Networking'!C13="","",'Networking'!C13) | E22: =IF('Networking'!D13="","",'Networking'!D13) | F22: =IF('Networking'!E13="","",'Networking'!E13) | G22: =IF('Networking'!F13="","",'Networking'!F13) | H22: =IF('Networking'!G13="","",'Networking'!G13) | I22: =IF('Networking'!H13="","",'Networking'!H13) | J22: =IF('Networking'!I13="","",'Networking'!I13) | ... N22: =IF('Networking'!M13="","",'Networking'!M13)
A23: =IF('Networking'!A14="","",'Networking'!A14) | B23: Networking | C23: =IF('Networking'!B14="","",'Networking'!B14) | D23: =IF('Networking'!C14="","",'Networking'!C14) | E23: =IF('Networking'!D14="","",'Networking'!D14) | F23: =IF('Networking'!E14="","",'Networking'!E14) | G23: =IF('Networking'!F14="","",'Networking'!F14) | H23: =IF('Networking'!G14="","",'Networking'!G14) | I23: =IF('Networking'!H14="","",'Networking'!H14) | J23: =IF('Networking'!I14="","",'Networking'!I14) | ... N23: =IF('Networking'!M14="","",'Networking'!M14)
... A25: =IF('Networking'!A16="","",'Networking'!A16) | B25: Networking | C25: =IF('Networking'!B16="","",'Networking'!B16) | D25: =IF('Networking'!C16="","",'Networking'!C16) | E25: =IF('Networking'!D16="","",'Networking'!D16) | F25: =IF('Networking'!E16="","",'Networking'!E16) | G25: =IF('Networking'!F16="","",'Networking'!F16) | H25: =IF('Networking'!G16="","",'Networking'!G16) | I25: =IF('Networking'!H16="","",'Networking'!H16) | J25: =IF('Networking'!I16="","",'Networking'!I16) | ... N25: =IF('Networking'!M16="","",'Networking'!M16)
A26: =IF('Security'!A3="","",'Security'!A3) | B26: Security | C26: =IF('Security'!B3="","",'Security'!B3) | D26: =IF('Security'!C3="","",'Security'!C3) | E26: =IF('Security'!D3="","",'Security'!D3) | F26: =IF('Security'!E3="","",'Security'!E3) | G26: =IF('Security'!F3="","",'Security'!F3) | H26: =IF('Security'!G3="","",'Security'!G3) | I26: =IF('Security'!H3="","",'Security'!H3) | J26: =IF('Security'!I3="","",'Security'!I3) | ... N26: =IF('Security'!M3="","",'Security'!M3)
A27: =IF('Security'!A4="","",'Security'!A4) | B27: Security | C27: =IF('Security'!B4="","",'Security'!B4) | D27: =IF('Security'!C4="","",'Security'!C4) | E27: =IF('Security'!D4="","",'Security'!D4) | F27: =IF('Security'!E4="","",'Security'!E4) | G27: =IF('Security'!F4="","",'Security'!F4) | H27: =IF('Security'!G4="","",'Security'!G4) | I27: =IF('Security'!H4="","",'Security'!H4) | J27: =IF('Security'!I4="","",'Security'!I4) | ... N27: =IF('Security'!M4="","",'Security'!M4)
A28: =IF('Security'!A5="","",'Security'!A5) | B28: Security | C28: =IF('Security'!B5="","",'Security'!B5) | D28: =IF('Security'!C5="","",'Security'!C5) | E28: =IF('Security'!D5="","",'Security'!D5) | F28: =IF('Security'!E5="","",'Security'!E5) | G28: =IF('Security'!F5="","",'Security'!F5) | H28: =IF('Security'!G5="","",'Security'!G5) | I28: =IF('Security'!H5="","",'Security'!H5) | J28: =IF('Security'!I5="","",'Security'!I5) | ... N28: =IF('Security'!M5="","",'Security'!M5)
A29: =IF('Security'!A6="","",'Security'!A6) | B29: Security | C29: =IF('Security'!B6="","",'Security'!B6) | D29: =IF('Security'!C6="","",'Security'!C6) | E29: =IF('Security'!D6="","",'Security'!D6) | F29: =IF('Security'!E6="","",'Security'!E6) | G29: =IF('Security'!F6="","",'Security'!F6) | H29: =IF('Security'!G6="","",'Security'!G6) | I29: =IF('Security'!H6="","",'Security'!H6) | J29: =IF('Security'!I6="","",'Security'!I6) | ... N29: =IF('Security'!M6="","",'Security'!M6)
A30: =IF('Security'!A7="","",'Security'!A7) | B30: Security | C30: =IF('Security'!B7="","",'Security'!B7) | D30: =IF('Security'!C7="","",'Security'!C7) | E30: =IF('Security'!D7="","",'Security'!D7) | F30: =IF('Security'!E7="","",'Security'!E7) | G30: =IF('Security'!F7="","",'Security'!F7) | H30: =IF('Security'!G7="","",'Security'!G7) | I30: =IF('Security'!H7="","",'Security'!H7) | J30: =IF('Security'!I7="","",'Security'!I7) | ... N30: =IF('Security'!M7="","",'Security'!M7)
A31: =IF('Security'!A8="","",'Security'!A8) | B31: Security | C31: =IF('Security'!B8="","",'Security'!B8) | D31: =IF('Security'!C8="","",'Security'!C8) | E31: =IF('Security'!D8="","",'Security'!D8) | F31: =IF('Security'!E8="","",'Security'!E8) | G31: =IF('Security'!F8="","",'Security'!F8) | H31: =IF('Security'!G8="","",'Security'!G8) | I31: =IF('Security'!H8="","",'Security'!H8) | J31: =IF('Security'!I8="","",'Security'!I8) | ... N31: =IF('Security'!M8="","",'Security'!M8)
A32: =IF('Security'!A9="","",'Security'!A9) | B32: Security | C32: =IF('Security'!B9="","",'Security'!B9) | D32: =IF('Security'!C9="","",'Security'!C9) | E32: =IF('Security'!D9="","",'Security'!D9) | F32: =IF('Security'!E9="","",'Security'!E9) | G32: =IF('Security'!F9="","",'Security'!F9) | H32: =IF('Security'!G9="","",'Security'!G9) | I32: =IF('Security'!H9="","",'Security'!H9) | J32: =IF('Security'!I9="","",'Security'!I9) | ... N32: =IF('Security'!M9="","",'Security'!M9)
A33: =IF('Security'!A10="","",'Security'!A10) | B33: Security | C33: =IF('Security'!B10="","",'Security'!B10) | D33: =IF('Security'!C10="","",'Security'!C10) | E33: =IF('Security'!D10="","",'Security'!D10) | F33: =IF('Security'!E10="","",'Security'!E10) | G33: =IF('Security'!F10="","",'Security'!F10) | H33: =IF('Security'!G10="","",'Security'!G10) | I33: =IF('Security'!H10="","",'Security'!H10) | J33: =IF('Security'!I10="","",'Security'!I10) | ... N33: =IF('Security'!M10="","",'Security'!M10)
A34: =IF('Security'!A11="","",'Security'!A11) | B34: Security | C34: =IF('Security'!B11="","",'Security'!B11) | D34: =IF('Security'!C11="","",'Security'!C11) | E34: =IF('Security'!D11="","",'Security'!D11) | F34: =IF('Security'!E11="","",'Security'!E11) | G34: =IF('Security'!F11="","",'Security'!F11) | H34: =IF('Security'!G11="","",'Security'!G11) | I34: =IF('Security'!H11="","",'Security'!H11) | J34: =IF('Security'!I11="","",'Security'!I11) | ... N34: =IF('Security'!M11="","",'Security'!M11)
A35: =IF('Security'!A12="","",'Security'!A12) | B35: Security | C35: =IF('Security'!B12="","",'Security'!B12) | D35: =IF('Security'!C12="","",'Security'!C12) | E35: =IF('Security'!D12="","",'Security'!D12) | F35: =IF('Security'!E12="","",'Security'!E12) | G35: =IF('Security'!F12="","",'Security'!F12) | H35: =IF('Security'!G12="","",'Security'!G12) | I35: =IF('Security'!H12="","",'Security'!H12) | J35: =IF('Security'!I12="","",'Security'!I12) | ... N35: =IF('Security'!M12="","",'Security'!M12)
A36: =IF('Security'!A13="","",'Security'!A13) | B36: Security | C36: =IF('Security'!B13="","",'Security'!B13) | D36: =IF('Security'!C13="","",'Security'!C13) | E36: =IF('Security'!D13="","",'Security'!D13) | F36: =IF('Security'!E13="","",'Security'!E13) | G36: =IF('Security'!F13="","",'Security'!F13) | H36: =IF('Security'!G13="","",'Security'!G13) | I36: =IF('Security'!H13="","",'Security'!H13) | J36: =IF('Security'!I13="","",'Security'!I13) | ... N36: =IF('Security'!M13="","",'Security'!M13)
A37: =IF('Security'!A14="","",'Security'!A14) | B37: Security | C37: =IF('Security'!B14="","",'Security'!B14) | D37: =IF('Security'!C14="","",'Security'!C14) | E37: =IF('Security'!D14="","",'Security'!D14) | F37: =IF('Security'!E14="","",'Security'!E14) | G37: =IF('Security'!F14="","",'Security'!F14) | H37: =IF('Security'!G14="","",'Security'!G14) | I37: =IF('Security'!H14="","",'Security'!H14) | J37: =IF('Security'!I14="","",'Security'!I14) | ... N37: =IF('Security'!M14="","",'Security'!M14)
... A41: =IF('Security'!A18="","",'Security'!A18) | B41: Security | C41: =IF('Security'!B18="","",'Security'!B18) | D41: =IF('Security'!C18="","",'Security'!C18) | E41: =IF('Security'!D18="","",'Security'!D18) | F41: =IF('Security'!E18="","",'Security'!E18) | G41: =IF('Security'!F18="","",'Security'!F18) | H41: =IF('Security'!G18="","",'Security'!G18) | I41: =IF('Security'!H18="","",'Security'!H18) | J41: =IF('Security'!I18="","",'Security'!I18) | ... N41: =IF('Security'!M18="","",'Security'!M18)
A42: =IF('Compute'!A3="","",'Compute'!A3) | B42: Compute | C42: =IF('Compute'!B3="","",'Compute'!B3) | D42: =IF('Compute'!C3="","",'Compute'!C3) | E42: =IF('Compute'!D3="","",'Compute'!D3) | F42: =IF('Compute'!E3="","",'Compute'!E3) | G42: =IF('Compute'!F3="","",'Compute'!F3) | H42: =IF('Compute'!G3="","",'Compute'!G3) | I42: =IF('Compute'!H3="","",'Compute'!H3) | J42: =IF('Compute'!I3="","",'Compute'!I3) | ... N42: =IF('Compute'!M3="","",'Compute'!M3)
A43: =IF('Compute'!A4="","",'Compute'!A4) | B43: Compute | C43: =IF('Compute'!B4="","",'Compute'!B4) | D43: =IF('Compute'!C4="","",'Compute'!C4) | E43: =IF('Compute'!D4="","",'Compute'!D4) | F43: =IF('Compute'!E4="","",'Compute'!E4) | G43: =IF('Compute'!F4="","",'Compute'!F4) | H43: =IF('Compute'!G4="","",'Compute'!G4) | I43: =IF('Compute'!H4="","",'Compute'!H4) | J43: =IF('Compute'!I4="","",'Compute'!I4) | ... N43: =IF('Compute'!M4="","",'Compute'!M4)
A44: =IF('Compute'!A5="","",'Compute'!A5) | B44: Compute | C44: =IF('Compute'!B5="","",'Compute'!B5) | D44: =IF('Compute'!C5="","",'Compute'!C5) | E44: =IF('Compute'!D5="","",'Compute'!D5) | F44: =IF('Compute'!E5="","",'Compute'!E5) | G44: =IF('Compute'!F5="","",'Compute'!F5) | H44: =IF('Compute'!G5="","",'Compute'!G5) | I44: =IF('Compute'!H5="","",'Compute'!H5) | J44: =IF('Compute'!I5="","",'Compute'!I5) | ... N44: =IF('Compute'!M5="","",'Compute'!M5)
A45: =IF('Compute'!A6="","",'Compute'!A6) | B45: Compute | C45: =IF('Compute'!B6="","",'Compute'!B6) | D45: =IF('Compute'!C6="","",'Compute'!C6) | E45: =IF('Compute'!D6="","",'Compute'!D6) | F45: =IF('Compute'!E6="","",'Compute'!E6) | G45: =IF('Compute'!F6="","",'Compute'!F6) | H45: =IF('Compute'!G6="","",'Compute'!G6) | I45: =IF('Compute'!H6="","",'Compute'!H6) | J45: =IF('Compute'!I6="","",'Compute'!I6) | ... N45: =IF('Compute'!M6="","",'Compute'!M6)
A46: =IF('Compute'!A7="","",'Compute'!A7) | B46: Compute | C46: =IF('Compute'!B7="","",'Compute'!B7) | D46: =IF('Compute'!C7="","",'Compute'!C7) | E46: =IF('Compute'!D7="","",'Compute'!D7) | F46: =IF('Compute'!E7="","",'Compute'!E7) | G46: =IF('Compute'!F7="","",'Compute'!F7) | H46: =IF('Compute'!G7="","",'Compute'!G7) | I46: =IF('Compute'!H7="","",'Compute'!H7) | J46: =IF('Compute'!I7="","",'Compute'!I7) | ... N46: =IF('Compute'!M7="","",'Compute'!M7)
A47: =IF('Compute'!A8="","",'Compute'!A8) | B47: Compute | C47: =IF('Compute'!B8="","",'Compute'!B8) | D47: =IF('Compute'!C8="","",'Compute'!C8) | E47: =IF('Compute'!D8="","",'Compute'!D8) | F47: =IF('Compute'!E8="","",'Compute'!E8) | G47: =IF('Compute'!F8="","",'Compute'!F8) | H47: =IF('Compute'!G8="","",'Compute'!G8) | I47: =IF('Compute'!H8="","",'Compute'!H8) | J47: =IF('Compute'!I8="","",'Compute'!I8) | ... N47: =IF('Compute'!M8="","",'Compute'!M8)
A48: =IF('Compute'!A9="","",'Compute'!A9) | B48: Compute | C48: =IF('Compute'!B9="","",'Compute'!B9) | D48: =IF('Compute'!C9="","",'Compute'!C9) | E48: =IF('Compute'!D9="","",'Compute'!D9) | F48: =IF('Compute'!E9="","",'Compute'!E9) | G48: =IF('Compute'!F9="","",'Compute'!F9) | H48: =IF('Compute'!G9="","",'Compute'!G9) | I48: =IF('Compute'!H9="","",'Compute'!H9) | J48: =IF('Compute'!I9="","",'Compute'!I9) | ... N48: =IF('Compute'!M9="","",'Compute'!M9)
A49: =IF('Compute'!A10="","",'Compute'!A10) | B49: Compute | C49: =IF('Compute'!B10="","",'Compute'!B10) | D49: =IF('Compute'!C10="","",'Compute'!C10) | E49: =IF('Compute'!D10="","",'Compute'!D10) | F49: =IF('Compute'!E10="","",'Compute'!E10) | G49: =IF('Compute'!F10="","",'Compute'!F10) | H49: =IF('Compute'!G10="","",'Compute'!G10) | I49: =IF('Compute'!H10="","",'Compute'!H10) | J49: =IF('Compute'!I10="","",'Compute'!I10) | ... N49: =IF('Compute'!M10="","",'Compute'!M10)
A50: =IF('Compute'!A11="","",'Compute'!A11) | B50: Compute | C50: =IF('Compute'!B11="","",'Compute'!B11) | D50: =IF('Compute'!C11="","",'Compute'!C11) | E50: =IF('Compute'!D11="","",'Compute'!D11) | F50: =IF('Compute'!E11="","",'Compute'!E11) | G50: =IF('Compute'!F11="","",'Compute'!F11) | H50: =IF('Compute'!G11="","",'Compute'!G11) | I50: =IF('Compute'!H11="","",'Compute'!H11) | J50: =IF('Compute'!I11="","",'Compute'!I11) | ... N50: =IF('Compute'!M11="","",'Compute'!M11)
A51: =IF('Compute'!A12="","",'Compute'!A12) | B51: Compute | C51: =IF('Compute'!B12="","",'Compute'!B12) | D51: =IF('Compute'!C12="","",'Compute'!C12) | E51: =IF('Compute'!D12="","",'Compute'!D12) | F51: =IF('Compute'!E12="","",'Compute'!E12) | G51: =IF('Compute'!F12="","",'Compute'!F12) | H51: =IF('Compute'!G12="","",'Compute'!G12) | I51: =IF('Compute'!H12="","",'Compute'!H12) | J51: =IF('Compute'!I12="","",'Compute'!I12) | ... N51: =IF('Compute'!M12="","",'Compute'!M12)
A52: =IF('Compute'!A13="","",'Compute'!A13) | B52: Compute | C52: =IF('Compute'!B13="","",'Compute'!B13) | D52: =IF('Compute'!C13="","",'Compute'!C13) | E52: =IF('Compute'!D13="","",'Compute'!D13) | F52: =IF('Compute'!E13="","",'Compute'!E13) | G52: =IF('Compute'!F13="","",'Compute'!F13) | H52: =IF('Compute'!G13="","",'Compute'!G13) | I52: =IF('Compute'!H13="","",'Compute'!H13) | J52: =IF('Compute'!I13="","",'Compute'!I13) | ... N52: =IF('Compute'!M13="","",'Compute'!M13)
A53: =IF('Compute'!A14="","",'Compute'!A14) | B53: Compute | C53: =IF('Compute'!B14="","",'Compute'!B14) | D53: =IF('Compute'!C14="","",'Compute'!C14) | E53: =IF('Compute'!D14="","",'Compute'!D14) | F53: =IF('Compute'!E14="","",'Compute'!E14) | G53: =IF('Compute'!F14="","",'Compute'!F14) | H53: =IF('Compute'!G14="","",'Compute'!G14) | I53: =IF('Compute'!H14="","",'Compute'!H14) | J53: =IF('Compute'!I14="","",'Compute'!I14) | ... N53: =IF('Compute'!M14="","",'Compute'!M14)
... A58: =IF('Compute'!A19="","",'Compute'!A19) | B58: Compute | C58: =IF('Compute'!B19="","",'Compute'!B19) | D58: =IF('Compute'!C19="","",'Compute'!C19) | E58: =IF('Compute'!D19="","",'Compute'!D19) | F58: =IF('Compute'!E19="","",'Compute'!E19) | G58: =IF('Compute'!F19="","",'Compute'!F19) | H58: =IF('Compute'!G19="","",'Compute'!G19) | I58: =IF('Compute'!H19="","",'Compute'!H19) | J58: =IF('Compute'!I19="","",'Compute'!I19) | ... N58: =IF('Compute'!M19="","",'Compute'!M19)
A59: =IF('Storage'!A3="","",'Storage'!A3) | B59: Storage | C59: =IF('Storage'!B3="","",'Storage'!B3) | D59: =IF('Storage'!C3="","",'Storage'!C3) | E59: =IF('Storage'!D3="","",'Storage'!D3) | F59: =IF('Storage'!E3="","",'Storage'!E3) | G59: =IF('Storage'!F3="","",'Storage'!F3) | H59: =IF('Storage'!G3="","",'Storage'!G3) | I59: =IF('Storage'!H3="","",'Storage'!H3) | J59: =IF('Storage'!I3="","",'Storage'!I3) | ... N59: =IF('Storage'!M3="","",'Storage'!M3)
A60: =IF('Storage'!A4="","",'Storage'!A4) | B60: Storage | C60: =IF('Storage'!B4="","",'Storage'!B4) | D60: =IF('Storage'!C4="","",'Storage'!C4) | E60: =IF('Storage'!D4="","",'Storage'!D4) | F60: =IF('Storage'!E4="","",'Storage'!E4) | G60: =IF('Storage'!F4="","",'Storage'!F4) | H60: =IF('Storage'!G4="","",'Storage'!G4) | I60: =IF('Storage'!H4="","",'Storage'!H4) | J60: =IF('Storage'!I4="","",'Storage'!I4) | ... N60: =IF('Storage'!M4="","",'Storage'!M4)
A61: =IF('Storage'!A5="","",'Storage'!A5) | B61: Storage | C61: =IF('Storage'!B5="","",'Storage'!B5) | D61: =IF('Storage'!C5="","",'Storage'!C5) | E61: =IF('Storage'!D5="","",'Storage'!D5) | F61: =IF('Storage'!E5="","",'Storage'!E5) | G61: =IF('Storage'!F5="","",'Storage'!F5) | H61: =IF('Storage'!G5="","",'Storage'!G5) | I61: =IF('Storage'!H5="","",'Storage'!H5) | J61: =IF('Storage'!I5="","",'Storage'!I5) | ... N61: =IF('Storage'!M5="","",'Storage'!M5)
A62: =IF('Storage'!A6="","",'Storage'!A6) | B62: Storage | C62: =IF('Storage'!B6="","",'Storage'!B6) | D62: =IF('Storage'!C6="","",'Storage'!C6) | E62: =IF('Storage'!D6="","",'Storage'!D6) | F62: =IF('Storage'!E6="","",'Storage'!E6) | G62: =IF('Storage'!F6="","",'Storage'!F6) | H62: =IF('Storage'!G6="","",'Storage'!G6) | I62: =IF('Storage'!H6="","",'Storage'!H6) | J62: =IF('Storage'!I6="","",'Storage'!I6) | ... N62: =IF('Storage'!M6="","",'Storage'!M6)
A63: =IF('Storage'!A7="","",'Storage'!A7) | B63: Storage | C63: =IF('Storage'!B7="","",'Storage'!B7) | D63: =IF('Storage'!C7="","",'Storage'!C7) | E63: =IF('Storage'!D7="","",'Storage'!D7) | F63: =IF('Storage'!E7="","",'Storage'!E7) | G63: =IF('Storage'!F7="","",'Storage'!F7) | H63: =IF('Storage'!G7="","",'Storage'!G7) | I63: =IF('Storage'!H7="","",'Storage'!H7) | J63: =IF('Storage'!I7="","",'Storage'!I7) | ... N63: =IF('Storage'!M7="","",'Storage'!M7)
A64: =IF('Storage'!A8="","",'Storage'!A8) | B64: Storage | C64: =IF('Storage'!B8="","",'Storage'!B8) | D64: =IF('Storage'!C8="","",'Storage'!C8) | E64: =IF('Storage'!D8="","",'Storage'!D8) | F64: =IF('Storage'!E8="","",'Storage'!E8) | G64: =IF('Storage'!F8="","",'Storage'!F8) | H64: =IF('Storage'!G8="","",'Storage'!G8) | I64: =IF('Storage'!H8="","",'Storage'!H8) | J64: =IF('Storage'!I8="","",'Storage'!I8) | ... N64: =IF('Storage'!M8="","",'Storage'!M8)
A65: =IF('Storage'!A9="","",'Storage'!A9) | B65: Storage | C65: =IF('Storage'!B9="","",'Storage'!B9) | D65: =IF('Storage'!C9="","",'Storage'!C9) | E65: =IF('Storage'!D9="","",'Storage'!D9) | F65: =IF('Storage'!E9="","",'Storage'!E9) | G65: =IF('Storage'!F9="","",'Storage'!F9) | H65: =IF('Storage'!G9="","",'Storage'!G9) | I65: =IF('Storage'!H9="","",'Storage'!H9) | J65: =IF('Storage'!I9="","",'Storage'!I9) | ... N65: =IF('Storage'!M9="","",'Storage'!M9)
A66: =IF('Storage'!A10="","",'Storage'!A10) | B66: Storage | C66: =IF('Storage'!B10="","",'Storage'!B10) | D66: =IF('Storage'!C10="","",'Storage'!C10) | E66: =IF('Storage'!D10="","",'Storage'!D10) | F66: =IF('Storage'!E10="","",'Storage'!E10) | G66: =IF('Storage'!F10="","",'Storage'!F10) | H66: =IF('Storage'!G10="","",'Storage'!G10) | I66: =IF('Storage'!H10="","",'Storage'!H10) | J66: =IF('Storage'!I10="","",'Storage'!I10) | ... N66: =IF('Storage'!M10="","",'Storage'!M10)
A67: =IF('Storage'!A11="","",'Storage'!A11) | B67: Storage | C67: =IF('Storage'!B11="","",'Storage'!B11) | D67: =IF('Storage'!C11="","",'Storage'!C11) | E67: =IF('Storage'!D11="","",'Storage'!D11) | F67: =IF('Storage'!E11="","",'Storage'!E11) | G67: =IF('Storage'!F11="","",'Storage'!F11) | H67: =IF('Storage'!G11="","",'Storage'!G11) | I67: =IF('Storage'!H11="","",'Storage'!H11) | J67: =IF('Storage'!I11="","",'Storage'!I11) | ... N67: =IF('Storage'!M11="","",'Storage'!M11)
A68: =IF('Database'!A3="","",'Database'!A3) | B68: Database | C68: =IF('Database'!B3="","",'Database'!B3) | D68: =IF('Database'!C3="","",'Database'!C3) | E68: =IF('Database'!D3="","",'Database'!D3) | F68: =IF('Database'!E3="","",'Database'!E3) | G68: =IF('Database'!F3="","",'Database'!F3) | H68: =IF('Database'!G3="","",'Database'!G3) | I68: =IF('Database'!H3="","",'Database'!H3) | J68: =IF('Database'!I3="","",'Database'!I3) | ... N68: =IF('Database'!M3="","",'Database'!M3)
A69: =IF('Database'!A4="","",'Database'!A4) | B69: Database | C69: =IF('Database'!B4="","",'Database'!B4) | D69: =IF('Database'!C4="","",'Database'!C4) | E69: =IF('Database'!D4="","",'Database'!D4) | F69: =IF('Database'!E4="","",'Database'!E4) | G69: =IF('Database'!F4="","",'Database'!F4) | H69: =IF('Database'!G4="","",'Database'!G4) | I69: =IF('Database'!H4="","",'Database'!H4) | J69: =IF('Database'!I4="","",'Database'!I4) | ... N69: =IF('Database'!M4="","",'Database'!M4)
A70: =IF('Database'!A5="","",'Database'!A5) | B70: Database | C70: =IF('Database'!B5="","",'Database'!B5) | D70: =IF('Database'!C5="","",'Database'!C5) | E70: =IF('Database'!D5="","",'Database'!D5) | F70: =IF('Database'!E5="","",'Database'!E5) | G70: =IF('Database'!F5="","",'Database'!F5) | H70: =IF('Database'!G5="","",'Database'!G5) | I70: =IF('Database'!H5="","",'Database'!H5) | J70: =IF('Database'!I5="","",'Database'!I5) | ... N70: =IF('Database'!M5="","",'Database'!M5)
A71: =IF('Database'!A6="","",'Database'!A6) | B71: Database | C71: =IF('Database'!B6="","",'Database'!B6) | D71: =IF('Database'!C6="","",'Database'!C6) | E71: =IF('Database'!D6="","",'Database'!D6) | F71: =IF('Database'!E6="","",'Database'!E6) | G71: =IF('Database'!F6="","",'Database'!F6) | H71: =IF('Database'!G6="","",'Database'!G6) | I71: =IF('Database'!H6="","",'Database'!H6) | J71: =IF('Database'!I6="","",'Database'!I6) | ... N71: =IF('Database'!M6="","",'Database'!M6)
A72: =IF('Database'!A7="","",'Database'!A7) | B72: Database | C72: =IF('Database'!B7="","",'Database'!B7) | D72: =IF('Database'!C7="","",'Database'!C7) | E72: =IF('Database'!D7="","",'Database'!D7) | F72: =IF('Database'!E7="","",'Database'!E7) | G72: =IF('Database'!F7="","",'Database'!F7) | H72: =IF('Database'!G7="","",'Database'!G7) | I72: =IF('Database'!H7="","",'Database'!H7) | J72: =IF('Database'!I7="","",'Database'!I7) | ... N72: =IF('Database'!M7="","",'Database'!M7)
A73: =IF('Database'!A8="","",'Database'!A8) | B73: Database | C73: =IF('Database'!B8="","",'Database'!B8) | D73: =IF('Database'!C8="","",'Database'!C8) | E73: =IF('Database'!D8="","",'Database'!D8) | F73: =IF('Database'!E8="","",'Database'!E8) | G73: =IF('Database'!F8="","",'Database'!F8) | H73: =IF('Database'!G8="","",'Database'!G8) | I73: =IF('Database'!H8="","",'Database'!H8) | J73: =IF('Database'!I8="","",'Database'!I8) | ... N73: =IF('Database'!M8="","",'Database'!M8)
A74: =IF('Database'!A9="","",'Database'!A9) | B74: Database | C74: =IF('Database'!B9="","",'Database'!B9) | D74: =IF('Database'!C9="","",'Database'!C9) | E74: =IF('Database'!D9="","",'Database'!D9) | F74: =IF('Database'!E9="","",'Database'!E9) | G74: =IF('Database'!F9="","",'Database'!F9) | H74: =IF('Database'!G9="","",'Database'!G9) | I74: =IF('Database'!H9="","",'Database'!H9) | J74: =IF('Database'!I9="","",'Database'!I9) | ... N74: =IF('Database'!M9="","",'Database'!M9)
A75: =IF('Database'!A10="","",'Database'!A10) | B75: Database | C75: =IF('Database'!B10="","",'Database'!B10) | D75: =IF('Database'!C10="","",'Database'!C10) | E75: =IF('Database'!D10="","",'Database'!D10) | F75: =IF('Database'!E10="","",'Database'!E10) | G75: =IF('Database'!F10="","",'Database'!F10) | H75: =IF('Database'!G10="","",'Database'!G10) | I75: =IF('Database'!H10="","",'Database'!H10) | J75: =IF('Database'!I10="","",'Database'!I10) | ... N75: =IF('Database'!M10="","",'Database'!M10)
A76: =IF('Database'!A11="","",'Database'!A11) | B76: Database | C76: =IF('Database'!B11="","",'Database'!B11) | D76: =IF('Database'!C11="","",'Database'!C11) | E76: =IF('Database'!D11="","",'Database'!D11) | F76: =IF('Database'!E11="","",'Database'!E11) | G76: =IF('Database'!F11="","",'Database'!F11) | H76: =IF('Database'!G11="","",'Database'!G11) | I76: =IF('Database'!H11="","",'Database'!H11) | J76: =IF('Database'!I11="","",'Database'!I11) | ... N76: =IF('Database'!M11="","",'Database'!M11)
A77: =IF('Database'!A12="","",'Database'!A12) | B77: Database | C77: =IF('Database'!B12="","",'Database'!B12) | D77: =IF('Database'!C12="","",'Database'!C12) | E77: =IF('Database'!D12="","",'Database'!D12) | F77: =IF('Database'!E12="","",'Database'!E12) | G77: =IF('Database'!F12="","",'Database'!F12) | H77: =IF('Database'!G12="","",'Database'!G12) | I77: =IF('Database'!H12="","",'Database'!H12) | J77: =IF('Database'!I12="","",'Database'!I12) | ... N77: =IF('Database'!M12="","",'Database'!M12)
A78: =IF('Application'!A3="","",'Application'!A3) | B78: Application | C78: =IF('Application'!B3="","",'Application'!B3) | D78: =IF('Application'!C3="","",'Application'!C3) | E78: =IF('Application'!D3="","",'Application'!D3) | F78: =IF('Application'!E3="","",'Application'!E3) | G78: =IF('Application'!F3="","",'Application'!F3) | H78: =IF('Application'!G3="","",'Application'!G3) | I78: =IF('Application'!H3="","",'Application'!H3) | J78: =IF('Application'!I3="","",'Application'!I3) | ... N78: =IF('Application'!M3="","",'Application'!M3)
A79: =IF('Application'!A4="","",'Application'!A4) | B79: Application | C79: =IF('Application'!B4="","",'Application'!B4) | D79: =IF('Application'!C4="","",'Application'!C4) | E79: =IF('Application'!D4="","",'Application'!D4) | F79: =IF('Application'!E4="","",'Application'!E4) | G79: =IF('Application'!F4="","",'Application'!F4) | H79: =IF('Application'!G4="","",'Application'!G4) | I79: =IF('Application'!H4="","",'Application'!H4) | J79: =IF('Application'!I4="","",'Application'!I4) | ... N79: =IF('Application'!M4="","",'Application'!M4)
A80: =IF('Application'!A5="","",'Application'!A5) | B80: Application | C80: =IF('Application'!B5="","",'Application'!B5) | D80: =IF('Application'!C5="","",'Application'!C5) | E80: =IF('Application'!D5="","",'Application'!D5) | F80: =IF('Application'!E5="","",'Application'!E5) | G80: =IF('Application'!F5="","",'Application'!F5) | H80: =IF('Application'!G5="","",'Application'!G5) | I80: =IF('Application'!H5="","",'Application'!H5) | J80: =IF('Application'!I5="","",'Application'!I5) | ... N80: =IF('Application'!M5="","",'Application'!M5)
A81: =IF('Application'!A6="","",'Application'!A6) | B81: Application | C81: =IF('Application'!B6="","",'Application'!B6) | D81: =IF('Application'!C6="","",'Application'!C6) | E81: =IF('Application'!D6="","",'Application'!D6) | F81: =IF('Application'!E6="","",'Application'!E6) | G81: =IF('Application'!F6="","",'Application'!F6) | H81: =IF('Application'!G6="","",'Application'!G6) | I81: =IF('Application'!H6="","",'Application'!H6) | J81: =IF('Application'!I6="","",'Application'!I6) | ... N81: =IF('Application'!M6="","",'Application'!M6)
A82: =IF('Application'!A7="","",'Application'!A7) | B82: Application | C82: =IF('Application'!B7="","",'Application'!B7) | D82: =IF('Application'!C7="","",'Application'!C7) | E82: =IF('Application'!D7="","",'Application'!D7) | F82: =IF('Application'!E7="","",'Application'!E7) | G82: =IF('Application'!F7="","",'Application'!F7) | H82: =IF('Application'!G7="","",'Application'!G7) | I82: =IF('Application'!H7="","",'Application'!H7) | J82: =IF('Application'!I7="","",'Application'!I7) | ... N82: =IF('Application'!M7="","",'Application'!M7)
A83: =IF('Application'!A8="","",'Application'!A8) | B83: Application | C83: =IF('Application'!B8="","",'Application'!B8) | D83: =IF('Application'!C8="","",'Application'!C8) | E83: =IF('Application'!D8="","",'Application'!D8) | F83: =IF('Application'!E8="","",'Application'!E8) | G83: =IF('Application'!F8="","",'Application'!F8) | H83: =IF('Application'!G8="","",'Application'!G8) | I83: =IF('Application'!H8="","",'Application'!H8) | J83: =IF('Application'!I8="","",'Application'!I8) | ... N83: =IF('Application'!M8="","",'Application'!M8)
A84: =IF('Application'!A9="","",'Application'!A9) | B84: Application | C84: =IF('Application'!B9="","",'Application'!B9) | D84: =IF('Application'!C9="","",'Application'!C9) | E84: =IF('Application'!D9="","",'Application'!D9) | F84: =IF('Application'!E9="","",'Application'!E9) | G84: =IF('Application'!F9="","",'Application'!F9) | H84: =IF('Application'!G9="","",'Application'!G9) | I84: =IF('Application'!H9="","",'Application'!H9) | J84: =IF('Application'!I9="","",'Application'!I9) | ... N84: =IF('Application'!M9="","",'Application'!M9)
A85: =IF('Application'!A10="","",'Application'!A10) | B85: Application | C85: =IF('Application'!B10="","",'Application'!B10) | D85: =IF('Application'!C10="","",'Application'!C10) | E85: =IF('Application'!D10="","",'Application'!D10) | F85: =IF('Application'!E10="","",'Application'!E10) | G85: =IF('Application'!F10="","",'Application'!F10) | H85: =IF('Application'!G10="","",'Application'!G10) | I85: =IF('Application'!H10="","",'Application'!H10) | J85: =IF('Application'!I10="","",'Application'!I10) | ... N85: =IF('Application'!M10="","",'Application'!M10)
A86: =IF('Application'!A11="","",'Application'!A11) | B86: Application | C86: =IF('Application'!B11="","",'Application'!B11) | D86: =IF('Application'!C11="","",'Application'!C11) | E86: =IF('Application'!D11="","",'Application'!D11) | F86: =IF('Application'!E11="","",'Application'!E11) | G86: =IF('Application'!F11="","",'Application'!F11) | H86: =IF('Application'!G11="","",'Application'!G11) | I86: =IF('Application'!H11="","",'Application'!H11) | J86: =IF('Application'!I11="","",'Application'!I11) | ... N86: =IF('Application'!M11="","",'Application'!M11)
A87: =IF('Application'!A12="","",'Application'!A12) | B87: Application | C87: =IF('Application'!B12="","",'Application'!B12) | D87: =IF('Application'!C12="","",'Application'!C12) | E87: =IF('Application'!D12="","",'Application'!D12) | F87: =IF('Application'!E12="","",'Application'!E12) | G87: =IF('Application'!F12="","",'Application'!F12) | H87: =IF('Application'!G12="","",'Application'!G12) | I87: =IF('Application'!H12="","",'Application'!H12) | J87: =IF('Application'!I12="","",'Application'!I12) | ... N87: =IF('Application'!M12="","",'Application'!M12)
A88: =IF('Application'!A13="","",'Application'!A13) | B88: Application | C88: =IF('Application'!B13="","",'Application'!B13) | D88: =IF('Application'!C13="","",'Application'!C13) | E88: =IF('Application'!D13="","",'Application'!D13) | F88: =IF('Application'!E13="","",'Application'!E13) | G88: =IF('Application'!F13="","",'Application'!F13) | H88: =IF('Application'!G13="","",'Application'!G13) | I88: =IF('Application'!H13="","",'Application'!H13) | J88: =IF('Application'!I13="","",'Application'!I13) | ... N88: =IF('Application'!M13="","",'Application'!M13)
A89: =IF('Monitoring'!A3="","",'Monitoring'!A3) | B89: Monitoring | C89: =IF('Monitoring'!B3="","",'Monitoring'!B3) | D89: =IF('Monitoring'!C3="","",'Monitoring'!C3) | E89: =IF('Monitoring'!D3="","",'Monitoring'!D3) | F89: =IF('Monitoring'!E3="","",'Monitoring'!E3) | G89: =IF('Monitoring'!F3="","",'Monitoring'!F3) | H89: =IF('Monitoring'!G3="","",'Monitoring'!G3) | I89: =IF('Monitoring'!H3="","",'Monitoring'!H3) | J89: =IF('Monitoring'!I3="","",'Monitoring'!I3) | ... N89: =IF('Monitoring'!M3="","",'Monitoring'!M3)
A90: =IF('Monitoring'!A4="","",'Monitoring'!A4) | B90: Monitoring | C90: =IF('Monitoring'!B4="","",'Monitoring'!B4) | D90: =IF('Monitoring'!C4="","",'Monitoring'!C4) | E90: =IF('Monitoring'!D4="","",'Monitoring'!D4) | F90: =IF('Monitoring'!E4="","",'Monitoring'!E4) | G90: =IF('Monitoring'!F4="","",'Monitoring'!F4) | H90: =IF('Monitoring'!G4="","",'Monitoring'!G4) | I90: =IF('Monitoring'!H4="","",'Monitoring'!H4) | J90: =IF('Monitoring'!I4="","",'Monitoring'!I4) | ... N90: =IF('Monitoring'!M4="","",'Monitoring'!M4)
A91: =IF('Monitoring'!A5="","",'Monitoring'!A5) | B91: Monitoring | C91: =IF('Monitoring'!B5="","",'Monitoring'!B5) | D91: =IF('Monitoring'!C5="","",'Monitoring'!C5) | E91: =IF('Monitoring'!D5="","",'Monitoring'!D5) | F91: =IF('Monitoring'!E5="","",'Monitoring'!E5) | G91: =IF('Monitoring'!F5="","",'Monitoring'!F5) | H91: =IF('Monitoring'!G5="","",'Monitoring'!G5) | I91: =IF('Monitoring'!H5="","",'Monitoring'!H5) | J91: =IF('Monitoring'!I5="","",'Monitoring'!I5) | ... N91: =IF('Monitoring'!M5="","",'Monitoring'!M5)
A92: =IF('Monitoring'!A6="","",'Monitoring'!A6) | B92: Monitoring | C92: =IF('Monitoring'!B6="","",'Monitoring'!B6) | D92: =IF('Monitoring'!C6="","",'Monitoring'!C6) | E92: =IF('Monitoring'!D6="","",'Monitoring'!D6) | F92: =IF('Monitoring'!E6="","",'Monitoring'!E6) | G92: =IF('Monitoring'!F6="","",'Monitoring'!F6) | H92: =IF('Monitoring'!G6="","",'Monitoring'!G6) | I92: =IF('Monitoring'!H6="","",'Monitoring'!H6) | J92: =IF('Monitoring'!I6="","",'Monitoring'!I6) | ... N92: =IF('Monitoring'!M6="","",'Monitoring'!M6)
A93: =IF('Monitoring'!A7="","",'Monitoring'!A7) | B93: Monitoring | C93: =IF('Monitoring'!B7="","",'Monitoring'!B7) | D93: =IF('Monitoring'!C7="","",'Monitoring'!C7) | E93: =IF('Monitoring'!D7="","",'Monitoring'!D7) | F93: =IF('Monitoring'!E7="","",'Monitoring'!E7) | G93: =IF('Monitoring'!F7="","",'Monitoring'!F7) | H93: =IF('Monitoring'!G7="","",'Monitoring'!G7) | I93: =IF('Monitoring'!H7="","",'Monitoring'!H7) | J93: =IF('Monitoring'!I7="","",'Monitoring'!I7) | ... N93: =IF('Monitoring'!M7="","",'Monitoring'!M7)
A94: =IF('Monitoring'!A8="","",'Monitoring'!A8) | B94: Monitoring | C94: =IF('Monitoring'!B8="","",'Monitoring'!B8) | D94: =IF('Monitoring'!C8="","",'Monitoring'!C8) | E94: =IF('Monitoring'!D8="","",'Monitoring'!D8) | F94: =IF('Monitoring'!E8="","",'Monitoring'!E8) | G94: =IF('Monitoring'!F8="","",'Monitoring'!F8) | H94: =IF('Monitoring'!G8="","",'Monitoring'!G8) | I94: =IF('Monitoring'!H8="","",'Monitoring'!H8) | J94: =IF('Monitoring'!I8="","",'Monitoring'!I8) | ... N94: =IF('Monitoring'!M8="","",'Monitoring'!M8)
A95: =IF('Monitoring'!A9="","",'Monitoring'!A9) | B95: Monitoring | C95: =IF('Monitoring'!B9="","",'Monitoring'!B9) | D95: =IF('Monitoring'!C9="","",'Monitoring'!C9) | E95: =IF('Monitoring'!D9="","",'Monitoring'!D9) | F95: =IF('Monitoring'!E9="","",'Monitoring'!E9) | G95: =IF('Monitoring'!F9="","",'Monitoring'!F9) | H95: =IF('Monitoring'!G9="","",'Monitoring'!G9) | I95: =IF('Monitoring'!H9="","",'Monitoring'!H9) | J95: =IF('Monitoring'!I9="","",'Monitoring'!I9) | ... N95: =IF('Monitoring'!M9="","",'Monitoring'!M9)
A96: =IF('Monitoring'!A10="","",'Monitoring'!A10) | B96: Monitoring | C96: =IF('Monitoring'!B10="","",'Monitoring'!B10) | D96: =IF('Monitoring'!C10="","",'Monitoring'!C10) | E96: =IF('Monitoring'!D10="","",'Monitoring'!D10) | F96: =IF('Monitoring'!E10="","",'Monitoring'!E10) | G96: =IF('Monitoring'!F10="","",'Monitoring'!F10) | H96: =IF('Monitoring'!G10="","",'Monitoring'!G10) | I96: =IF('Monitoring'!H10="","",'Monitoring'!H10) | J96: =IF('Monitoring'!I10="","",'Monitoring'!I10) | ... N96: =IF('Monitoring'!M10="","",'Monitoring'!M10)
A97: =IF('Monitoring'!A11="","",'Monitoring'!A11) | B97: Monitoring | C97: =IF('Monitoring'!B11="","",'Monitoring'!B11) | D97: =IF('Monitoring'!C11="","",'Monitoring'!C11) | E97: =IF('Monitoring'!D11="","",'Monitoring'!D11) | F97: =IF('Monitoring'!E11="","",'Monitoring'!E11) | G97: =IF('Monitoring'!F11="","",'Monitoring'!F11) | H97: =IF('Monitoring'!G11="","",'Monitoring'!G11) | I97: =IF('Monitoring'!H11="","",'Monitoring'!H11) | J97: =IF('Monitoring'!I11="","",'Monitoring'!I11) | ... N97: =IF('Monitoring'!M11="","",'Monitoring'!M11)
A98: =IF('Monitoring'!A12="","",'Monitoring'!A12) | B98: Monitoring | C98: =IF('Monitoring'!B12="","",'Monitoring'!B12) | D98: =IF('Monitoring'!C12="","",'Monitoring'!C12) | E98: =IF('Monitoring'!D12="","",'Monitoring'!D12) | F98: =IF('Monitoring'!E12="","",'Monitoring'!E12) | G98: =IF('Monitoring'!F12="","",'Monitoring'!F12) | H98: =IF('Monitoring'!G12="","",'Monitoring'!G12) | I98: =IF('Monitoring'!H12="","",'Monitoring'!H12) | J98: =IF('Monitoring'!I12="","",'Monitoring'!I12) | ... N98: =IF('Monitoring'!M12="","",'Monitoring'!M12)
A99: =IF('Monitoring'!A13="","",'Monitoring'!A13) | B99: Monitoring | C99: =IF('Monitoring'!B13="","",'Monitoring'!B13) | D99: =IF('Monitoring'!C13="","",'Monitoring'!C13) | E99: =IF('Monitoring'!D13="","",'Monitoring'!D13) | F99: =IF('Monitoring'!E13="","",'Monitoring'!E13) | G99: =IF('Monitoring'!F13="","",'Monitoring'!F13) | H99: =IF('Monitoring'!G13="","",'Monitoring'!G13) | I99: =IF('Monitoring'!H13="","",'Monitoring'!H13) | J99: =IF('Monitoring'!I13="","",'Monitoring'!I13) | ... N99: =IF('Monitoring'!M13="","",'Monitoring'!M13)
A100: =IF('Bedrock'!A3="","",'Bedrock'!A3) | B100: Bedrock | C100: =IF('Bedrock'!B3="","",'Bedrock'!B3) | D100: =IF('Bedrock'!C3="","",'Bedrock'!C3) | E100: =IF('Bedrock'!D3="","",'Bedrock'!D3) | F100: =IF('Bedrock'!E3="","",'Bedrock'!E3) | G100: =IF('Bedrock'!F3="","",'Bedrock'!F3) | H100: =IF('Bedrock'!G3="","",'Bedrock'!G3) | I100: =IF('Bedrock'!H3="","",'Bedrock'!H3) | J100: =IF('Bedrock'!I3="","",'Bedrock'!I3) | ... N100: =IF('Bedrock'!M3="","",'Bedrock'!M3)
A101: =IF('Bedrock'!A4="","",'Bedrock'!A4) | B101: Bedrock | C101: =IF('Bedrock'!B4="","",'Bedrock'!B4) | D101: =IF('Bedrock'!C4="","",'Bedrock'!C4) | E101: =IF('Bedrock'!D4="","",'Bedrock'!D4) | F101: =IF('Bedrock'!E4="","",'Bedrock'!E4) | G101: =IF('Bedrock'!F4="","",'Bedrock'!F4) | H101: =IF('Bedrock'!G4="","",'Bedrock'!G4) | I101: =IF('Bedrock'!H4="","",'Bedrock'!H4) | J101: =IF('Bedrock'!I4="","",'Bedrock'!I4) | ... N101: =IF('Bedrock'!M4="","",'Bedrock'!M4)
A102: =IF('Bedrock'!A5="","",'Bedrock'!A5) | B102: Bedrock | C102: =IF('Bedrock'!B5="","",'Bedrock'!B5) | D102: =IF('Bedrock'!C5="","",'Bedrock'!C5) | E102: =IF('Bedrock'!D5="","",'Bedrock'!D5) | F102: =IF('Bedrock'!E5="","",'Bedrock'!E5) | G102: =IF('Bedrock'!F5="","",'Bedrock'!F5) | H102: =IF('Bedrock'!G5="","",'Bedrock'!G5) | I102: =IF('Bedrock'!H5="","",'Bedrock'!H5) | J102: =IF('Bedrock'!I5="","",'Bedrock'!I5) | ... N102: =IF('Bedrock'!M5="","",'Bedrock'!M5)
A103: =IF('Bedrock'!A6="","",'Bedrock'!A6) | B103: Bedrock | C103: =IF('Bedrock'!B6="","",'Bedrock'!B6) | D103: =IF('Bedrock'!C6="","",'Bedrock'!C6) | E103: =IF('Bedrock'!D6="","",'Bedrock'!D6) | F103: =IF('Bedrock'!E6="","",'Bedrock'!E6) | G103: =IF('Bedrock'!F6="","",'Bedrock'!F6) | H103: =IF('Bedrock'!G6="","",'Bedrock'!G6) | I103: =IF('Bedrock'!H6="","",'Bedrock'!H6) | J103: =IF('Bedrock'!I6="","",'Bedrock'!I6) | ... N103: =IF('Bedrock'!M6="","",'Bedrock'!M6)
A104: =IF('Bedrock'!A7="","",'Bedrock'!A7) | B104: Bedrock | C104: =IF('Bedrock'!B7="","",'Bedrock'!B7) | D104: =IF('Bedrock'!C7="","",'Bedrock'!C7) | E104: =IF('Bedrock'!D7="","",'Bedrock'!D7) | F104: =IF('Bedrock'!E7="","",'Bedrock'!E7) | G104: =IF('Bedrock'!F7="","",'Bedrock'!F7) | H104: =IF('Bedrock'!G7="","",'Bedrock'!G7) | I104: =IF('Bedrock'!H7="","",'Bedrock'!H7) | J104: =IF('Bedrock'!I7="","",'Bedrock'!I7) | ... N104: =IF('Bedrock'!M7="","",'Bedrock'!M7)
A105: =IF('Bedrock'!A8="","",'Bedrock'!A8) | B105: Bedrock | C105: =IF('Bedrock'!B8="","",'Bedrock'!B8) | D105: =IF('Bedrock'!C8="","",'Bedrock'!C8) | E105: =IF('Bedrock'!D8="","",'Bedrock'!D8) | F105: =IF('Bedrock'!E8="","",'Bedrock'!E8) | G105: =IF('Bedrock'!F8="","",'Bedrock'!F8) | H105: =IF('Bedrock'!G8="","",'Bedrock'!G8) | I105: =IF('Bedrock'!H8="","",'Bedrock'!H8) | J105: =IF('Bedrock'!I8="","",'Bedrock'!I8) | ... N105: =IF('Bedrock'!M8="","",'Bedrock'!M8)
A106: =IF('Integration'!A3="","",'Integration'!A3) | B106: Integration | C106: =IF('Integration'!B3="","",'Integration'!B3) | D106: =IF('Integration'!C3="","",'Integration'!C3) | E106: =IF('Integration'!D3="","",'Integration'!D3) | F106: =IF('Integration'!E3="","",'Integration'!E3) | G106: =IF('Integration'!F3="","",'Integration'!F3) | H106: =IF('Integration'!G3="","",'Integration'!G3) | I106: =IF('Integration'!H3="","",'Integration'!H3) | J106: =IF('Integration'!I3="","",'Integration'!I3) | ... N106: =IF('Integration'!M3="","",'Integration'!M3)
A107: =IF('Integration'!A4="","",'Integration'!A4) | B107: Integration | C107: =IF('Integration'!B4="","",'Integration'!B4) | D107: =IF('Integration'!C4="","",'Integration'!C4) | E107: =IF('Integration'!D4="","",'Integration'!D4) | F107: =IF('Integration'!E4="","",'Integration'!E4) | G107: =IF('Integration'!F4="","",'Integration'!F4) | H107: =IF('Integration'!G4="","",'Integration'!G4) | I107: =IF('Integration'!H4="","",'Integration'!H4) | J107: =IF('Integration'!I4="","",'Integration'!I4) | ... N107: =IF('Integration'!M4="","",'Integration'!M4)
A108: =IF('Integration'!A5="","",'Integration'!A5) | B108: Integration | C108: =IF('Integration'!B5="","",'Integration'!B5) | D108: =IF('Integration'!C5="","",'Integration'!C5) | E108: =IF('Integration'!D5="","",'Integration'!D5) | F108: =IF('Integration'!E5="","",'Integration'!E5) | G108: =IF('Integration'!F5="","",'Integration'!F5) | H108: =IF('Integration'!G5="","",'Integration'!G5) | I108: =IF('Integration'!H5="","",'Integration'!H5) | J108: =IF('Integration'!I5="","",'Integration'!I5) | ... N108: =IF('Integration'!M5="","",'Integration'!M5)
A109: =IF('Integration'!A6="","",'Integration'!A6) | B109: Integration | C109: =IF('Integration'!B6="","",'Integration'!B6) | D109: =IF('Integration'!C6="","",'Integration'!C6) | E109: =IF('Integration'!D6="","",'Integration'!D6) | F109: =IF('Integration'!E6="","",'Integration'!E6) | G109: =IF('Integration'!F6="","",'Integration'!F6) | H109: =IF('Integration'!G6="","",'Integration'!G6) | I109: =IF('Integration'!H6="","",'Integration'!H6) | J109: =IF('Integration'!I6="","",'Integration'!I6) | ... N109: =IF('Integration'!M6="","",'Integration'!M6)
...

Sheet Project
A1: Project Parameters
A2: Parameter Name | B2: Production | C2: Test | D2: DR | E2: Description | F2: Required | G2: Data Type | H2: Validation Rules | I2: Security Level | J2: Owner Team | K2: Dependencies | L2: Notes | M2: Last Updated
A3: solution.name | B3: aws-agentic-presales | C3: aws-agentic-presales | D3: aws-agentic-presales | E3: Solution identifier used for resource naming and tagging across all environments | F3: Yes | G3: String | H3: lowercase alphanumeric hyphens only max 50 chars | I3: Public | J3: Cloud CoE | M3: 2025-06-01
A4: solution.region.primary | B4: us-west-2 | C4: us-west-2 | D4: us-west-2 | E4: Primary AWS deployment region; isolated from PREDICTif us-east-1 workloads per SOW | F4: Yes | G4: String | H4: Valid AWS region code | I4: Public | J4: Cloud CoE | L4: Single region per SOW scope; multi-region deferred to Phase 2 | M4: 2025-06-01
A5: solution.environment | B5: production | C5: dev | D5: production | E5: Deployment environment identifier used in resource naming pattern eofw-{env}-* | F5: Yes | G5: String | H5: production | dev | staging | I5: Public | J5: Cloud CoE | L5: DR mirrors production environment naming | M5: 2025-06-01
A6: solution.version | B6: 1.0.0 | C6: 1.0.0 | D6: 1.0.0 | E6: Current platform release version tracked in GitHub and used for CLI pip package versioning | F6: Yes | G6: String | H6: Semantic versioning X.Y.Z | I6: Public | J6: Cloud CoE | M6: 2025-06-01
A7: solution.account_id | B7: [aws-account-id] | C7: [aws-account-id] | D7: [aws-account-id] | E7: AWS account ID hosting the us-west-2 platform footprint | F7: Yes | G7: String | H7: 12-digit numeric | I7: Confidential | J7: Cloud CoE | L7: Dedicated account isolated from us-east-1 per SOW scope | M7: 2025-06-01
A8: solution.cost_center | B8: AMATRA-PRESALES-2026 | C8: AMATRA-PRESALES-2026 | D8: AMATRA-PRESALES-2026 | E8: Cost center tag applied to all AWS resources for billing attribution per SOC 2 CC9.1 | F8: Yes | G8: String | H8: Non-empty string | I8: Public | J8: Cloud CoE | L8: Required tag enforced by Terraform and AWS Config rules | M8: 2025-06-01
A9: solution.deadline | B9: 2026-04-30 | C9: 2026-04-30 | D9: 2026-04-30 | E9: Hard go-live deadline (end of April 2026) for executive demonstration to Sarah Lin (CRO) | F9: Yes | G9: String | H9: ISO 8601 date YYYY-MM-DD | I9: Public | J9: Cloud CoE | L9: Critical path gate; drives 12-week delivery schedule | M9: 2025-06-01

Sheet Networking
A1: Networking Parameters
A2: Parameter Name | B2: Production | C2: Test | D2: DR | E2: Description | F2: Required | G2: Data Type | H2: Validation Rules | I2: Security Level | J2: Owner Team | K2: Dependencies | L2: Notes | M2: Last Updated
A3: networking.vpc_cidr | B3: 10.0.0.0/16 | C3: 10.0.0.0/16 | D3: 10.0.0.0/16 | E3: VPC CIDR block for the us-west-2 platform footprint; isolated from us-east-1 | F3: Yes | G3: String | H3: Valid CIDR /16 or smaller | I3: Confidential | J3: Network Team | K3: solution.region.primary | M3: 2025-06-01
A4: networking.subnet_public_az1_cidr | B4: 10.0.1.0/24 | C4: 10.0.1.0/24 | D4: 10.0.1.0/24 | E4: Public subnet AZ1 (us-west-2a) for NAT Gateway only; no Lambda compute in public subnets | F4: Yes | G4: String | H4: Valid CIDR within VPC CIDR | I4: Confidential | J4: Network Team | K4: networking.vpc_cidr | M4: 2025-06-01
A5: networking.subnet_public_az2_cidr | B5: 10.0.2.0/24 | C5: 10.0.2.0/24 | D5: 10.0.2.0/24 | E5: Public subnet AZ2 (us-west-2b) for NAT Gateway only | F5: Yes | G5: String | H5: Valid CIDR within VPC CIDR | I5: Confidential | J5: Network Team | K5: networking.vpc_cidr | M5: 2025-06-01
A6: networking.subnet_private_az1_cidr | B6: 10.0.10.0/24 | C6: 10.0.10.0/24 | D6: 10.0.10.0/24 | E6: Private subnet AZ1 (us-west-2a) hosting all Lambda functions and agent orchestration | F6: Yes | G6: String | H6: Valid CIDR within VPC CIDR | I6: Confidential | J6: Network Team | K6: networking.vpc_cidr | M6: 2025-06-01
A7: networking.subnet_private_az2_cidr | B7: 10.0.11.0/24 | C7: 10.0.11.0/24 | D7: 10.0.11.0/24 | E7: Private subnet AZ2 (us-west-2b) hosting all Lambda functions and agent orchestration | F7: Yes | G7: String | H7: Valid CIDR within VPC CIDR | I7: Confidential | J7: Network Team | K7: networking.vpc_cidr | M7: 2025-06-01
A8: networking.subnet_db_az1_cidr | B8: 10.0.20.0/24 | C8: 10.0.20.0/24 | D8: 10.0.20.0/24 | E8: Database subnet AZ1 reserved for future RDS/ElastiCache; DynamoDB accessed via VPC Endpoint | F8: Yes | G8: String | H8: Valid CIDR within VPC CIDR | I8: Confidential | J8: Network Team | K8: networking.vpc_cidr | M8: 2025-06-01
A9: networking.subnet_db_az2_cidr | B9: 10.0.21.0/24 | C9: 10.0.21.0/24 | D9: 10.0.21.0/24 | E9: Database subnet AZ2 reserved for future RDS/ElastiCache | F9: Yes | G9: String | H9: Valid CIDR within VPC CIDR | I9: Confidential | J9: Network Team | K9: networking.vpc_cidr | M9: 2025-06-01
A10: networking.nat_gateway_count | B10: 1 | C10: 1 | D10: 1 | E10: NAT Gateways deployed in public subnets for Lambda outbound internet access | F10: Yes | G10: Integer | H10: 1-3 | I10: Public | J10: Network Team | K10: networking.vpc_cidr | L10: Single NAT in AZ1 for PoC; second AZ2 NAT recommended in Phase 2 for AZ resilience | M10: 2025-06-01
A11: networking.vpc_endpoint_s3 | B11: true | C11: true | D11: true | E11: Enable S3 Gateway VPC Endpoint to route Lambda-to-S3 traffic without public internet | F11: Yes | G11: Boolean | H11: true | false | I11: Public | J11: Network Team | K11: networking.vpc_cidr | L11: Required to keep artifact reads/writes off public internet | M11: 2025-06-01
A12: networking.vpc_endpoint_dynamodb | B12: true | C12: true | D12: true | E12: Enable DynamoDB Gateway VPC Endpoint to route Lambda-to-DynamoDB quota operations privately | F12: Yes | G12: Boolean | H12: true | false | I12: Public | J12: Network Team | K12: networking.vpc_cidr | L12: Required for quota enforcement latency target < 50ms P99 | M12: 2025-06-01
A13: networking.vpc_endpoint_secrets_manager | B13: true | C13: true | D13: true | E13: Enable Secrets Manager Interface VPC Endpoint for PAT retrieval without public internet traversal | F13: Yes | G13: Boolean | H13: true | false | I13: Public | J13: Network Team | K13: networking.vpc_cidr | L13: Required for secure runtime PAT retrieval by GitHub push Lambda | M13: 2025-06-01
A14: networking.vpc_endpoint_bedrock_runtime | B14: true | C14: true | D14: true | E14: Enable Bedrock Runtime Interface VPC Endpoint to route agent invocations privately | F14: Yes | G14: Boolean | H14: true | false | I14: Public | J14: Network Team | K14: networking.vpc_cidr | L14: Reduces latency and eliminates public internet exposure of model invocations | M14: 2025-06-01
A15: networking.apigw_endpoint | B15: https://[apigw-id].execute-api.us-west-2.amazonaws.com | C15: https://[apigw-id].execute-api.us-west-2.amazonaws.com | D15: https://[apigw-id].execute-api.us-west-2.amazonaws.com | E15: API Gateway HTTP API v2 regional endpoint base URL | F15: Yes | G15: String | H15: Valid HTTPS URL | I15: Confidential | J15: Network Team | K15: solution.region.primary | L15: HTTPS-only; HTTP rejected; 11 Lambda routes mounted under /api/v1/ | M15: 2025-06-01
A16: networking.apigw_throttle_rps_burst | B16: 1000 | C16: 100 | D16: 1000 | E16: API Gateway burst throttle limit in requests per second | F16: Yes | G16: Integer | H16: 1-10000 | I16: Public | J16: Network Team | K16: networking.apigw_endpoint | L16: Per-user quota enforced in DynamoDB in addition to API Gateway throttle | M16: 2025-06-01

Sheet Security
A1: Security Parameters
A2: Parameter Name | B2: Production | C2: Test | D2: DR | E2: Description | F2: Required | G2: Data Type | H2: Validation Rules | I2: Security Level | J2: Owner Team | K2: Dependencies | L2: Notes | M2: Last Updated
A3: security.cognito.user_pool_name | B3: eofw-prd-userpool | C3: eofw-dev-userpool | D3: eofw-prd-userpool | E3: Amazon Cognito User Pool name providing JWT authentication for all 11 API routes and CLI | F3: Yes | G3: String | H3: Non-empty string max 128 chars | I3: Confidential | J3: Security Team | K3: solution.region.primary | M3: 2025-06-01
A4: security.cognito.user_pool_id | B4: [cognito-user-pool-id] | C4: [cognito-user-pool-id] | D4: [cognito-user-pool-id] | E4: Cognito User Pool ID; referenced by API Gateway JWT authoriser and Lambda route handlers | F4: Yes | G4: String | H4: Format: {region}_{poolId} | I4: Secret | J4: Security Team | K4: security.cognito.user_pool_name | L4: Store in Secrets Manager; CTO sign-off required before provisioning in production | M4: 2025-06-01
A5: security.cognito.app_client_id | B5: [cognito-app-client-id] | C5: [cognito-app-client-id] | D5: [cognito-app-client-id] | E5: Cognito User Pool App Client ID used by the CLI for PKCE-based authorization code flow | F5: Yes | G5: String | H5: Alphanumeric | I5: Secret | J5: Security Team | K5: security.cognito.user_pool_id | L5: Store in Secrets Manager; never bake into CLI package or container image | M5: 2025-06-01
A6: security.cognito.access_token_expiry_seconds | B6: 3600 | C6: 3600 | D6: 3600 | E6: JWT access token expiry in seconds (1 hour); CLI auto-refreshes using stored refresh token | F6: Yes | G6: Integer | H6: 300-86400 | I6: Public | J6: Security Team | K6: security.cognito.user_pool_id | L6: SOC 2 CC6.1 control; short expiry limits blast radius of compromised token | M6: 2025-06-01
A7: security.cognito.refresh_token_expiry_days | B7: 30 | C7: 30 | D7: 30 | E7: Cognito refresh token validity in days per SOW Security & Compliance specification | F7: Yes | G7: Integer | H7: 1-3650 | I7: Public | J7: Security Team | K7: security.cognito.user_pool_id | L7: 30-day refresh token per SOW; CLI stores in ~/.eoframework/credentials | M7: 2025-06-01
A8: security.cognito.mfa_enabled | B8: true | C8: false | D8: true | E8: Require MFA for Admin role in production; standard Cognito MFA setting | F8: Yes | G8: Boolean | H8: true | false | I8: Public | J8: Security Team | K8: security.cognito.user_pool_id | L8: SOC 2 CC6.1 control; Admin role requires MFA; Consultant role exempt at PoC | M8: 2025-06-01
A9: security.cognito.cto_signoff_required | B9: true | C9: false | D9: true | E9: CTO approval gate required before provisioning production Cognito User Pool per SOW | F9: Yes | G9: Boolean | H9: true | false | I9: Public | J9: Security Team | K9: security.cognito.user_pool_id | L9: Critical path for Phase 1 milestone M3; must not slip beyond Week 3 | M9: 2025-06-01
A10: security.kms.s3_cmk_arn | B10: [kms-s3-cmk-arn] | C10: [kms-s3-cmk-arn] | D10: [kms-s3-cmk-arn] | E10: Customer-managed KMS key ARN for S3 artifact bucket SSE-KMS encryption at rest | F10: Yes | G10: String | H10: Valid KMS key ARN | I10: Secret | J10: Security Team | K10: storage.s3.artifact_bucket_name | L10: Stored in Secrets Manager; 90-day key rotation policy; key usage logged in CloudTrail | M10: 2025-06-01
A11: security.kms.rotation_days | B11: 90 | C11: 90 | D11: 90 | E11: KMS key rotation period in days applied to S3 CMK and Secrets Manager encryption keys | F11: Yes | G11: Integer | H11: 1-365 | I11: Public | J11: Security Team | K11: security.kms.s3_cmk_arn | M11: 2025-06-01
A12: security.iam.access_analyzer_enabled | B12: true | C12: true | D12: true | E12: Enable IAM Access Analyzer to continuously validate no overly permissive Lambda execution roles exist | F12: Yes | G12: Boolean | H12: true | false | I12: Public | J12: Security Team | L12: Required by SOW security design; no wildcard IAM actions permitted | M12: 2025-06-01
A13: security.guardduty_enabled | B13: true | C13: true | D13: true | E13: Enable AWS GuardDuty for threat detection in us-west-2 account; findings routed to Security Hub | F13: Yes | G13: Boolean | H13: true | false | I13: Public | J13: Security Team | K13: security.securityhub_enabled | M13: 2025-06-01
A14: security.securityhub_enabled | B14: true | C14: true | D14: true | E14: Enable AWS Security Hub aggregating GuardDuty / Config / Inspector findings for SOC 2 posture | F14: Yes | G14: Boolean | H14: true | false | I14: Public | J14: Security Team | K14: security.guardduty_enabled | L14: SOC 2 CC7.2 control; reviewed by Daniel Park quarterly | M14: 2025-06-01
A15: security.cloudtrail.management_events | B15: true | C15: true | D15: true | E15: Enable CloudTrail Management Events logging all AWS API calls in us-west-2 account | F15: Yes | G15: Boolean | H15: true | false | I15: Public | J15: Security Team | L15: SOC 2 CC8.1 control; logs stored in dedicated S3 bucket with Object Lock (WORM) | M15: 2025-06-01
A16: security.cloudtrail.s3_data_events | B16: true | C16: false | D16: true | E16: Enable CloudTrail S3 Data Events on artifact bucket for GetObject/PutObject audit trail | F16: Yes | G16: Boolean | H16: true | false | I16: Public | J16: Security Team | K16: storage.s3.artifact_bucket_name | L16: SOC 2 CC6.1 evidence; disabled in dev to reduce CloudTrail cost | M16: 2025-06-01
A17: security.cloudtrail.retention_days | B17: 365 | C17: 90 | D17: 365 | E17: CloudTrail log retention in days in dedicated S3 bucket with Object Lock | F17: Yes | G17: Integer | H17: 90-3650 | I17: Public | J17: Security Team | L17: 365 days required for SOC 2 evidence window | M17: 2025-06-01
A18: security.tls_minimum_version | B18: TLS1.2 | C18: TLS1.2 | D18: TLS1.2 | E18: Minimum TLS version enforced on API Gateway / Cognito / DynamoDB / S3 SDK endpoints | F18: Yes | G18: String | H18: TLS1.2 | TLS1.3 | I18: Public | J18: Security Team | L18: No HTTP endpoints; all requests rejected without TLS per SOW security design | M18: 2025-06-01

Sheet Compute
A1: Compute Parameters
A2: Parameter Name | B2: Production | C2: Test | D2: DR | E2: Description | F2: Required | G2: Data Type | H2: Validation Rules | I2: Security Level | J2: Owner Team | K2: Dependencies | L2: Notes | M2: Last Updated
A3: compute.lambda.api_handler.memory_mb | B3: 256 | C3: 256 | D3: 256 | E3: Memory allocation for non-generation API route handler Lambda functions (10 functions) | F3: Yes | G3: Integer | H3: 128-10240 | I3: Public | J3: Development | K3: solution.region.primary | M3: 2025-06-01
A4: compute.lambda.api_handler.timeout_seconds | B4: 30 | C4: 30 | D4: 30 | E4: Timeout for synchronous API route handlers; generation initiator uses separate config | F4: Yes | G4: Integer | H4: 1-900 | I4: Public | J4: Development | M4: 2025-06-01
A5: compute.lambda.generation_initiator.memory_mb | B5: 512 | C5: 512 | D5: 512 | E5: Memory for the Solution Generation Initiator Lambda that triggers the five-agent graph | F5: Yes | G5: Integer | H5: 128-10240 | I5: Public | J5: Development | K5: bedrock.agentcore.runtime_region | M5: 2025-06-01
A6: compute.lambda.generation_initiator.timeout_seconds | B6: 60 | C6: 60 | D6: 60 | E6: Timeout for the Solution Generation Initiator Lambda; returns 202 Accepted immediately | F6: Yes | G6: Integer | H6: 1-900 | I6: Public | J6: Development | K6: compute.lambda.generation_initiator.memory_mb | M6: 2025-06-01
A7: compute.lambda.agent_trigger.memory_mb | B7: 1024 | C7: 1024 | D7: 1024 | E7: Memory for the 5 agent orchestration trigger Lambdas running eof-tools container image | F7: Yes | G7: Integer | H7: 128-10240 | I7: Public | J7: Development | K7: compute.ecr.agent_image_uri | M7: 2025-06-01
A8: compute.lambda.agent_trigger.timeout_seconds | B8: 900 | C8: 900 | D8: 900 | E8: Maximum Lambda timeout applied to agent triggers to accommodate eof-tools conversion | F8: Yes | G8: Integer | H8: 1-900 | I8: Public | J8: Development | K8: compute.lambda.agent_trigger.memory_mb | L8: Must be ≤ Bedrock AgentCore Runtime invocation timeout | M8: 2025-06-01
A9: compute.lambda.cognito_trigger.memory_mb | B9: 256 | C9: 256 | D9: 256 | E9: Memory for the Cognito post-confirmation trigger Lambda that writes DynamoDB user profiles | F9: Yes | G9: Integer | H9: 128-10240 | I9: Public | J9: Development | K9: security.cognito.user_pool_id | M9: 2025-06-01
A10: compute.lambda.cognito_trigger.timeout_seconds | B10: 10 | C10: 10 | D10: 10 | E10: Timeout for the Cognito post-confirmation trigger; must complete before Cognito times out | F10: Yes | G10: Integer | H10: 1-900 | I10: Public | J10: Development | K10: compute.lambda.cognito_trigger.memory_mb | M10: 2025-06-01
A11: compute.lambda.github_push.memory_mb | B11: 256 | C11: 256 | D11: 256 | E11: Memory for the GitHub push Lambda that commits artifacts to the configured repository | F11: Yes | G11: Integer | H11: 128-10240 | I11: Public | J11: Development | K11: integration.github.secret_arn | M11: 2025-06-01
A12: compute.lambda.github_push.timeout_seconds | B12: 60 | C12: 60 | D12: 60 | E12: Timeout for GitHub push Lambda; accounts for Secrets Manager retrieval and GitHub API call | F12: Yes | G12: Integer | H12: 1-900 | I12: Public | J12: Development | K12: compute.lambda.github_push.memory_mb | M12: 2025-06-01
A13: compute.lambda.runtime | B13: python3.12 | C13: python3.12 | D13: python3.12 | E13: Python runtime version for all 17 Lambda functions | F13: Yes | G13: String | H13: Valid AWS Lambda runtime identifier | I13: Public | J13: Development | M13: 2025-06-01
A14: compute.lambda.architecture | B14: arm64 | C14: arm64 | D14: arm64 | E14: Lambda function CPU architecture; arm64 provides better price-performance for Python workloads | F14: Yes | G14: String | H14: x86_64 | arm64 | I14: Public | J14: Development | M14: 2025-06-01
A15: compute.lambda.total_function_count | B15: 17 | C15: 17 | D15: 17 | E15: Total Lambda functions: 11 API routes + 5 agent triggers + 1 Cognito post-confirmation | F15: Yes | G15: Integer | H15: 17 | I15: Public | J15: Development | M15: 2025-06-01
A16: compute.lambda.provisioned_concurrency_agent_triggers | B16: 0 | C16: 0 | D16: 0 | E16: Provisioned concurrency for agent triggers; set to 0 at launch; evaluate after Phase 3 load test | F16: Yes | G16: Integer | H16: 0-100 | I16: Public | J16: Development | K16: compute.lambda.agent_trigger.memory_mb | L16: Increase if P99 cold-start timeout observed in Phase 3 load test per risk register | M16: 2025-06-01
A17: compute.ecr.repository_name | B17: eofw-prd-ecr-agent-image | C17: eofw-dev-ecr-agent-image | D17: eofw-prd-ecr-agent-image | E17: ECR repository name for the eof-tools agent container image | F17: Yes | G17: String | H17: Valid ECR repo name | I17: Confidential | J17: DevOps | K17: solution.region.primary | M17: 2025-06-01
A18: compute.ecr.agent_image_uri | B18: [ecr-agent-image-uri] | C18: [ecr-agent-image-uri] | D18: [ecr-agent-image-uri] | E18: Full ECR URI including tag for the eof-tools Docker image baked with ~30 Python converter modules | F18: Yes | G18: String | H18: Valid ECR URI format: {account}.dkr.ecr.{region}.amazonaws.com/{repo}:{tag} | I18: Confidential | J18: DevOps | K18: compute.ecr.repository_name | L18: Image tag must be immutable; updated each sprint via CI/CD pipeline | M18: 2025-06-01
A19: compute.lambda.xray_tracing | B19: Active | C19: Active | D19: Active | E19: AWS X-Ray tracing mode for all 17 Lambda functions; enables distributed service maps | F19: Yes | G19: String | H19: Active | PassThrough | I19: Public | J19: Operations | M19: 2025-06-01

Sheet Storage
A1: Storage Parameters
A2: Parameter Name | B2: Production | C2: Test | D2: DR | E2: Description | F2: Required | G2: Data Type | H2: Validation Rules | I2: Security Level | J2: Owner Team | K2: Dependencies | L2: Notes | M2: Last Updated
A3: storage.s3.artifact_bucket_name | B3: [s3-artifact-bucket-name] | C3: [s3-artifact-bucket-name] | D3: [s3-artifact-bucket-name] | E3: S3 bucket for all generated artifacts: raw MD/CSV + converted DOCX/PPTX/XLSX + Terraform bundles | F3: Yes | G3: String | H3: Globally unique bucket name lowercase alphanumeric hyphens | I3: Confidential | J3: Operations | K3: solution.region.primary | L3: Versioning enabled; SSE-KMS encryption; public access block enabled | M3: 2025-06-01
A4: storage.s3.artifact_bucket_versioning | B4: Enabled | C4: Enabled | D4: Enabled | E4: S3 versioning on artifact bucket; retains previous object versions for 90 days | F4: Yes | G4: String | H4: Enabled | Suspended | I4: Public | J4: Operations | K4: storage.s3.artifact_bucket_name | L4: S3 versioning covers artifact history for RPO of 1 hour | M4: 2025-06-01
A5: storage.s3.artifact_standard_retention_days | B5: 365 | C5: 90 | D5: 365 | E5: S3 Standard storage retention in days before lifecycle transition to S3 Glacier | F5: Yes | G5: Integer | H5: 1-3650 | I5: Public | J5: Operations | K5: storage.s3.artifact_bucket_name | L5: Managed via S3 Lifecycle rules; transition to Glacier after 12 months in production | M5: 2025-06-01
A6: storage.s3.artifact_glacier_retention_days | B6: 730 | C6: 0 | D6: 730 | E6: S3 Glacier retention in days before expiry after transition from Standard storage | F6: Yes | G6: Integer | H6: 0-3650 | I6: Public | J6: Operations | K6: storage.s3.artifact_standard_retention_days | L6: 730 days = 24 months Glacier per SOW Data Architecture section | M6: 2025-06-01
A7: storage.s3.artifact_path_raw_presales | B7: {solution_id}/raw/pre-sales/ | C7: {solution_id}/raw/pre-sales/ | D7: {solution_id}/raw/pre-sales/ | E7: S3 key prefix for raw MD/CSV presales artifacts per structured path hierarchy | F7: Yes | G7: String | H7: Must include {solution_id} token | I7: Public | J7: Development | K7: storage.s3.artifact_bucket_name | M7: 2025-06-01
A8: storage.s3.artifact_path_raw_delivery | B8: {solution_id}/raw/delivery/ | C8: {solution_id}/raw/delivery/ | D8: {solution_id}/raw/delivery/ | E8: S3 key prefix for raw MD delivery artifacts per structured path hierarchy | F8: Yes | G8: String | H8: Must include {solution_id} token | I8: Public | J8: Development | K8: storage.s3.artifact_bucket_name | M8: 2025-06-01
A9: storage.s3.artifact_path_automation | B9: {solution_id}/automation/ | C9: {solution_id}/automation/ | D9: {solution_id}/automation/ | E9: S3 key prefix for the Terraform IaC automation bundle (12th artifact type) | F9: Yes | G9: String | H9: Must include {solution_id} token | I9: Public | J9: Development | K9: storage.s3.artifact_bucket_name | M9: 2025-06-01
A10: storage.s3.cloudtrail_bucket_name | B10: [s3-cloudtrail-bucket-name] | C10: [s3-cloudtrail-bucket-name] | D10: [s3-cloudtrail-bucket-name] | E10: Dedicated S3 bucket for CloudTrail logs; Object Lock (WORM) enabled to prevent tampering | F10: Yes | G10: String | H10: Globally unique bucket name lowercase alphanumeric hyphens | I10: Confidential | J10: Security Team | K10: security.cloudtrail.management_events | L10: Separate from artifact bucket; Object Lock enforces immutability per SOC 2 CC8.1 | M10: 2025-06-01
A11: storage.s3.guidance_bucket_name | B11: [s3-guidance-bucket-name] | C11: [s3-guidance-bucket-name] | D11: [s3-guidance-bucket-name] | E11: S3 bucket hosting EO Framework guidance files used by generation agents for artifact prompting | F11: Yes | G11: String | H11: Globally unique bucket name lowercase alphanumeric hyphens | I11: Confidential | J11: Operations | K11: solution.region.primary | L11: Vendor team requires read access from Week 1 per SOW assumption A13 | M11: 2025-06-01

Sheet Database
A1: Database Parameters
A2: Parameter Name | B2: Production | C2: Test | D2: DR | E2: Description | F2: Required | G2: Data Type | H2: Validation Rules | I2: Security Level | J2: Owner Team | K2: Dependencies | L2: Notes | M2: Last Updated
A3: database.users_table_name | B3: eofw-prd-tbl-users | C3: eofw-dev-tbl-users | D3: eofw-prd-tbl-users | E3: DynamoDB table storing Cognito user profiles written by post-confirmation trigger Lambda | F3: Yes | G3: String | H3: Alphanumeric hyphens max 255 chars | I3: Confidential | J3: Database Team | K3: solution.region.primary | M3: 2025-06-01
A4: database.solutions_table_name | B4: eofw-prd-tbl-solutions | C4: eofw-dev-tbl-solutions | D4: eofw-prd-tbl-solutions | E4: DynamoDB table storing solution state / artifact statuses / per-phase token usage (PK: solution_id) | F4: Yes | G4: String | H4: Alphanumeric hyphens max 255 chars | I4: Confidential | J4: Database Team | K4: solution.region.primary | M4: 2025-06-01
A5: database.quotas_table_name | B5: eofw-prd-tbl-quotas | C5: eofw-dev-tbl-quotas | D5: eofw-prd-tbl-quotas | E5: DynamoDB table for per-user and global atomic quota counters (PK: user_id or GLOBAL) | F5: Yes | G5: String | H5: Alphanumeric hyphens max 255 chars | I5: Confidential | J5: Database Team | K5: solution.region.primary | L5: Atomic conditional writes prevent quota bypass; validated in Phase 3 security testing | M5: 2025-06-01
A6: database.audit_events_table_name | B6: eofw-prd-tbl-audit-events | C6: eofw-dev-tbl-audit-events | D6: eofw-prd-tbl-audit-events | E6: DynamoDB immutable audit log table capturing all API calls per SOC 2 CC7 requirements | F6: Yes | G6: String | H6: Alphanumeric hyphens max 255 chars | I6: Confidential | J6: Database Team | K6: solution.region.primary | M6: 2025-06-01
A7: database.billing_mode | B7: PAY_PER_REQUEST | C7: PAY_PER_REQUEST | D7: PAY_PER_REQUEST | E7: DynamoDB billing mode for all four tables; On-Demand auto-scales to any throughput | F7: Yes | G7: String | H7: PROVISIONED | PAY_PER_REQUEST | I7: Public | J7: Database Team | L7: Review reserved capacity at scale post-PoC per cost model | M7: 2025-06-01
A8: database.pitr_enabled | B8: true | C8: false | D8: true | E8: Enable DynamoDB Point-In-Time Recovery on all four tables; required for 4-hour RTO target | F8: Yes | G8: Boolean | H8: true | false | I8: Public | J8: Database Team | L8: PITR restore test executed in Phase 3 to validate RTO; 35-day recovery window | M8: 2025-06-01
A9: database.audit_events_ttl_days | B9: 90 | C9: 30 | D9: 90 | E9: TTL-based retention for audit_events records; expires items automatically without manual deletion | F9: Yes | G9: Integer | H9: 1-3653 | I9: Public | J9: Database Team | K9: database.audit_events_table_name | L9: SOC 2 CC7.2 evidence; set shorter in dev to control costs | M9: 2025-06-01
A10: database.quota_per_user_monthly | B10: 10 | C10: 10 | D10: 10 | E10: Maximum solutions per Amatra consultant per calendar month per SOW scope parameter | F10: Yes | G10: Integer | H10: 1-1000 | I10: Public | J10: Operations | K10: database.quotas_table_name | L10: Enforced via atomic DynamoDB conditional write; admin override available via API | M10: 2025-06-01
A11: database.quota_global_monthly | B11: 1000 | C11: 100 | D11: 1000 | E11: Maximum total solutions across all users per calendar month per SOW scope parameter | F11: Yes | G11: Integer | H11: 1-100000 | I11: Public | J11: Operations | K11: database.quotas_table_name | L11: CloudWatch alarm fires at 90% of this threshold (900 solutions) | M11: 2025-06-01
A12: database.inactive_user_suspension_days | B12: 90 | C12: 90 | D12: 90 | E12: Days of API inactivity before the scheduled Lambda suspends the Cognito account per SOC 2 CC6.2 | F12: Yes | G12: Integer | H12: 1-365 | I12: Public | J12: Security Team | K12: database.users_table_name | L12: Quarterly access reviews conducted by Daniel Park | M12: 2025-06-01

Sheet Application
A1: Application Parameters
A2: Parameter Name | B2: Production | C2: Test | D2: DR | E2: Description | F2: Required | G2: Data Type | H2: Validation Rules | I2: Security Level | J2: Owner Team | K2: Dependencies | L2: Notes | M2: Last Updated
A3: application.name | B3: eoframework | C3: eoframework | D3: eoframework | E3: Application identifier used in CloudWatch log groups and X-Ray service maps | F3: Yes | G3: String | H3: lowercase alphanumeric hyphens only max 50 chars | I3: Public | J3: Development | K3: solution.name | M3: 2025-06-01
A4: application.log_level | B4: info | C4: debug | D4: info | E4: Logging verbosity for all 17 Lambda functions; debug enabled in dev for agent tracing | F4: Yes | G4: String | H4: debug | info | warn | error | I4: Public | J4: Operations | M4: 2025-06-01
A5: application.port | B5: 443 | C5: 443 | D5: 443 | E5: HTTPS port enforced on API Gateway HTTP API v2; HTTP requests rejected | F5: Yes | G5: Integer | H5: 443 only | I5: Public | J5: Development | K5: networking.apigw_endpoint | M5: 2025-06-01
A6: application.timeout_seconds | B6: 30 | C6: 30 | D6: 30 | E6: Synchronous API route Lambda timeout in seconds; async generation routes use separate config | F6: Yes | G6: Integer | H6: 1-900 | I6: Public | J6: Development | K6: compute.lambda.api_handler.timeout_seconds | M6: 2025-06-01
A7: application.cli_package_name | B7: eoframework-cli | C7: eoframework-cli | D7: eoframework-cli | E7: Pip-installable Python package name for the 14-subcommand consultant-facing CLI | F7: Yes | G7: String | H7: Valid Python package name | I7: Public | J7: Development | M7: 2025-06-01
A8: application.cli_subcommand_count | B8: 14 | C8: 14 | D8: 14 | E8: Total CLI subcommands including auth / generate / status / admin per SOW specification | F8: Yes | G8: Integer | H8: 14 | I8: Public | J8: Development | K8: application.cli_package_name | L8: Must match SOW deliverable D11 exactly | M8: 2025-06-01
A9: application.api_route_count | B9: 11 | C9: 11 | D9: 11 | E9: Total HTTP API v2 Lambda routes per SOW specification | F9: Yes | G9: Integer | H9: 11 | I9: Public | J9: Development | K9: networking.apigw_endpoint | L9: Must match SOW deliverable D4 exactly | M9: 2025-06-01
A10: application.artifact_types_count | B10: 12 | C10: 12 | D10: 12 | E10: Total EO Framework artifact types: 5 presales + 6 delivery + 1 Terraform automation bundle | F10: Yes | G10: Integer | H10: 12 | I10: Public | J10: Development | M10: 2025-06-01
A11: application.agent_count | B11: 5 | C11: 5 | D11: 5 | E11: Total Strands agents registered in Bedrock AgentCore Runtime per SOW scope | F11: Yes | G11: Integer | H11: 5 | I11: Public | J11: Development | K11: bedrock.agentcore.runtime_region | M11: 2025-06-01
A12: application.max_retries_per_artifact | B12: 3 | C12: 3 | D12: 3 | E12: Maximum automatic retries per artifact in the EO Validator validation loop | F12: Yes | G12: Integer | H12: 1-10 | I12: Public | J12: Development | K12: bedrock.validator_model_id | L12: Graded delivery policy surfaces passing artifacts while retrying failures | M12: 2025-06-01
A13: application.generation_timeout_minutes | B13: 60 | C13: 60 | D13: 60 | E13: End-to-end 12-artifact solution bundle generation time limit; SLA target from SOW | F13: Yes | G13: Integer | H13: 1-480 | I13: Public | J13: Operations | M13: 2025-06-01

Sheet Monitoring
A1: Monitoring Parameters
A2: Parameter Name | B2: Production | C2: Test | D2: DR | E2: Description | F2: Required | G2: Data Type | H2: Validation Rules | I2: Security Level | J2: Owner Team | K2: Dependencies | L2: Notes | M2: Last Updated
A3: monitoring.cloudwatch_dashboard_name | B3: eofw-prd-health | C3: eofw-dev-health | D3: eofw-prd-health | E3: CloudWatch dashboard name for real-time Lambda / DynamoDB / Bedrock operational visibility | F3: Yes | G3: String | H3: Non-empty string max 255 chars | I3: Public | J3: Operations | K3: solution.region.primary | M3: 2025-06-01
A4: monitoring.log_retention_lambda_days | B4: 90 | C4: 30 | D4: 90 | E4: CloudWatch Log Group retention in days for the 17 Lambda function log groups | F4: Yes | G4: Integer | H4: 1-3653 | I4: Public | J4: Operations | L4: Production uses 90 days per SOW data architecture; shorter in dev to control cost | M4: 2025-06-01
A5: monitoring.log_retention_cloudtrail_days | B5: 365 | C5: 90 | D5: 365 | E5: CloudWatch Logs retention for CloudTrail delivery to CloudWatch Logs group | F5: Yes | G5: Integer | H5: 1-3653 | I5: Public | J5: Security Team | K5: security.cloudtrail.management_events | L5: 365 days required for SOC 2 evidence window | M5: 2025-06-01
A6: monitoring.xray_sampling_rate | B6: 0.05 | C6: 1.0 | D6: 0.05 | E6: X-Ray trace sampling rate; 5% in production / 100% in dev for full distributed tracing | F6: Yes | G6: Number | H6: 0.0-1.0 | I6: Public | J6: Operations | K6: compute.lambda.xray_tracing | L6: Configurable post-launch; increase to 0.10 during Phase 3 load test investigation | M6: 2025-06-01
A7: monitoring.alert_sns_topic_arn | B7: [sns-ops-alerts-arn] | C7: [sns-ops-alerts-arn] | D7: [sns-ops-alerts-arn] | E7: SNS topic ARN for all CloudWatch Alarms; email subscriptions for Daniel Park and ops on-call | F7: Yes | G7: String | H7: Valid SNS ARN | I7: Confidential | J7: Operations | K7: solution.region.primary | L7: Routes Lambda error rate / Bedrock throttle / DLQ / quota threshold alarms | M7: 2025-06-01
A8: monitoring.alarm_lambda_error_rate_pct | B8: 1 | C8: 5 | D8: 1 | E8: Lambda error rate alarm threshold as a percentage; triggers P2 alert to ops team | F8: Yes | G8: Number | H8: 0.1-100.0 | I8: Public | J8: Operations | K8: monitoring.alert_sns_topic_arn | L8: Escalate to P1 if sustained > 15 minutes per alert definitions in detailed design | M8: 2025-06-01
A9: monitoring.alarm_bedrock_throttle_count | B9: 5 | C9: 20 | D9: 5 | E9: Bedrock ThrottlingException count per 5-minute window before alarm fires | F9: Yes | G9: Integer | H9: 1-1000 | I9: Public | J9: Operations | K9: monitoring.alert_sns_topic_arn | L9: Triggers SNS notification; investigate token throughput and request quota increase if sustained | M9: 2025-06-01
A10: monitoring.alarm_global_quota_threshold_pct | B10: 90 | C10: 90 | D10: 90 | E10: Percentage of global monthly quota (1000 solutions) that triggers P3 warning alarm | F10: Yes | G10: Integer | H10: 1-100 | I10: Public | J10: Operations | K10: monitoring.alert_sns_topic_arn, database.quota_global_monthly | L10: Fires at 900/1000 solutions; notify Admin to evaluate quota increase | M10: 2025-06-01
A11: monitoring.canary_health_check_interval_minutes | B11: 5 | C11: 5 | D11: 5 | E11: CloudWatch Synthetics canary polling interval in minutes for /api/v1/health route | F11: Yes | G11: Integer | H11: 1-60 | I11: Public | J11: Operations | K11: networking.apigw_endpoint | L11: P1 alarm fires on 2 consecutive canary failures; immediate escalation required | M11: 2025-06-01
A12: monitoring.api_gateway_p99_latency_ms | B12: 3000 | C12: 3000 | D12: 3000 | E12: API Gateway P99 latency SLA target in milliseconds for synchronous routes per SOW | F12: Yes | G12: Integer | H12: 100-30000 | I12: Public | J12: Operations | K12: networking.apigw_endpoint | L12: CloudWatch metric alarm configured against this threshold | M12: 2025-06-01
A13: monitoring.bedrock_cost_per_solution_alert_usd | B13: 5.00 | C13: 5.00 | D13: 5.00 | E13: Alert threshold for estimated per-solution Bedrock cost in USD; matches SOW success metric | F13: Yes | G13: Number | H13: 0.01-100.00 | I13: Public | J13: Operations | K13: monitoring.alert_sns_topic_arn, bedrock.cost_per_solution_target_usd | M13: 2025-06-01

Sheet Bedrock
A1: Bedrock Parameters
A2: Parameter Name | B2: Production | C2: Test | D2: DR | E2: Description | F2: Required | G2: Data Type | H2: Validation Rules | I2: Security Level | J2: Owner Team | K2: Dependencies | L2: Notes | M2: Last Updated
A3: bedrock.primary_model_id | B3: anthropic.claude-sonnet-4-5 | C3: anthropic.claude-sonnet-4-5 | D3: anthropic.claude-sonnet-4-5 | E3: Claude Sonnet 4.6 model ID used by Pre-Sales / Delivery / Code Generator agents for artifact generation | F3: Yes | G3: String | H3: Valid Bedrock model ID | I3: Confidential | J3: Development | K3: bedrock.agentcore.runtime_region | L3: Primary generation model; targets < $5 per solution at 200 solutions/month | M3: 2025-06-01
A4: bedrock.validator_model_id | B4: anthropic.claude-haiku-4-5 | C4: anthropic.claude-haiku-4-5 | D4: anthropic.claude-haiku-4-5 | E4: Claude Haiku 4.5 model ID used by EO Validator agent for cost-efficient quality scoring | F4: Yes | G4: String | H4: Valid Bedrock model ID | I4: Confidential | J4: Development | K4: bedrock.agentcore.runtime_region | L4: Haiku chosen to reduce validation cost vs Sonnet per infrastructure cost model | M4: 2025-06-01
A5: bedrock.agentcore.runtime_region | B5: us-west-2 | C5: us-west-2 | D5: us-west-2 | E5: AWS region where Bedrock AgentCore Runtime hosts the five Strands agents | F5: Yes | G5: String | H5: Valid AWS region code | I5: Public | J5: Development | K5: solution.region.primary | L5: Must be GA in us-west-2 before Phase 2 start per SOW assumption A8; validate in Week 1 spike | M5: 2025-06-01
A6: bedrock.input_tokens_monthly_sonnet | B6: 3000000 | C6: 500000 | D6: 3000000 | E6: Target Bedrock Sonnet 4.6 input token volume per month at PoC steady state (~50 solutions/month) | F6: Yes | G6: Integer | H6: 1-1000000000 | I6: Public | J6: Operations | K6: bedrock.primary_model_id | L6: Sourced from SOW Scope Parameters; quota pre-approval via AWS Solutions Architect required | M6: 2025-06-01
A7: bedrock.output_tokens_monthly_sonnet | B7: 1000000 | C7: 100000 | D7: 1000000 | E7: Target Bedrock Sonnet 4.6 output token volume per month at PoC steady state | F7: Yes | G7: Integer | H7: 1-1000000000 | I7: Public | J7: Operations | K7: bedrock.primary_model_id | L7: Monitor in CloudWatch; alert if trending above cost model projection | M7: 2025-06-01
A8: bedrock.cost_per_solution_target_usd | B8: 5.00 | C8: 5.00 | D8: 5.00 | E8: Maximum acceptable Bedrock model spend per 12-artifact solution bundle per SOW success metric | F8: Yes | G8: Number | H8: 0.01-100.00 | I8: Public | J8: Operations | K8: bedrock.primary_model_id | L8: Validated in Phase 3 load test at 200 solutions/month | M8: 2025-06-01

Sheet Integration
A1: Integration Parameters
A2: Parameter Name | B2: Production | C2: Test | D2: DR | E2: Description | F2: Required | G2: Data Type | H2: Validation Rules | I2: Security Level | J2: Owner Team | K2: Dependencies | L2: Notes | M2: Last Updated
A3: integration.github.repository_url | B3: [github-repo-url] | C3: [github-repo-url] | D3: [github-repo-url] | E3: GitHub repository URL for automated PAT-based artifact commit pipeline per SOW deliverable D13 | F3: Yes | G3: String | H3: Valid HTTPS GitHub URL | I3: Confidential | J3: Integration Team | K3: integration.github.secret_arn | L3: Provisioned by Marcus Patel before Week 5 per SOW dependency table | M3: 2025-06-01
A4: integration.github.secret_arn | B4: [secrets-manager-arn-github-pat] | C4: [secrets-manager-arn-github-pat] | D4: [secrets-manager-arn-github-pat] | E4: Secrets Manager ARN storing the GitHub PAT with repo-write scope | F4: Yes | G4: String | H4: Valid Secrets Manager ARN | I4: Secret | J4: Security Team | K4: integration.github.repository_url | L4: 90-day automatic rotation; PAT retrieved at runtime; never logged or baked into image | M4: 2025-06-01
A5: integration.github.pat_rotation_days | B5: 90 | C5: 90 | D5: 90 | E5: GitHub PAT rotation period in days matching Secrets Manager automatic rotation schedule | F5: Yes | G5: Integer | H5: 1-365 | I5: Public | J5: Security Team | K5: integration.github.secret_arn | L5: PAT expiry alarm configured in CloudWatch; DLQ for failed commits | M5: 2025-06-01
A6: integration.github.push_retry_count | B6: 3 | C6: 3 | D6: 3 | E6: Maximum GitHub API push retry attempts before writing to SQS DLQ for failed commits | F6: Yes | G6: Integer | H6: 1-10 | I6: Public | J6: Integration Team | K6: integration.github.secret_arn | L6: CloudWatch alarm fires on DLQ depth > 0; SNS notification to Daniel Park | M6: 2025-06-01
A7: integration.github.commit_message_format | B7: {solution_id}/{artifact_type}: generated by EO Validator — {status} | C7: {solution_id}/{artifact_type}: generated by EO Validator — {status} | D7: {solution_id}/{artifact_type}: generated by EO Validator — {status} | E7: Structured commit message format creating immutable delivery audit trail in GitHub history | F7: Yes | G7: String | H7: Must include solution_id and artifact_type tokens | I7: Public | J7: Integration Team | K7: integration.github.repository_url | M7: 2025-06-01
A8: integration.github.dlq_name | B8: eofw-prd-sqs-github-dlq | C8: eofw-dev-sqs-github-dlq | D8: eofw-prd-sqs-github-dlq | E8: SQS FIFO DLQ name for failed GitHub push messages after retry exhaustion | F8: Yes | G8: String | H8: Valid SQS queue name ending in .fifo | I8: Confidential | J8: Integration Team | K8: integration.github.push_retry_count | M8: 2025-06-01

Sheet Operations
A1: Operations Parameters
A2: Parameter Name | B2: Production | C2: Test | D2: DR | E2: Description | F2: Required | G2: Data Type | H2: Validation Rules | I2: Security Level | J2: Owner Team | K2: Dependencies | L2: Notes | M2: Last Updated
A3: operations.backup_enabled | B3: true | C3: true | D3: true | E3: Enable automated DynamoDB PITR and S3 versioning backups across all environments | F3: Yes | G3: Boolean | H3: true | false | I3: Public | J3: Operations | K3: database.pitr_enabled | M3: 2025-06-01
A4: operations.rto_hours | B4: 4 | C4: 4 | D4: 4 | E4: Recovery Time Objective in hours; validated by DynamoDB PITR restore test in Phase 3 | F4: Yes | G4: Integer | H4: 1-72 | I4: Public | J4: Operations | K4: database.pitr_enabled | L4: PITR restore test performed in staging during Phase 3 to validate this target | M4: 2025-06-01
A5: operations.rpo_hours | B5: 1 | C5: 1 | D5: 1 | E5: Recovery Point Objective in hours; met by DynamoDB PITR continuous backup per SOW DR design | F5: Yes | G5: Integer | H5: 1-24 | I5: Public | J5: Operations | K5: database.pitr_enabled | M5: 2025-06-01
A6: operations.scaling_min_solutions_monthly | B6: 50 | C6: 10 | D6: 50 | E6: Minimum monthly solution volume sizing baseline used for infrastructure cost model | F6: Yes | G6: Integer | H6: 1-10000 | I6: Public | J6: Operations | K6: bedrock.cost_per_solution_target_usd | L6: PoC baseline is 50 solutions/month; load test targets 200 solutions/month in Phase 3 | M6: 2025-06-01
A7: operations.scaling_max_solutions_monthly | B7: 1000 | C7: 100 | D7: 1000 | E7: Global quota cap defining maximum monthly platform throughput | F7: Yes | G7: Integer | H7: 1-100000 | I7: Public | J7: Operations | K7: database.quota_global_monthly | L7: Matches database.quota_global_monthly; increase requires both config and DynamoDB change | M7: 2025-06-01
A8: operations.hypercare_duration_weeks | B8: 4 | C8: 0 | D8: 4 | E8: Post-go-live hypercare support period duration in weeks per SOW Handover section | F8: Yes | G8: Integer | H8: 1-52 | I8: Public | J8: Operations | L8: Weeks 13-16; P1 2-hour / P2 4-hour / P3 next-business-day response times | M8: 2025-06-01
A9: operations.cicd_pipeline_tool | B9: github-actions | C9: github-actions | D9: github-actions | E9: CI/CD pipeline tool for Docker build / ECR push / Lambda deploy / terraform validate gate | F9: Yes | G9: String | H9: github-actions | codepipeline | I9: Public | J9: DevOps | L9: AWS CodePipeline is fallback per SOW; GitHub Actions is primary | M9: 2025-06-01
A10: operations.terraform_validate_gate | B10: true | C10: true | D10: true | E10: Enforce terraform validate syntax gate in CI/CD pipeline before terraform apply | F10: Yes | G10: Boolean | H10: true | false | I10: Public | J10: DevOps | K10: operations.cicd_pipeline_tool | L10: IaC-only changes enforced; no manual console changes permitted in production | M10: 2025-06-01
A11: operations.peer_review_required | B11: true | C11: true | D11: true | E11: Require peer review of terraform plan output before terraform apply per SOW governance | F11: Yes | G11: Boolean | H11: true | false | I11: Public | J11: DevOps | K11: operations.terraform_validate_gate | L11: SOC 2 CC8.1 change management control | M11: 2025-06-01
A12: operations.availability_target_pct | B12: 99.5 | C12: 99.5 | D12: 99.5 | E12: Monthly API availability target as a percentage per SOW success metrics | F12: Yes | G12: Number | H12: 90.0-100.0 | I12: Public | J12: Operations | K12: monitoring.alarm_lambda_error_rate_pct | L12: Measured by CloudWatch Lambda error rate alarm across all 11 API routes | M12: 2025-06-01
A13: operations.artifact_pass_rate_target_pct | B13: 95 | C13: 95 | D13: 95 | E13: Minimum artifact validation first-attempt pass rate across all 12 artifact types per SOW | F13: Yes | G13: Number | H13: 50.0-100.0 | I13: Public | J13: Operations | K13: application.max_retries_per_artifact | L13: EO Validator DynamoDB metrics track this KPI; Phase 3 acceptance gate | M13: 2025-06-01
A14: operations.quota_bypass_incidents_target | B14: 0 | C14: 0 | D14: 0 | E14: Zero quota bypass incidents permitted; enforced via atomic DynamoDB conditional writes | F14: Yes | G14: Integer | H14: 0-0 | I14: Public | J14: Security Team | K14: database.quotas_table_name | L14: Validated in Phase 3 security testing via concurrent batch request scenarios | M14: 2025-06-01
