Workbook

Sheet Cover
B3: Configuration Parameters
B5: Generated: | C5: June 10, 2026
B6: Solution: | C6: Tmpqz8Q6Wcz
B7: Customer: | C7: [Customer Name]
B8: Version: | C8: 1.0
B9: Status: | C9: Draft
C12: eoframework.org

Sheet All Parameters (Read Only)
A1: Total Parameters | B1: Categories | C1: Required | D1: Confidential/Secret
A2: 100 | B2: 9 | C2: 100 | D2: 25
A4: Parameter Name | B4: Category | C4: Production | D4: Test | E4: DR | F4: Description | G4: Required | H4: Data Type | I4: Validation Rules | J4: Security Level | K4: Owner Team | L4: Dependencies | M4: Notes | N4: Last Updated
A5: =IF('Project'!A3="","",'Project'!A3) | B5: Project | C5: =IF('Project'!B3="","",'Project'!B3) | D5: =IF('Project'!C3="","",'Project'!C3) | E5: =IF('Project'!D3="","",'Project'!D3) | F5: =IF('Project'!E3="","",'Project'!E3) | G5: =IF('Project'!F3="","",'Project'!F3) | H5: =IF('Project'!G3="","",'Project'!G3) | I5: =IF('Project'!H3="","",'Project'!H3) | J5: =IF('Project'!I3="","",'Project'!I3) | ... N5: =IF('Project'!M3="","",'Project'!M3)
A6: =IF('Project'!A4="","",'Project'!A4) | B6: Project | C6: =IF('Project'!B4="","",'Project'!B4) | D6: =IF('Project'!C4="","",'Project'!C4) | E6: =IF('Project'!D4="","",'Project'!D4) | F6: =IF('Project'!E4="","",'Project'!E4) | G6: =IF('Project'!F4="","",'Project'!F4) | H6: =IF('Project'!G4="","",'Project'!G4) | I6: =IF('Project'!H4="","",'Project'!H4) | J6: =IF('Project'!I4="","",'Project'!I4) | ... N6: =IF('Project'!M4="","",'Project'!M4)
A7: =IF('Project'!A5="","",'Project'!A5) | B7: Project | C7: =IF('Project'!B5="","",'Project'!B5) | D7: =IF('Project'!C5="","",'Project'!C5) | E7: =IF('Project'!D5="","",'Project'!D5) | F7: =IF('Project'!E5="","",'Project'!E5) | G7: =IF('Project'!F5="","",'Project'!F5) | H7: =IF('Project'!G5="","",'Project'!G5) | I7: =IF('Project'!H5="","",'Project'!H5) | J7: =IF('Project'!I5="","",'Project'!I5) | ... N7: =IF('Project'!M5="","",'Project'!M5)
A8: =IF('Project'!A6="","",'Project'!A6) | B8: Project | C8: =IF('Project'!B6="","",'Project'!B6) | D8: =IF('Project'!C6="","",'Project'!C6) | E8: =IF('Project'!D6="","",'Project'!D6) | F8: =IF('Project'!E6="","",'Project'!E6) | G8: =IF('Project'!F6="","",'Project'!F6) | H8: =IF('Project'!G6="","",'Project'!G6) | I8: =IF('Project'!H6="","",'Project'!H6) | J8: =IF('Project'!I6="","",'Project'!I6) | ... N8: =IF('Project'!M6="","",'Project'!M6)
A9: =IF('Project'!A7="","",'Project'!A7) | B9: Project | C9: =IF('Project'!B7="","",'Project'!B7) | D9: =IF('Project'!C7="","",'Project'!C7) | E9: =IF('Project'!D7="","",'Project'!D7) | F9: =IF('Project'!E7="","",'Project'!E7) | G9: =IF('Project'!F7="","",'Project'!F7) | H9: =IF('Project'!G7="","",'Project'!G7) | I9: =IF('Project'!H7="","",'Project'!H7) | J9: =IF('Project'!I7="","",'Project'!I7) | ... N9: =IF('Project'!M7="","",'Project'!M7)
A10: =IF('Project'!A8="","",'Project'!A8) | B10: Project | C10: =IF('Project'!B8="","",'Project'!B8) | D10: =IF('Project'!C8="","",'Project'!C8) | E10: =IF('Project'!D8="","",'Project'!D8) | F10: =IF('Project'!E8="","",'Project'!E8) | G10: =IF('Project'!F8="","",'Project'!F8) | H10: =IF('Project'!G8="","",'Project'!G8) | I10: =IF('Project'!H8="","",'Project'!H8) | J10: =IF('Project'!I8="","",'Project'!I8) | ... N10: =IF('Project'!M8="","",'Project'!M8)
A11: =IF('Project'!A9="","",'Project'!A9) | B11: Project | C11: =IF('Project'!B9="","",'Project'!B9) | D11: =IF('Project'!C9="","",'Project'!C9) | E11: =IF('Project'!D9="","",'Project'!D9) | F11: =IF('Project'!E9="","",'Project'!E9) | G11: =IF('Project'!F9="","",'Project'!F9) | H11: =IF('Project'!G9="","",'Project'!G9) | I11: =IF('Project'!H9="","",'Project'!H9) | J11: =IF('Project'!I9="","",'Project'!I9) | ... N11: =IF('Project'!M9="","",'Project'!M9)
A12: =IF('Security'!A3="","",'Security'!A3) | B12: Security | C12: =IF('Security'!B3="","",'Security'!B3) | D12: =IF('Security'!C3="","",'Security'!C3) | E12: =IF('Security'!D3="","",'Security'!D3) | F12: =IF('Security'!E3="","",'Security'!E3) | G12: =IF('Security'!F3="","",'Security'!F3) | H12: =IF('Security'!G3="","",'Security'!G3) | I12: =IF('Security'!H3="","",'Security'!H3) | J12: =IF('Security'!I3="","",'Security'!I3) | ... N12: =IF('Security'!M3="","",'Security'!M3)
A13: =IF('Security'!A4="","",'Security'!A4) | B13: Security | C13: =IF('Security'!B4="","",'Security'!B4) | D13: =IF('Security'!C4="","",'Security'!C4) | E13: =IF('Security'!D4="","",'Security'!D4) | F13: =IF('Security'!E4="","",'Security'!E4) | G13: =IF('Security'!F4="","",'Security'!F4) | H13: =IF('Security'!G4="","",'Security'!G4) | I13: =IF('Security'!H4="","",'Security'!H4) | J13: =IF('Security'!I4="","",'Security'!I4) | ... N13: =IF('Security'!M4="","",'Security'!M4)
A14: =IF('Security'!A5="","",'Security'!A5) | B14: Security | C14: =IF('Security'!B5="","",'Security'!B5) | D14: =IF('Security'!C5="","",'Security'!C5) | E14: =IF('Security'!D5="","",'Security'!D5) | F14: =IF('Security'!E5="","",'Security'!E5) | G14: =IF('Security'!F5="","",'Security'!F5) | H14: =IF('Security'!G5="","",'Security'!G5) | I14: =IF('Security'!H5="","",'Security'!H5) | J14: =IF('Security'!I5="","",'Security'!I5) | ... N14: =IF('Security'!M5="","",'Security'!M5)
A15: =IF('Security'!A6="","",'Security'!A6) | B15: Security | C15: =IF('Security'!B6="","",'Security'!B6) | D15: =IF('Security'!C6="","",'Security'!C6) | E15: =IF('Security'!D6="","",'Security'!D6) | F15: =IF('Security'!E6="","",'Security'!E6) | G15: =IF('Security'!F6="","",'Security'!F6) | H15: =IF('Security'!G6="","",'Security'!G6) | I15: =IF('Security'!H6="","",'Security'!H6) | J15: =IF('Security'!I6="","",'Security'!I6) | ... N15: =IF('Security'!M6="","",'Security'!M6)
A16: =IF('Security'!A7="","",'Security'!A7) | B16: Security | C16: =IF('Security'!B7="","",'Security'!B7) | D16: =IF('Security'!C7="","",'Security'!C7) | E16: =IF('Security'!D7="","",'Security'!D7) | F16: =IF('Security'!E7="","",'Security'!E7) | G16: =IF('Security'!F7="","",'Security'!F7) | H16: =IF('Security'!G7="","",'Security'!G7) | I16: =IF('Security'!H7="","",'Security'!H7) | J16: =IF('Security'!I7="","",'Security'!I7) | ... N16: =IF('Security'!M7="","",'Security'!M7)
A17: =IF('Security'!A8="","",'Security'!A8) | B17: Security | C17: =IF('Security'!B8="","",'Security'!B8) | D17: =IF('Security'!C8="","",'Security'!C8) | E17: =IF('Security'!D8="","",'Security'!D8) | F17: =IF('Security'!E8="","",'Security'!E8) | G17: =IF('Security'!F8="","",'Security'!F8) | H17: =IF('Security'!G8="","",'Security'!G8) | I17: =IF('Security'!H8="","",'Security'!H8) | J17: =IF('Security'!I8="","",'Security'!I8) | ... N17: =IF('Security'!M8="","",'Security'!M8)
A18: =IF('Security'!A9="","",'Security'!A9) | B18: Security | C18: =IF('Security'!B9="","",'Security'!B9) | D18: =IF('Security'!C9="","",'Security'!C9) | E18: =IF('Security'!D9="","",'Security'!D9) | F18: =IF('Security'!E9="","",'Security'!E9) | G18: =IF('Security'!F9="","",'Security'!F9) | H18: =IF('Security'!G9="","",'Security'!G9) | I18: =IF('Security'!H9="","",'Security'!H9) | J18: =IF('Security'!I9="","",'Security'!I9) | ... N18: =IF('Security'!M9="","",'Security'!M9)
A19: =IF('Security'!A10="","",'Security'!A10) | B19: Security | C19: =IF('Security'!B10="","",'Security'!B10) | D19: =IF('Security'!C10="","",'Security'!C10) | E19: =IF('Security'!D10="","",'Security'!D10) | F19: =IF('Security'!E10="","",'Security'!E10) | G19: =IF('Security'!F10="","",'Security'!F10) | H19: =IF('Security'!G10="","",'Security'!G10) | I19: =IF('Security'!H10="","",'Security'!H10) | J19: =IF('Security'!I10="","",'Security'!I10) | ... N19: =IF('Security'!M10="","",'Security'!M10)
A20: =IF('Security'!A11="","",'Security'!A11) | B20: Security | C20: =IF('Security'!B11="","",'Security'!B11) | D20: =IF('Security'!C11="","",'Security'!C11) | E20: =IF('Security'!D11="","",'Security'!D11) | F20: =IF('Security'!E11="","",'Security'!E11) | G20: =IF('Security'!F11="","",'Security'!F11) | H20: =IF('Security'!G11="","",'Security'!G11) | I20: =IF('Security'!H11="","",'Security'!H11) | J20: =IF('Security'!I11="","",'Security'!I11) | ... N20: =IF('Security'!M11="","",'Security'!M11)
A21: =IF('Security'!A12="","",'Security'!A12) | B21: Security | C21: =IF('Security'!B12="","",'Security'!B12) | D21: =IF('Security'!C12="","",'Security'!C12) | E21: =IF('Security'!D12="","",'Security'!D12) | F21: =IF('Security'!E12="","",'Security'!E12) | G21: =IF('Security'!F12="","",'Security'!F12) | H21: =IF('Security'!G12="","",'Security'!G12) | I21: =IF('Security'!H12="","",'Security'!H12) | J21: =IF('Security'!I12="","",'Security'!I12) | ... N21: =IF('Security'!M12="","",'Security'!M12)
A22: =IF('Security'!A13="","",'Security'!A13) | B22: Security | C22: =IF('Security'!B13="","",'Security'!B13) | D22: =IF('Security'!C13="","",'Security'!C13) | E22: =IF('Security'!D13="","",'Security'!D13) | F22: =IF('Security'!E13="","",'Security'!E13) | G22: =IF('Security'!F13="","",'Security'!F13) | H22: =IF('Security'!G13="","",'Security'!G13) | I22: =IF('Security'!H13="","",'Security'!H13) | J22: =IF('Security'!I13="","",'Security'!I13) | ... N22: =IF('Security'!M13="","",'Security'!M13)
A23: =IF('Security'!A14="","",'Security'!A14) | B23: Security | C23: =IF('Security'!B14="","",'Security'!B14) | D23: =IF('Security'!C14="","",'Security'!C14) | E23: =IF('Security'!D14="","",'Security'!D14) | F23: =IF('Security'!E14="","",'Security'!E14) | G23: =IF('Security'!F14="","",'Security'!F14) | H23: =IF('Security'!G14="","",'Security'!G14) | I23: =IF('Security'!H14="","",'Security'!H14) | J23: =IF('Security'!I14="","",'Security'!I14) | ... N23: =IF('Security'!M14="","",'Security'!M14)
... A30: =IF('Security'!A21="","",'Security'!A21) | B30: Security | C30: =IF('Security'!B21="","",'Security'!B21) | D30: =IF('Security'!C21="","",'Security'!C21) | E30: =IF('Security'!D21="","",'Security'!D21) | F30: =IF('Security'!E21="","",'Security'!E21) | G30: =IF('Security'!F21="","",'Security'!F21) | H30: =IF('Security'!G21="","",'Security'!G21) | I30: =IF('Security'!H21="","",'Security'!H21) | J30: =IF('Security'!I21="","",'Security'!I21) | ... N30: =IF('Security'!M21="","",'Security'!M21)
A31: =IF('Compute'!A3="","",'Compute'!A3) | B31: Compute | C31: =IF('Compute'!B3="","",'Compute'!B3) | D31: =IF('Compute'!C3="","",'Compute'!C3) | E31: =IF('Compute'!D3="","",'Compute'!D3) | F31: =IF('Compute'!E3="","",'Compute'!E3) | G31: =IF('Compute'!F3="","",'Compute'!F3) | H31: =IF('Compute'!G3="","",'Compute'!G3) | I31: =IF('Compute'!H3="","",'Compute'!H3) | J31: =IF('Compute'!I3="","",'Compute'!I3) | ... N31: =IF('Compute'!M3="","",'Compute'!M3)
A32: =IF('Compute'!A4="","",'Compute'!A4) | B32: Compute | C32: =IF('Compute'!B4="","",'Compute'!B4) | D32: =IF('Compute'!C4="","",'Compute'!C4) | E32: =IF('Compute'!D4="","",'Compute'!D4) | F32: =IF('Compute'!E4="","",'Compute'!E4) | G32: =IF('Compute'!F4="","",'Compute'!F4) | H32: =IF('Compute'!G4="","",'Compute'!G4) | I32: =IF('Compute'!H4="","",'Compute'!H4) | J32: =IF('Compute'!I4="","",'Compute'!I4) | ... N32: =IF('Compute'!M4="","",'Compute'!M4)
A33: =IF('Compute'!A5="","",'Compute'!A5) | B33: Compute | C33: =IF('Compute'!B5="","",'Compute'!B5) | D33: =IF('Compute'!C5="","",'Compute'!C5) | E33: =IF('Compute'!D5="","",'Compute'!D5) | F33: =IF('Compute'!E5="","",'Compute'!E5) | G33: =IF('Compute'!F5="","",'Compute'!F5) | H33: =IF('Compute'!G5="","",'Compute'!G5) | I33: =IF('Compute'!H5="","",'Compute'!H5) | J33: =IF('Compute'!I5="","",'Compute'!I5) | ... N33: =IF('Compute'!M5="","",'Compute'!M5)
A34: =IF('Compute'!A6="","",'Compute'!A6) | B34: Compute | C34: =IF('Compute'!B6="","",'Compute'!B6) | D34: =IF('Compute'!C6="","",'Compute'!C6) | E34: =IF('Compute'!D6="","",'Compute'!D6) | F34: =IF('Compute'!E6="","",'Compute'!E6) | G34: =IF('Compute'!F6="","",'Compute'!F6) | H34: =IF('Compute'!G6="","",'Compute'!G6) | I34: =IF('Compute'!H6="","",'Compute'!H6) | J34: =IF('Compute'!I6="","",'Compute'!I6) | ... N34: =IF('Compute'!M6="","",'Compute'!M6)
A35: =IF('Compute'!A7="","",'Compute'!A7) | B35: Compute | C35: =IF('Compute'!B7="","",'Compute'!B7) | D35: =IF('Compute'!C7="","",'Compute'!C7) | E35: =IF('Compute'!D7="","",'Compute'!D7) | F35: =IF('Compute'!E7="","",'Compute'!E7) | G35: =IF('Compute'!F7="","",'Compute'!F7) | H35: =IF('Compute'!G7="","",'Compute'!G7) | I35: =IF('Compute'!H7="","",'Compute'!H7) | J35: =IF('Compute'!I7="","",'Compute'!I7) | ... N35: =IF('Compute'!M7="","",'Compute'!M7)
A36: =IF('Compute'!A8="","",'Compute'!A8) | B36: Compute | C36: =IF('Compute'!B8="","",'Compute'!B8) | D36: =IF('Compute'!C8="","",'Compute'!C8) | E36: =IF('Compute'!D8="","",'Compute'!D8) | F36: =IF('Compute'!E8="","",'Compute'!E8) | G36: =IF('Compute'!F8="","",'Compute'!F8) | H36: =IF('Compute'!G8="","",'Compute'!G8) | I36: =IF('Compute'!H8="","",'Compute'!H8) | J36: =IF('Compute'!I8="","",'Compute'!I8) | ... N36: =IF('Compute'!M8="","",'Compute'!M8)
A37: =IF('Compute'!A9="","",'Compute'!A9) | B37: Compute | C37: =IF('Compute'!B9="","",'Compute'!B9) | D37: =IF('Compute'!C9="","",'Compute'!C9) | E37: =IF('Compute'!D9="","",'Compute'!D9) | F37: =IF('Compute'!E9="","",'Compute'!E9) | G37: =IF('Compute'!F9="","",'Compute'!F9) | H37: =IF('Compute'!G9="","",'Compute'!G9) | I37: =IF('Compute'!H9="","",'Compute'!H9) | J37: =IF('Compute'!I9="","",'Compute'!I9) | ... N37: =IF('Compute'!M9="","",'Compute'!M9)
A38: =IF('Compute'!A10="","",'Compute'!A10) | B38: Compute | C38: =IF('Compute'!B10="","",'Compute'!B10) | D38: =IF('Compute'!C10="","",'Compute'!C10) | E38: =IF('Compute'!D10="","",'Compute'!D10) | F38: =IF('Compute'!E10="","",'Compute'!E10) | G38: =IF('Compute'!F10="","",'Compute'!F10) | H38: =IF('Compute'!G10="","",'Compute'!G10) | I38: =IF('Compute'!H10="","",'Compute'!H10) | J38: =IF('Compute'!I10="","",'Compute'!I10) | ... N38: =IF('Compute'!M10="","",'Compute'!M10)
A39: =IF('Compute'!A11="","",'Compute'!A11) | B39: Compute | C39: =IF('Compute'!B11="","",'Compute'!B11) | D39: =IF('Compute'!C11="","",'Compute'!C11) | E39: =IF('Compute'!D11="","",'Compute'!D11) | F39: =IF('Compute'!E11="","",'Compute'!E11) | G39: =IF('Compute'!F11="","",'Compute'!F11) | H39: =IF('Compute'!G11="","",'Compute'!G11) | I39: =IF('Compute'!H11="","",'Compute'!H11) | J39: =IF('Compute'!I11="","",'Compute'!I11) | ... N39: =IF('Compute'!M11="","",'Compute'!M11)
A40: =IF('Compute'!A12="","",'Compute'!A12) | B40: Compute | C40: =IF('Compute'!B12="","",'Compute'!B12) | D40: =IF('Compute'!C12="","",'Compute'!C12) | E40: =IF('Compute'!D12="","",'Compute'!D12) | F40: =IF('Compute'!E12="","",'Compute'!E12) | G40: =IF('Compute'!F12="","",'Compute'!F12) | H40: =IF('Compute'!G12="","",'Compute'!G12) | I40: =IF('Compute'!H12="","",'Compute'!H12) | J40: =IF('Compute'!I12="","",'Compute'!I12) | ... N40: =IF('Compute'!M12="","",'Compute'!M12)
A41: =IF('Compute'!A13="","",'Compute'!A13) | B41: Compute | C41: =IF('Compute'!B13="","",'Compute'!B13) | D41: =IF('Compute'!C13="","",'Compute'!C13) | E41: =IF('Compute'!D13="","",'Compute'!D13) | F41: =IF('Compute'!E13="","",'Compute'!E13) | G41: =IF('Compute'!F13="","",'Compute'!F13) | H41: =IF('Compute'!G13="","",'Compute'!G13) | I41: =IF('Compute'!H13="","",'Compute'!H13) | J41: =IF('Compute'!I13="","",'Compute'!I13) | ... N41: =IF('Compute'!M13="","",'Compute'!M13)
A42: =IF('Storage'!A3="","",'Storage'!A3) | B42: Storage | C42: =IF('Storage'!B3="","",'Storage'!B3) | D42: =IF('Storage'!C3="","",'Storage'!C3) | E42: =IF('Storage'!D3="","",'Storage'!D3) | F42: =IF('Storage'!E3="","",'Storage'!E3) | G42: =IF('Storage'!F3="","",'Storage'!F3) | H42: =IF('Storage'!G3="","",'Storage'!G3) | I42: =IF('Storage'!H3="","",'Storage'!H3) | J42: =IF('Storage'!I3="","",'Storage'!I3) | ... N42: =IF('Storage'!M3="","",'Storage'!M3)
A43: =IF('Storage'!A4="","",'Storage'!A4) | B43: Storage | C43: =IF('Storage'!B4="","",'Storage'!B4) | D43: =IF('Storage'!C4="","",'Storage'!C4) | E43: =IF('Storage'!D4="","",'Storage'!D4) | F43: =IF('Storage'!E4="","",'Storage'!E4) | G43: =IF('Storage'!F4="","",'Storage'!F4) | H43: =IF('Storage'!G4="","",'Storage'!G4) | I43: =IF('Storage'!H4="","",'Storage'!H4) | J43: =IF('Storage'!I4="","",'Storage'!I4) | ... N43: =IF('Storage'!M4="","",'Storage'!M4)
A44: =IF('Storage'!A5="","",'Storage'!A5) | B44: Storage | C44: =IF('Storage'!B5="","",'Storage'!B5) | D44: =IF('Storage'!C5="","",'Storage'!C5) | E44: =IF('Storage'!D5="","",'Storage'!D5) | F44: =IF('Storage'!E5="","",'Storage'!E5) | G44: =IF('Storage'!F5="","",'Storage'!F5) | H44: =IF('Storage'!G5="","",'Storage'!G5) | I44: =IF('Storage'!H5="","",'Storage'!H5) | J44: =IF('Storage'!I5="","",'Storage'!I5) | ... N44: =IF('Storage'!M5="","",'Storage'!M5)
A45: =IF('Storage'!A6="","",'Storage'!A6) | B45: Storage | C45: =IF('Storage'!B6="","",'Storage'!B6) | D45: =IF('Storage'!C6="","",'Storage'!C6) | E45: =IF('Storage'!D6="","",'Storage'!D6) | F45: =IF('Storage'!E6="","",'Storage'!E6) | G45: =IF('Storage'!F6="","",'Storage'!F6) | H45: =IF('Storage'!G6="","",'Storage'!G6) | I45: =IF('Storage'!H6="","",'Storage'!H6) | J45: =IF('Storage'!I6="","",'Storage'!I6) | ... N45: =IF('Storage'!M6="","",'Storage'!M6)
A46: =IF('Storage'!A7="","",'Storage'!A7) | B46: Storage | C46: =IF('Storage'!B7="","",'Storage'!B7) | D46: =IF('Storage'!C7="","",'Storage'!C7) | E46: =IF('Storage'!D7="","",'Storage'!D7) | F46: =IF('Storage'!E7="","",'Storage'!E7) | G46: =IF('Storage'!F7="","",'Storage'!F7) | H46: =IF('Storage'!G7="","",'Storage'!G7) | I46: =IF('Storage'!H7="","",'Storage'!H7) | J46: =IF('Storage'!I7="","",'Storage'!I7) | ... N46: =IF('Storage'!M7="","",'Storage'!M7)
A47: =IF('Storage'!A8="","",'Storage'!A8) | B47: Storage | C47: =IF('Storage'!B8="","",'Storage'!B8) | D47: =IF('Storage'!C8="","",'Storage'!C8) | E47: =IF('Storage'!D8="","",'Storage'!D8) | F47: =IF('Storage'!E8="","",'Storage'!E8) | G47: =IF('Storage'!F8="","",'Storage'!F8) | H47: =IF('Storage'!G8="","",'Storage'!G8) | I47: =IF('Storage'!H8="","",'Storage'!H8) | J47: =IF('Storage'!I8="","",'Storage'!I8) | ... N47: =IF('Storage'!M8="","",'Storage'!M8)
A48: =IF('Database'!A3="","",'Database'!A3) | B48: Database | C48: =IF('Database'!B3="","",'Database'!B3) | D48: =IF('Database'!C3="","",'Database'!C3) | E48: =IF('Database'!D3="","",'Database'!D3) | F48: =IF('Database'!E3="","",'Database'!E3) | G48: =IF('Database'!F3="","",'Database'!F3) | H48: =IF('Database'!G3="","",'Database'!G3) | I48: =IF('Database'!H3="","",'Database'!H3) | J48: =IF('Database'!I3="","",'Database'!I3) | ... N48: =IF('Database'!M3="","",'Database'!M3)
A49: =IF('Database'!A4="","",'Database'!A4) | B49: Database | C49: =IF('Database'!B4="","",'Database'!B4) | D49: =IF('Database'!C4="","",'Database'!C4) | E49: =IF('Database'!D4="","",'Database'!D4) | F49: =IF('Database'!E4="","",'Database'!E4) | G49: =IF('Database'!F4="","",'Database'!F4) | H49: =IF('Database'!G4="","",'Database'!G4) | I49: =IF('Database'!H4="","",'Database'!H4) | J49: =IF('Database'!I4="","",'Database'!I4) | ... N49: =IF('Database'!M4="","",'Database'!M4)
A50: =IF('Database'!A5="","",'Database'!A5) | B50: Database | C50: =IF('Database'!B5="","",'Database'!B5) | D50: =IF('Database'!C5="","",'Database'!C5) | E50: =IF('Database'!D5="","",'Database'!D5) | F50: =IF('Database'!E5="","",'Database'!E5) | G50: =IF('Database'!F5="","",'Database'!F5) | H50: =IF('Database'!G5="","",'Database'!G5) | I50: =IF('Database'!H5="","",'Database'!H5) | J50: =IF('Database'!I5="","",'Database'!I5) | ... N50: =IF('Database'!M5="","",'Database'!M5)
A51: =IF('Database'!A6="","",'Database'!A6) | B51: Database | C51: =IF('Database'!B6="","",'Database'!B6) | D51: =IF('Database'!C6="","",'Database'!C6) | E51: =IF('Database'!D6="","",'Database'!D6) | F51: =IF('Database'!E6="","",'Database'!E6) | G51: =IF('Database'!F6="","",'Database'!F6) | H51: =IF('Database'!G6="","",'Database'!G6) | I51: =IF('Database'!H6="","",'Database'!H6) | J51: =IF('Database'!I6="","",'Database'!I6) | ... N51: =IF('Database'!M6="","",'Database'!M6)
A52: =IF('Database'!A7="","",'Database'!A7) | B52: Database | C52: =IF('Database'!B7="","",'Database'!B7) | D52: =IF('Database'!C7="","",'Database'!C7) | E52: =IF('Database'!D7="","",'Database'!D7) | F52: =IF('Database'!E7="","",'Database'!E7) | G52: =IF('Database'!F7="","",'Database'!F7) | H52: =IF('Database'!G7="","",'Database'!G7) | I52: =IF('Database'!H7="","",'Database'!H7) | J52: =IF('Database'!I7="","",'Database'!I7) | ... N52: =IF('Database'!M7="","",'Database'!M7)
A53: =IF('Database'!A8="","",'Database'!A8) | B53: Database | C53: =IF('Database'!B8="","",'Database'!B8) | D53: =IF('Database'!C8="","",'Database'!C8) | E53: =IF('Database'!D8="","",'Database'!D8) | F53: =IF('Database'!E8="","",'Database'!E8) | G53: =IF('Database'!F8="","",'Database'!F8) | H53: =IF('Database'!G8="","",'Database'!G8) | I53: =IF('Database'!H8="","",'Database'!H8) | J53: =IF('Database'!I8="","",'Database'!I8) | ... N53: =IF('Database'!M8="","",'Database'!M8)
A54: =IF('Database'!A9="","",'Database'!A9) | B54: Database | C54: =IF('Database'!B9="","",'Database'!B9) | D54: =IF('Database'!C9="","",'Database'!C9) | E54: =IF('Database'!D9="","",'Database'!D9) | F54: =IF('Database'!E9="","",'Database'!E9) | G54: =IF('Database'!F9="","",'Database'!F9) | H54: =IF('Database'!G9="","",'Database'!G9) | I54: =IF('Database'!H9="","",'Database'!H9) | J54: =IF('Database'!I9="","",'Database'!I9) | ... N54: =IF('Database'!M9="","",'Database'!M9)
A55: =IF('Application'!A3="","",'Application'!A3) | B55: Application | C55: =IF('Application'!B3="","",'Application'!B3) | D55: =IF('Application'!C3="","",'Application'!C3) | E55: =IF('Application'!D3="","",'Application'!D3) | F55: =IF('Application'!E3="","",'Application'!E3) | G55: =IF('Application'!F3="","",'Application'!F3) | H55: =IF('Application'!G3="","",'Application'!G3) | I55: =IF('Application'!H3="","",'Application'!H3) | J55: =IF('Application'!I3="","",'Application'!I3) | ... N55: =IF('Application'!M3="","",'Application'!M3)
A56: =IF('Application'!A4="","",'Application'!A4) | B56: Application | C56: =IF('Application'!B4="","",'Application'!B4) | D56: =IF('Application'!C4="","",'Application'!C4) | E56: =IF('Application'!D4="","",'Application'!D4) | F56: =IF('Application'!E4="","",'Application'!E4) | G56: =IF('Application'!F4="","",'Application'!F4) | H56: =IF('Application'!G4="","",'Application'!G4) | I56: =IF('Application'!H4="","",'Application'!H4) | J56: =IF('Application'!I4="","",'Application'!I4) | ... N56: =IF('Application'!M4="","",'Application'!M4)
A57: =IF('Application'!A5="","",'Application'!A5) | B57: Application | C57: =IF('Application'!B5="","",'Application'!B5) | D57: =IF('Application'!C5="","",'Application'!C5) | E57: =IF('Application'!D5="","",'Application'!D5) | F57: =IF('Application'!E5="","",'Application'!E5) | G57: =IF('Application'!F5="","",'Application'!F5) | H57: =IF('Application'!G5="","",'Application'!G5) | I57: =IF('Application'!H5="","",'Application'!H5) | J57: =IF('Application'!I5="","",'Application'!I5) | ... N57: =IF('Application'!M5="","",'Application'!M5)
A58: =IF('Application'!A6="","",'Application'!A6) | B58: Application | C58: =IF('Application'!B6="","",'Application'!B6) | D58: =IF('Application'!C6="","",'Application'!C6) | E58: =IF('Application'!D6="","",'Application'!D6) | F58: =IF('Application'!E6="","",'Application'!E6) | G58: =IF('Application'!F6="","",'Application'!F6) | H58: =IF('Application'!G6="","",'Application'!G6) | I58: =IF('Application'!H6="","",'Application'!H6) | J58: =IF('Application'!I6="","",'Application'!I6) | ... N58: =IF('Application'!M6="","",'Application'!M6)
A59: =IF('Application'!A7="","",'Application'!A7) | B59: Application | C59: =IF('Application'!B7="","",'Application'!B7) | D59: =IF('Application'!C7="","",'Application'!C7) | E59: =IF('Application'!D7="","",'Application'!D7) | F59: =IF('Application'!E7="","",'Application'!E7) | G59: =IF('Application'!F7="","",'Application'!F7) | H59: =IF('Application'!G7="","",'Application'!G7) | I59: =IF('Application'!H7="","",'Application'!H7) | J59: =IF('Application'!I7="","",'Application'!I7) | ... N59: =IF('Application'!M7="","",'Application'!M7)
A60: =IF('Application'!A8="","",'Application'!A8) | B60: Application | C60: =IF('Application'!B8="","",'Application'!B8) | D60: =IF('Application'!C8="","",'Application'!C8) | E60: =IF('Application'!D8="","",'Application'!D8) | F60: =IF('Application'!E8="","",'Application'!E8) | G60: =IF('Application'!F8="","",'Application'!F8) | H60: =IF('Application'!G8="","",'Application'!G8) | I60: =IF('Application'!H8="","",'Application'!H8) | J60: =IF('Application'!I8="","",'Application'!I8) | ... N60: =IF('Application'!M8="","",'Application'!M8)
A61: =IF('Monitoring'!A3="","",'Monitoring'!A3) | B61: Monitoring | C61: =IF('Monitoring'!B3="","",'Monitoring'!B3) | D61: =IF('Monitoring'!C3="","",'Monitoring'!C3) | E61: =IF('Monitoring'!D3="","",'Monitoring'!D3) | F61: =IF('Monitoring'!E3="","",'Monitoring'!E3) | G61: =IF('Monitoring'!F3="","",'Monitoring'!F3) | H61: =IF('Monitoring'!G3="","",'Monitoring'!G3) | I61: =IF('Monitoring'!H3="","",'Monitoring'!H3) | J61: =IF('Monitoring'!I3="","",'Monitoring'!I3) | ... N61: =IF('Monitoring'!M3="","",'Monitoring'!M3)
A62: =IF('Monitoring'!A4="","",'Monitoring'!A4) | B62: Monitoring | C62: =IF('Monitoring'!B4="","",'Monitoring'!B4) | D62: =IF('Monitoring'!C4="","",'Monitoring'!C4) | E62: =IF('Monitoring'!D4="","",'Monitoring'!D4) | F62: =IF('Monitoring'!E4="","",'Monitoring'!E4) | G62: =IF('Monitoring'!F4="","",'Monitoring'!F4) | H62: =IF('Monitoring'!G4="","",'Monitoring'!G4) | I62: =IF('Monitoring'!H4="","",'Monitoring'!H4) | J62: =IF('Monitoring'!I4="","",'Monitoring'!I4) | ... N62: =IF('Monitoring'!M4="","",'Monitoring'!M4)
A63: =IF('Monitoring'!A5="","",'Monitoring'!A5) | B63: Monitoring | C63: =IF('Monitoring'!B5="","",'Monitoring'!B5) | D63: =IF('Monitoring'!C5="","",'Monitoring'!C5) | E63: =IF('Monitoring'!D5="","",'Monitoring'!D5) | F63: =IF('Monitoring'!E5="","",'Monitoring'!E5) | G63: =IF('Monitoring'!F5="","",'Monitoring'!F5) | H63: =IF('Monitoring'!G5="","",'Monitoring'!G5) | I63: =IF('Monitoring'!H5="","",'Monitoring'!H5) | J63: =IF('Monitoring'!I5="","",'Monitoring'!I5) | ... N63: =IF('Monitoring'!M5="","",'Monitoring'!M5)
A64: =IF('Monitoring'!A6="","",'Monitoring'!A6) | B64: Monitoring | C64: =IF('Monitoring'!B6="","",'Monitoring'!B6) | D64: =IF('Monitoring'!C6="","",'Monitoring'!C6) | E64: =IF('Monitoring'!D6="","",'Monitoring'!D6) | F64: =IF('Monitoring'!E6="","",'Monitoring'!E6) | G64: =IF('Monitoring'!F6="","",'Monitoring'!F6) | H64: =IF('Monitoring'!G6="","",'Monitoring'!G6) | I64: =IF('Monitoring'!H6="","",'Monitoring'!H6) | J64: =IF('Monitoring'!I6="","",'Monitoring'!I6) | ... N64: =IF('Monitoring'!M6="","",'Monitoring'!M6)
A65: =IF('Monitoring'!A7="","",'Monitoring'!A7) | B65: Monitoring | C65: =IF('Monitoring'!B7="","",'Monitoring'!B7) | D65: =IF('Monitoring'!C7="","",'Monitoring'!C7) | E65: =IF('Monitoring'!D7="","",'Monitoring'!D7) | F65: =IF('Monitoring'!E7="","",'Monitoring'!E7) | G65: =IF('Monitoring'!F7="","",'Monitoring'!F7) | H65: =IF('Monitoring'!G7="","",'Monitoring'!G7) | I65: =IF('Monitoring'!H7="","",'Monitoring'!H7) | J65: =IF('Monitoring'!I7="","",'Monitoring'!I7) | ... N65: =IF('Monitoring'!M7="","",'Monitoring'!M7)
A66: =IF('Monitoring'!A8="","",'Monitoring'!A8) | B66: Monitoring | C66: =IF('Monitoring'!B8="","",'Monitoring'!B8) | D66: =IF('Monitoring'!C8="","",'Monitoring'!C8) | E66: =IF('Monitoring'!D8="","",'Monitoring'!D8) | F66: =IF('Monitoring'!E8="","",'Monitoring'!E8) | G66: =IF('Monitoring'!F8="","",'Monitoring'!F8) | H66: =IF('Monitoring'!G8="","",'Monitoring'!G8) | I66: =IF('Monitoring'!H8="","",'Monitoring'!H8) | J66: =IF('Monitoring'!I8="","",'Monitoring'!I8) | ... N66: =IF('Monitoring'!M8="","",'Monitoring'!M8)
A67: =IF('Monitoring'!A9="","",'Monitoring'!A9) | B67: Monitoring | C67: =IF('Monitoring'!B9="","",'Monitoring'!B9) | D67: =IF('Monitoring'!C9="","",'Monitoring'!C9) | E67: =IF('Monitoring'!D9="","",'Monitoring'!D9) | F67: =IF('Monitoring'!E9="","",'Monitoring'!E9) | G67: =IF('Monitoring'!F9="","",'Monitoring'!F9) | H67: =IF('Monitoring'!G9="","",'Monitoring'!G9) | I67: =IF('Monitoring'!H9="","",'Monitoring'!H9) | J67: =IF('Monitoring'!I9="","",'Monitoring'!I9) | ... N67: =IF('Monitoring'!M9="","",'Monitoring'!M9)
A68: =IF('Monitoring'!A10="","",'Monitoring'!A10) | B68: Monitoring | C68: =IF('Monitoring'!B10="","",'Monitoring'!B10) | D68: =IF('Monitoring'!C10="","",'Monitoring'!C10) | E68: =IF('Monitoring'!D10="","",'Monitoring'!D10) | F68: =IF('Monitoring'!E10="","",'Monitoring'!E10) | G68: =IF('Monitoring'!F10="","",'Monitoring'!F10) | H68: =IF('Monitoring'!G10="","",'Monitoring'!G10) | I68: =IF('Monitoring'!H10="","",'Monitoring'!H10) | J68: =IF('Monitoring'!I10="","",'Monitoring'!I10) | ... N68: =IF('Monitoring'!M10="","",'Monitoring'!M10)
A69: =IF('Monitoring'!A11="","",'Monitoring'!A11) | B69: Monitoring | C69: =IF('Monitoring'!B11="","",'Monitoring'!B11) | D69: =IF('Monitoring'!C11="","",'Monitoring'!C11) | E69: =IF('Monitoring'!D11="","",'Monitoring'!D11) | F69: =IF('Monitoring'!E11="","",'Monitoring'!E11) | G69: =IF('Monitoring'!F11="","",'Monitoring'!F11) | H69: =IF('Monitoring'!G11="","",'Monitoring'!G11) | I69: =IF('Monitoring'!H11="","",'Monitoring'!H11) | J69: =IF('Monitoring'!I11="","",'Monitoring'!I11) | ... N69: =IF('Monitoring'!M11="","",'Monitoring'!M11)
A70: =IF('Monitoring'!A12="","",'Monitoring'!A12) | B70: Monitoring | C70: =IF('Monitoring'!B12="","",'Monitoring'!B12) | D70: =IF('Monitoring'!C12="","",'Monitoring'!C12) | E70: =IF('Monitoring'!D12="","",'Monitoring'!D12) | F70: =IF('Monitoring'!E12="","",'Monitoring'!E12) | G70: =IF('Monitoring'!F12="","",'Monitoring'!F12) | H70: =IF('Monitoring'!G12="","",'Monitoring'!G12) | I70: =IF('Monitoring'!H12="","",'Monitoring'!H12) | J70: =IF('Monitoring'!I12="","",'Monitoring'!I12) | ... N70: =IF('Monitoring'!M12="","",'Monitoring'!M12)
A71: =IF('Monitoring'!A13="","",'Monitoring'!A13) | B71: Monitoring | C71: =IF('Monitoring'!B13="","",'Monitoring'!B13) | D71: =IF('Monitoring'!C13="","",'Monitoring'!C13) | E71: =IF('Monitoring'!D13="","",'Monitoring'!D13) | F71: =IF('Monitoring'!E13="","",'Monitoring'!E13) | G71: =IF('Monitoring'!F13="","",'Monitoring'!F13) | H71: =IF('Monitoring'!G13="","",'Monitoring'!G13) | I71: =IF('Monitoring'!H13="","",'Monitoring'!H13) | J71: =IF('Monitoring'!I13="","",'Monitoring'!I13) | ... N71: =IF('Monitoring'!M13="","",'Monitoring'!M13)
A72: =IF('Integration'!A3="","",'Integration'!A3) | B72: Integration | C72: =IF('Integration'!B3="","",'Integration'!B3) | D72: =IF('Integration'!C3="","",'Integration'!C3) | E72: =IF('Integration'!D3="","",'Integration'!D3) | F72: =IF('Integration'!E3="","",'Integration'!E3) | G72: =IF('Integration'!F3="","",'Integration'!F3) | H72: =IF('Integration'!G3="","",'Integration'!G3) | I72: =IF('Integration'!H3="","",'Integration'!H3) | J72: =IF('Integration'!I3="","",'Integration'!I3) | ... N72: =IF('Integration'!M3="","",'Integration'!M3)
A73: =IF('Integration'!A4="","",'Integration'!A4) | B73: Integration | C73: =IF('Integration'!B4="","",'Integration'!B4) | D73: =IF('Integration'!C4="","",'Integration'!C4) | E73: =IF('Integration'!D4="","",'Integration'!D4) | F73: =IF('Integration'!E4="","",'Integration'!E4) | G73: =IF('Integration'!F4="","",'Integration'!F4) | H73: =IF('Integration'!G4="","",'Integration'!G4) | I73: =IF('Integration'!H4="","",'Integration'!H4) | J73: =IF('Integration'!I4="","",'Integration'!I4) | ... N73: =IF('Integration'!M4="","",'Integration'!M4)
A74: =IF('Integration'!A5="","",'Integration'!A5) | B74: Integration | C74: =IF('Integration'!B5="","",'Integration'!B5) | D74: =IF('Integration'!C5="","",'Integration'!C5) | E74: =IF('Integration'!D5="","",'Integration'!D5) | F74: =IF('Integration'!E5="","",'Integration'!E5) | G74: =IF('Integration'!F5="","",'Integration'!F5) | H74: =IF('Integration'!G5="","",'Integration'!G5) | I74: =IF('Integration'!H5="","",'Integration'!H5) | J74: =IF('Integration'!I5="","",'Integration'!I5) | ... N74: =IF('Integration'!M5="","",'Integration'!M5)
A75: =IF('Integration'!A6="","",'Integration'!A6) | B75: Integration | C75: =IF('Integration'!B6="","",'Integration'!B6) | D75: =IF('Integration'!C6="","",'Integration'!C6) | E75: =IF('Integration'!D6="","",'Integration'!D6) | F75: =IF('Integration'!E6="","",'Integration'!E6) | G75: =IF('Integration'!F6="","",'Integration'!F6) | H75: =IF('Integration'!G6="","",'Integration'!G6) | I75: =IF('Integration'!H6="","",'Integration'!H6) | J75: =IF('Integration'!I6="","",'Integration'!I6) | ... N75: =IF('Integration'!M6="","",'Integration'!M6)
A76: =IF('Integration'!A7="","",'Integration'!A7) | B76: Integration | C76: =IF('Integration'!B7="","",'Integration'!B7) | D76: =IF('Integration'!C7="","",'Integration'!C7) | E76: =IF('Integration'!D7="","",'Integration'!D7) | F76: =IF('Integration'!E7="","",'Integration'!E7) | G76: =IF('Integration'!F7="","",'Integration'!F7) | H76: =IF('Integration'!G7="","",'Integration'!G7) | I76: =IF('Integration'!H7="","",'Integration'!H7) | J76: =IF('Integration'!I7="","",'Integration'!I7) | ... N76: =IF('Integration'!M7="","",'Integration'!M7)
A77: =IF('Integration'!A8="","",'Integration'!A8) | B77: Integration | C77: =IF('Integration'!B8="","",'Integration'!B8) | D77: =IF('Integration'!C8="","",'Integration'!C8) | E77: =IF('Integration'!D8="","",'Integration'!D8) | F77: =IF('Integration'!E8="","",'Integration'!E8) | G77: =IF('Integration'!F8="","",'Integration'!F8) | H77: =IF('Integration'!G8="","",'Integration'!G8) | I77: =IF('Integration'!H8="","",'Integration'!H8) | J77: =IF('Integration'!I8="","",'Integration'!I8) | ... N77: =IF('Integration'!M8="","",'Integration'!M8)
A78: =IF('Integration'!A9="","",'Integration'!A9) | B78: Integration | C78: =IF('Integration'!B9="","",'Integration'!B9) | D78: =IF('Integration'!C9="","",'Integration'!C9) | E78: =IF('Integration'!D9="","",'Integration'!D9) | F78: =IF('Integration'!E9="","",'Integration'!E9) | G78: =IF('Integration'!F9="","",'Integration'!F9) | H78: =IF('Integration'!G9="","",'Integration'!G9) | I78: =IF('Integration'!H9="","",'Integration'!H9) | J78: =IF('Integration'!I9="","",'Integration'!I9) | ... N78: =IF('Integration'!M9="","",'Integration'!M9)
A79: =IF('Integration'!A10="","",'Integration'!A10) | B79: Integration | C79: =IF('Integration'!B10="","",'Integration'!B10) | D79: =IF('Integration'!C10="","",'Integration'!C10) | E79: =IF('Integration'!D10="","",'Integration'!D10) | F79: =IF('Integration'!E10="","",'Integration'!E10) | G79: =IF('Integration'!F10="","",'Integration'!F10) | H79: =IF('Integration'!G10="","",'Integration'!G10) | I79: =IF('Integration'!H10="","",'Integration'!H10) | J79: =IF('Integration'!I10="","",'Integration'!I10) | ... N79: =IF('Integration'!M10="","",'Integration'!M10)
A80: =IF('Integration'!A11="","",'Integration'!A11) | B80: Integration | C80: =IF('Integration'!B11="","",'Integration'!B11) | D80: =IF('Integration'!C11="","",'Integration'!C11) | E80: =IF('Integration'!D11="","",'Integration'!D11) | F80: =IF('Integration'!E11="","",'Integration'!E11) | G80: =IF('Integration'!F11="","",'Integration'!F11) | H80: =IF('Integration'!G11="","",'Integration'!G11) | I80: =IF('Integration'!H11="","",'Integration'!H11) | J80: =IF('Integration'!I11="","",'Integration'!I11) | ... N80: =IF('Integration'!M11="","",'Integration'!M11)
A81: =IF('Integration'!A12="","",'Integration'!A12) | B81: Integration | C81: =IF('Integration'!B12="","",'Integration'!B12) | D81: =IF('Integration'!C12="","",'Integration'!C12) | E81: =IF('Integration'!D12="","",'Integration'!D12) | F81: =IF('Integration'!E12="","",'Integration'!E12) | G81: =IF('Integration'!F12="","",'Integration'!F12) | H81: =IF('Integration'!G12="","",'Integration'!G12) | I81: =IF('Integration'!H12="","",'Integration'!H12) | J81: =IF('Integration'!I12="","",'Integration'!I12) | ... N81: =IF('Integration'!M12="","",'Integration'!M12)
A82: =IF('Integration'!A13="","",'Integration'!A13) | B82: Integration | C82: =IF('Integration'!B13="","",'Integration'!B13) | D82: =IF('Integration'!C13="","",'Integration'!C13) | E82: =IF('Integration'!D13="","",'Integration'!D13) | F82: =IF('Integration'!E13="","",'Integration'!E13) | G82: =IF('Integration'!F13="","",'Integration'!F13) | H82: =IF('Integration'!G13="","",'Integration'!G13) | I82: =IF('Integration'!H13="","",'Integration'!H13) | J82: =IF('Integration'!I13="","",'Integration'!I13) | ... N82: =IF('Integration'!M13="","",'Integration'!M13)
A83: =IF('Integration'!A14="","",'Integration'!A14) | B83: Integration | C83: =IF('Integration'!B14="","",'Integration'!B14) | D83: =IF('Integration'!C14="","",'Integration'!C14) | E83: =IF('Integration'!D14="","",'Integration'!D14) | F83: =IF('Integration'!E14="","",'Integration'!E14) | G83: =IF('Integration'!F14="","",'Integration'!F14) | H83: =IF('Integration'!G14="","",'Integration'!G14) | I83: =IF('Integration'!H14="","",'Integration'!H14) | J83: =IF('Integration'!I14="","",'Integration'!I14) | ... N83: =IF('Integration'!M14="","",'Integration'!M14)
... A92: =IF('Integration'!A23="","",'Integration'!A23) | B92: Integration | C92: =IF('Integration'!B23="","",'Integration'!B23) | D92: =IF('Integration'!C23="","",'Integration'!C23) | E92: =IF('Integration'!D23="","",'Integration'!D23) | F92: =IF('Integration'!E23="","",'Integration'!E23) | G92: =IF('Integration'!F23="","",'Integration'!F23) | H92: =IF('Integration'!G23="","",'Integration'!G23) | I92: =IF('Integration'!H23="","",'Integration'!H23) | J92: =IF('Integration'!I23="","",'Integration'!I23) | ... N92: =IF('Integration'!M23="","",'Integration'!M23)
A93: =IF('Operations'!A3="","",'Operations'!A3) | B93: Operations | C93: =IF('Operations'!B3="","",'Operations'!B3) | D93: =IF('Operations'!C3="","",'Operations'!C3) | E93: =IF('Operations'!D3="","",'Operations'!D3) | F93: =IF('Operations'!E3="","",'Operations'!E3) | G93: =IF('Operations'!F3="","",'Operations'!F3) | H93: =IF('Operations'!G3="","",'Operations'!G3) | I93: =IF('Operations'!H3="","",'Operations'!H3) | J93: =IF('Operations'!I3="","",'Operations'!I3) | ... N93: =IF('Operations'!M3="","",'Operations'!M3)
A94: =IF('Operations'!A4="","",'Operations'!A4) | B94: Operations | C94: =IF('Operations'!B4="","",'Operations'!B4) | D94: =IF('Operations'!C4="","",'Operations'!C4) | E94: =IF('Operations'!D4="","",'Operations'!D4) | F94: =IF('Operations'!E4="","",'Operations'!E4) | G94: =IF('Operations'!F4="","",'Operations'!F4) | H94: =IF('Operations'!G4="","",'Operations'!G4) | I94: =IF('Operations'!H4="","",'Operations'!H4) | J94: =IF('Operations'!I4="","",'Operations'!I4) | ... N94: =IF('Operations'!M4="","",'Operations'!M4)
A95: =IF('Operations'!A5="","",'Operations'!A5) | B95: Operations | C95: =IF('Operations'!B5="","",'Operations'!B5) | D95: =IF('Operations'!C5="","",'Operations'!C5) | E95: =IF('Operations'!D5="","",'Operations'!D5) | F95: =IF('Operations'!E5="","",'Operations'!E5) | G95: =IF('Operations'!F5="","",'Operations'!F5) | H95: =IF('Operations'!G5="","",'Operations'!G5) | I95: =IF('Operations'!H5="","",'Operations'!H5) | J95: =IF('Operations'!I5="","",'Operations'!I5) | ... N95: =IF('Operations'!M5="","",'Operations'!M5)
A96: =IF('Operations'!A6="","",'Operations'!A6) | B96: Operations | C96: =IF('Operations'!B6="","",'Operations'!B6) | D96: =IF('Operations'!C6="","",'Operations'!C6) | E96: =IF('Operations'!D6="","",'Operations'!D6) | F96: =IF('Operations'!E6="","",'Operations'!E6) | G96: =IF('Operations'!F6="","",'Operations'!F6) | H96: =IF('Operations'!G6="","",'Operations'!G6) | I96: =IF('Operations'!H6="","",'Operations'!H6) | J96: =IF('Operations'!I6="","",'Operations'!I6) | ... N96: =IF('Operations'!M6="","",'Operations'!M6)
A97: =IF('Operations'!A7="","",'Operations'!A7) | B97: Operations | C97: =IF('Operations'!B7="","",'Operations'!B7) | D97: =IF('Operations'!C7="","",'Operations'!C7) | E97: =IF('Operations'!D7="","",'Operations'!D7) | F97: =IF('Operations'!E7="","",'Operations'!E7) | G97: =IF('Operations'!F7="","",'Operations'!F7) | H97: =IF('Operations'!G7="","",'Operations'!G7) | I97: =IF('Operations'!H7="","",'Operations'!H7) | J97: =IF('Operations'!I7="","",'Operations'!I7) | ... N97: =IF('Operations'!M7="","",'Operations'!M7)
A98: =IF('Operations'!A8="","",'Operations'!A8) | B98: Operations | C98: =IF('Operations'!B8="","",'Operations'!B8) | D98: =IF('Operations'!C8="","",'Operations'!C8) | E98: =IF('Operations'!D8="","",'Operations'!D8) | F98: =IF('Operations'!E8="","",'Operations'!E8) | G98: =IF('Operations'!F8="","",'Operations'!F8) | H98: =IF('Operations'!G8="","",'Operations'!G8) | I98: =IF('Operations'!H8="","",'Operations'!H8) | J98: =IF('Operations'!I8="","",'Operations'!I8) | ... N98: =IF('Operations'!M8="","",'Operations'!M8)
A99: =IF('Operations'!A9="","",'Operations'!A9) | B99: Operations | C99: =IF('Operations'!B9="","",'Operations'!B9) | D99: =IF('Operations'!C9="","",'Operations'!C9) | E99: =IF('Operations'!D9="","",'Operations'!D9) | F99: =IF('Operations'!E9="","",'Operations'!E9) | G99: =IF('Operations'!F9="","",'Operations'!F9) | H99: =IF('Operations'!G9="","",'Operations'!G9) | I99: =IF('Operations'!H9="","",'Operations'!H9) | J99: =IF('Operations'!I9="","",'Operations'!I9) | ... N99: =IF('Operations'!M9="","",'Operations'!M9)
A100: =IF('Operations'!A10="","",'Operations'!A10) | B100: Operations | C100: =IF('Operations'!B10="","",'Operations'!B10) | D100: =IF('Operations'!C10="","",'Operations'!C10) | E100: =IF('Operations'!D10="","",'Operations'!D10) | F100: =IF('Operations'!E10="","",'Operations'!E10) | G100: =IF('Operations'!F10="","",'Operations'!F10) | H100: =IF('Operations'!G10="","",'Operations'!G10) | I100: =IF('Operations'!H10="","",'Operations'!H10) | J100: =IF('Operations'!I10="","",'Operations'!I10) | ... N100: =IF('Operations'!M10="","",'Operations'!M10)
A101: =IF('Operations'!A11="","",'Operations'!A11) | B101: Operations | C101: =IF('Operations'!B11="","",'Operations'!B11) | D101: =IF('Operations'!C11="","",'Operations'!C11) | E101: =IF('Operations'!D11="","",'Operations'!D11) | F101: =IF('Operations'!E11="","",'Operations'!E11) | G101: =IF('Operations'!F11="","",'Operations'!F11) | H101: =IF('Operations'!G11="","",'Operations'!G11) | I101: =IF('Operations'!H11="","",'Operations'!H11) | J101: =IF('Operations'!I11="","",'Operations'!I11) | ... N101: =IF('Operations'!M11="","",'Operations'!M11)
A102: =IF('Operations'!A12="","",'Operations'!A12) | B102: Operations | C102: =IF('Operations'!B12="","",'Operations'!B12) | D102: =IF('Operations'!C12="","",'Operations'!C12) | E102: =IF('Operations'!D12="","",'Operations'!D12) | F102: =IF('Operations'!E12="","",'Operations'!E12) | G102: =IF('Operations'!F12="","",'Operations'!F12) | H102: =IF('Operations'!G12="","",'Operations'!G12) | I102: =IF('Operations'!H12="","",'Operations'!H12) | J102: =IF('Operations'!I12="","",'Operations'!I12) | ... N102: =IF('Operations'!M12="","",'Operations'!M12)
A103: =IF('Operations'!A13="","",'Operations'!A13) | B103: Operations | C103: =IF('Operations'!B13="","",'Operations'!B13) | D103: =IF('Operations'!C13="","",'Operations'!C13) | E103: =IF('Operations'!D13="","",'Operations'!D13) | F103: =IF('Operations'!E13="","",'Operations'!E13) | G103: =IF('Operations'!F13="","",'Operations'!F13) | H103: =IF('Operations'!G13="","",'Operations'!G13) | I103: =IF('Operations'!H13="","",'Operations'!H13) | J103: =IF('Operations'!I13="","",'Operations'!I13) | ... N103: =IF('Operations'!M13="","",'Operations'!M13)
A104: =IF('Operations'!A14="","",'Operations'!A14) | B104: Operations | C104: =IF('Operations'!B14="","",'Operations'!B14) | D104: =IF('Operations'!C14="","",'Operations'!C14) | E104: =IF('Operations'!D14="","",'Operations'!D14) | F104: =IF('Operations'!E14="","",'Operations'!E14) | G104: =IF('Operations'!F14="","",'Operations'!F14) | H104: =IF('Operations'!G14="","",'Operations'!G14) | I104: =IF('Operations'!H14="","",'Operations'!H14) | J104: =IF('Operations'!I14="","",'Operations'!I14) | ... N104: =IF('Operations'!M14="","",'Operations'!M14)

Sheet Project
A1: Project Parameters
A2: Parameter Name | B2: Production | C2: Test | D2: DR | E2: Description | F2: Required | G2: Data Type | H2: Validation Rules | I2: Security Level | J2: Owner Team | K2: Dependencies | L2: Notes | M2: Last Updated
A3: solution.name | B3: amatra-isb | C3: amatra-isb | D3: amatra-isb | E3: Solution identifier used for all resource naming and tagging | F3: Yes | G3: String | H3: lowercase alphanumeric hyphens only max 20 chars | I3: Public | J3: Cloud CoE | M3: 2026-07-01
A4: solution.region.primary | B4: us-west-2 | C4: us-west-2 | D4: us-west-2 | E4: Primary AWS region for all solution resources; enforces US data residency per SOW | F4: Yes | G4: String | H4: Valid AWS region code | I4: Public | J4: Cloud CoE | L4: Single region per SOW scope; SCP blocks replication outside us-east-1 and us-west-2 | M4: 2026-07-01
A5: solution.environment | B5: prod | C5: dev | D5: prod | E5: Deployment environment identifier used in resource naming and IAM policies | F5: Yes | G5: String | H5: prod|staging|dev | I5: Public | J5: Cloud CoE | L5: DR not applicable — single-region serverless per SOW out-of-scope clause | M5: 2026-07-01
A6: solution.opportunity_id | B6: OPP-2026-001 | C6: OPP-2026-001 | D6: OPP-2026-001 | E6: Opportunity identifier for cost tracking and tagging | F6: Yes | G6: String | H6: Alphanumeric hyphens format OPP-YYYY-NNN | I6: Public | J6: Cloud CoE | L6: Used as CostCenter tag value across all AWS resources | M6: 2026-07-01
A7: solution.version | B7: 1.0.0 | C7: 1.0.0 | D7: 1.0.0 | E7: Current platform version used in Lambda aliases and deployment tracking | F7: Yes | G7: String | H7: Semantic versioning X.Y.Z | I7: Public | J7: Cloud CoE | L7: Updated at each phase gate approval by CTO | M7: 2026-07-01
A8: aws.account_id | B8: [aws-account-id] | C8: [aws-account-id] | D8: [aws-account-id] | E8: 12-digit AWS account ID for the target deployment account | F8: Yes | G8: String | H8: 12-digit numeric string | I8: Confidential | J8: Cloud CoE | L8: Separate account IDs per environment recommended; VP Engineering provisions | M8: 2026-07-01
A9: aws.region | B9: us-west-2 | C9: us-west-2 | D9: us-west-2 | E9: AWS region for all resource provisioning; must match solution.region.primary | F9: Yes | G9: String | H9: Valid AWS region code | I9: Public | J9: Cloud CoE | K9: solution.region.primary | L9: Must always equal solution.region.primary; validated in CI/CD pipeline pre-deploy check | M9: 2026-07-01

Sheet Security
A1: Security Parameters
A2: Parameter Name | B2: Production | C2: Test | D2: DR | E2: Description | F2: Required | G2: Data Type | H2: Validation Rules | I2: Security Level | J2: Owner Team | K2: Dependencies | L2: Notes | M2: Last Updated
A3: security.cognito.user_pool_id | B3: [cognito-user-pool-id] | C3: [cognito-user-pool-id] | D3: [cognito-user-pool-id] | E3: Amazon Cognito User Pool ID for all platform user authentication | F3: Yes | G3: String | H3: Format: {region}_[A-Za-z0-9]+ | I3: Secret | J3: Security Team | K3: aws.region | L3: Provisioned in Phase 1 Month 2; replaces Okta as IdP; ~50 migrated users initially scaling to ~120 | M3: 2026-07-01
A4: security.cognito.user_pool_client_id | B4: [cognito-app-client-id] | C4: [cognito-app-client-id] | D4: [cognito-app-client-id] | E4: Cognito App Client ID used by API Gateway Cognito authoriser for JWT token validation | F4: Yes | G4: String | H4: Alphanumeric 26-char string | I4: Secret | J4: Security Team | K4: security.cognito.user_pool_id | L4: Do not expose in client-side code; referenced by API Gateway authoriser only | M4: 2026-07-01
A5: security.cognito.admin_group_name | B5: AmAdmin | C5: AmAdmin | D5: AmAdmin | E5: Cognito group name for platform administrators with usage-limit override capability | F5: Yes | G5: String | H5: Alphanumeric max 128 chars | I5: Public | J5: Security Team | K5: security.cognito.user_pool_id | L5: MFA (TOTP) enforced for all members of this group per SOC 2 CC6 control | M5: 2026-07-01
A6: security.cognito.presales_group_name | B6: PreSales | C6: PreSales | D6: PreSales | E6: Cognito group name for pre-sales consultants (Phase 1 artifact types only) | F6: Yes | G6: String | H6: Alphanumeric max 128 chars | I6: Public | J6: Security Team | K6: security.cognito.user_pool_id | L6: Access scoped to 4 Phase 1 artifact types; expanded to Delivery group post-Phase 2 | M6: 2026-07-01
A7: security.cognito.delivery_group_name | B7: Delivery | C7: Delivery | D7: Delivery | E7: Cognito group name for delivery consultants with access to all 7 artifact types | F7: Yes | G7: String | H7: Alphanumeric max 128 chars | I7: Public | J7: Security Team | K7: security.cognito.user_pool_id | L7: Activated in Phase 2; maps to full artifact_types list in application.artifact_types | M7: 2026-07-01
A8: security.cognito.mfa_enforcement | B8: OPTIONAL | C8: OPTIONAL | D8: OPTIONAL | E8: Cognito MFA enforcement level for PreSales and Delivery groups | F8: Yes | G8: String | H8: OFF|OPTIONAL|REQUIRED | I8: Public | J8: Security Team | K8: security.cognito.user_pool_id | L8: AmAdmin group enforces MFA via Cognito group policy regardless of this setting; Phase 3 tightens to REQUIRED | M8: 2026-07-01
A9: security.cognito.token_expiry_minutes | B9: 15 | C9: 60 | D9: 15 | E9: Access token validity in minutes for Cognito-issued JWTs | F9: Yes | G9: Integer | H9: 5-1440 | I9: Public | J9: Security Team | K9: security.cognito.user_pool_id | L9: 15-min Prod expiry limits blast radius of stolen tokens; refresh token is 30 days | M9: 2026-07-01
A10: security.kms.s3_key_id | B10: [kms-s3-artifacts-key-id] | C10: [kms-s3-artifacts-key-id] | D10: [kms-s3-artifacts-key-id] | E10: KMS Customer Managed Key ID for S3 artifacts bucket encryption | F10: Yes | G10: String | H10: Valid KMS key ID or ARN | I10: Secret | J10: Security Team | K10: aws.region | L10: Store in Secrets Manager; annual rotation enabled; key policy denies all but named IAM roles | M10: 2026-07-01
A11: security.kms.dynamodb_key_id | B11: [kms-dynamodb-key-id] | C11: [kms-dynamodb-key-id] | D11: [kms-dynamodb-key-id] | E11: KMS Customer Managed Key ID for DynamoDB table encryption | F11: Yes | G11: String | H11: Valid KMS key ID or ARN | I11: Secret | J11: Security Team | K11: aws.region | L11: Separate CMK from S3 key; annual rotation enabled; used by both DynamoDB tables | M11: 2026-07-01
A12: security.kms.cloudtrail_key_id | B12: [kms-cloudtrail-key-id] | C12: [kms-cloudtrail-key-id] | D12: [kms-cloudtrail-key-id] | E12: KMS Customer Managed Key ID for CloudTrail log bucket encryption | F12: Yes | G12: String | H12: Valid KMS key ID or ARN | I12: Secret | J12: Security Team | K12: aws.region | L12: Root user explicitly denied usage in key policy per SOC 2 WORM requirement | M12: 2026-07-01
A13: security.kms.secrets_manager_key_id | B13: [kms-secrets-manager-key-id] | C13: [kms-secrets-manager-key-id] | D13: [kms-secrets-manager-key-id] | E13: KMS Customer Managed Key ID for Secrets Manager secret encryption | F13: Yes | G13: String | H13: Valid KMS key ID or ARN | I13: Secret | J13: Security Team | K13: aws.region | L13: Annual rotation enabled; fourth dedicated CMK per SOW security design | M13: 2026-07-01
... A15: security.waf.rate_limit_per_ip_per_5min | B15: 2000 | C15: 500 | D15: 2000 | E15: WAF rate-based rule threshold: maximum requests per IP per 5-minute window | F15: Yes | G15: Integer | H15: 100-100000 | I15: Public | J15: Security Team | K15: security.waf.web_acl_arn | L15: Aligned to API Gateway stage throttle; prevents per-IP abuse while allowing burst for internal users | M15: 2026-07-01
A16: security.s3.block_public_access | B16: true | C16: true | D16: true | E16: Enforce S3 Block Public Access at the AWS account level | F16: Yes | G16: Boolean | H16: true|false | I16: Public | J16: Security Team | L16: Must be true in all environments; enforced via AWS Config rule and SCP | M16: 2026-07-01
A17: security.guardduty_enabled | B17: true | C17: true | D17: true | E17: Enable AWS GuardDuty for continuous threat detection across the account | F17: Yes | G17: Boolean | H17: true|false | I17: Public | J17: Security Team | L17: GuardDuty high-severity findings trigger automated Lambda remediation per SOW security design | M17: 2026-07-01
A18: security.securityhub_enabled | B18: true | C18: true | D18: true | E18: Enable AWS Security Hub to aggregate GuardDuty and Config findings | F18: Yes | G18: Boolean | H18: true|false | I18: Public | J18: Security Team | K18: security.guardduty_enabled | L18: Reviewed weekly by Security & Compliance Lead; required for SOC 2 CC7 control evidence | M18: 2026-07-01
A19: security.cloudtrail_enabled | B19: true | C19: true | D19: true | E19: Enable AWS CloudTrail for all management events and S3 data events | F19: Yes | G19: Boolean | H19: true|false | I19: Public | J19: Security Team | K19: storage.s3.cloudtrail_bucket_name | L19: CloudTrail with S3 Object Lock is the primary SOC 2 audit trail; must be enabled before Phase 1 go-live | M19: 2026-07-01
A20: security.cloudtrail_retention_years | B20: 7 | C20: 1 | D20: 7 | E20: Retention period in years for CloudTrail logs in the S3 audit bucket (Object Lock Compliance mode) | F20: Yes | G20: Integer | H20: 1-10 | I20: Public | J20: Security Team | K20: storage.s3.cloudtrail_bucket_name | L20: 7-year retention meets SOC 2 and enterprise client contractual requirements | M20: 2026-07-01
A21: security.session_timeout_minutes | B21: 30 | C21: 60 | D21: 30 | E21: Inactive session timeout in minutes enforced by Cognito app client | F21: Yes | G21: Integer | H21: 5-480 | I21: Public | J21: Security Team | K21: security.cognito.user_pool_id | L21: 30-min Prod timeout aligns to SOC 2 CC6 access control requirements | M21: 2026-07-01

Sheet Compute
A1: Compute Parameters
A2: Parameter Name | B2: Production | C2: Test | D2: DR | E2: Description | F2: Required | G2: Data Type | H2: Validation Rules | I2: Security Level | J2: Owner Team | K2: Dependencies | L2: Notes | M2: Last Updated
A3: compute.lambda.runtime | B3: python3.12 | C3: python3.12 | D3: python3.12 | E3: Python runtime version for all Lambda functions | F3: Yes | G3: String | H3: python3.12|python3.11 | I3: Public | J3: Development | L3: Python 3.12 is team standard per SOW; all boto3 calls use this runtime | M3: 2026-07-01
A4: compute.lambda.api_submit.memory_mb | B4: 512 | C4: 512 | D4: 512 | E4: Memory allocation in MB for the brief-submission API Handler Lambda (isb-api-submit) | F4: Yes | G4: Integer | H4: 128-10240 | I4: Public | J4: Development | K4: compute.lambda.runtime | L4: 512 MB sufficient for JSON validation and DynamoDB/SQS write; provisioned concurrency covers cold-start | M4: 2026-07-01
A5: compute.lambda.api_submit.timeout_seconds | B5: 30 | C5: 30 | D5: 30 | E5: Timeout in seconds for the brief-submission API Handler Lambda | F5: Yes | G5: Integer | H5: 1-900 | I5: Public | J5: Development | K5: compute.lambda.api_submit.memory_mb | L5: Must be less than API Gateway integration timeout of 29 s; synchronous path only | M5: 2026-07-01
A6: compute.lambda.api_submit.provisioned_concurrency | B6: 5 | C6: 0 | D6: 5 | E6: Provisioned concurrency units for isb-api-submit to eliminate cold-start on latency-sensitive path | F6: Yes | G6: Integer | H6: 0-100 | I6: Public | J6: Development | K6: compute.lambda.api_submit.memory_mb | L6: Provisioned in Prod only; Dev uses on-demand; targets ≤500 ms p99 API response SLA | M6: 2026-07-01
A7: compute.lambda.bedrock_sonnet.memory_mb | B7: 1024 | C7: 1024 | D7: 1024 | E7: Memory allocation in MB for the Bedrock Invoker Lambda for Claude 3 Sonnet (complex artifact types) | F7: Yes | G7: Integer | H7: 128-10240 | I7: Public | J7: Development | K7: compute.lambda.runtime | L7: 1024 MB required for large prompt assembly and response buffering for complex artifact types | M7: 2026-07-01
A8: compute.lambda.bedrock_sonnet.timeout_seconds | B8: 900 | C8: 900 | D8: 900 | E8: Timeout in seconds for the Bedrock Invoker Lambda for Claude 3 Sonnet | F8: Yes | G8: Integer | H8: 1-900 | I8: Public | J8: Development | K8: compute.lambda.bedrock_sonnet.memory_mb | L8: 900 s (Lambda max) required; Step Functions TaskToken callback prevents blocking | M8: 2026-07-01
A9: compute.lambda.bedrock_haiku.memory_mb | B9: 512 | C9: 512 | D9: 512 | E9: Memory allocation in MB for the Bedrock Invoker Lambda for Claude 3 Haiku (lightweight artifact types) | F9: Yes | G9: Integer | H9: 128-10240 | I9: Public | J9: Development | K9: compute.lambda.runtime | L9: 512 MB sufficient for Haiku; lower-cost path for discovery questionnaire type | M9: 2026-07-01
A10: compute.lambda.bedrock_haiku.timeout_seconds | B10: 600 | C10: 600 | D10: 600 | E10: Timeout in seconds for the Bedrock Invoker Lambda for Claude 3 Haiku | F10: Yes | G10: Integer | H10: 1-900 | I10: Public | J10: Development | K10: compute.lambda.bedrock_haiku.memory_mb | L10: 600 s sufficient for Haiku generation; reduces Lambda execution cost vs Sonnet | M10: 2026-07-01
A11: compute.lambda.artifact_processor.memory_mb | B11: 512 | C11: 512 | D11: 512 | E11: Memory allocation in MB for the Artifact Processor / QA scoring Lambda | F11: Yes | G11: Integer | H11: 128-10240 | I11: Public | J11: Development | K11: compute.lambda.runtime | L11: 512 MB covers QA rubric scoring and S3 write; increased to 1024 MB if Phase 2 QA logic grows | M11: 2026-07-01
A12: compute.lambda.artifact_processor.timeout_seconds | B12: 300 | C12: 300 | D12: 300 | E12: Timeout in seconds for the Artifact Processor / QA scoring Lambda | F12: Yes | G12: Integer | H12: 1-900 | I12: Public | J12: Development | K12: compute.lambda.artifact_processor.memory_mb | M12: 2026-07-01
A13: compute.lambda.reserved_concurrency_total | B13: 500 | C13: 100 | D13: 500 | E13: Total reserved Lambda concurrency across all platform functions to prevent account-level starvation | F13: Yes | G13: Integer | H13: 10-3000 | I13: Public | J13: Development | K13: compute.lambda.api_submit.provisioned_concurrency | L13: Protects other AWS account workloads; sized for 24 concurrent generation jobs with headroom | M13: 2026-07-01

Sheet Storage
A1: Storage Parameters
A2: Parameter Name | B2: Production | C2: Test | D2: DR | E2: Description | F2: Required | G2: Data Type | H2: Validation Rules | I2: Security Level | J2: Owner Team | K2: Dependencies | L2: Notes | M2: Last Updated
A3: storage.s3.artifacts_bucket_name | B3: [amatra-isb-artifacts-prod-account-id] | C3: [amatra-isb-artifacts-dev-account-id] | D3: [amatra-isb-artifacts-prod-account-id] | E3: S3 bucket name for all generated artifacts stored under structured key taxonomy | F3: Yes | G3: String | H3: Globally unique; lowercase alphanumeric hyphens | I3: Confidential | J3: Operations | K3: aws.account_id | L3: Globally unique; includes account ID suffix per naming convention; Block Public Access enforced | M3: 2026-07-01
A4: storage.s3.cloudtrail_bucket_name | B4: [amatra-isb-cloudtrail-logs-prod] | C4: [amatra-isb-cloudtrail-logs-dev] | D4: [amatra-isb-cloudtrail-logs-prod] | E4: S3 bucket name for immutable CloudTrail audit logs with Object Lock (WORM) | F4: Yes | G4: String | H4: Globally unique; lowercase alphanumeric hyphens | I4: Confidential | J4: Security Team | K4: aws.account_id | L4: Object Lock Compliance mode; 7-year retention; root user deny on CMK per SOC 2 requirement | M4: 2026-07-01
A5: storage.s3.templates_bucket_name | B5: [amatra-isb-templates-prod] | C5: [amatra-isb-templates-dev] | D5: [amatra-isb-templates-prod] | E5: S3 bucket name for Bedrock prompt templates and ingested legacy Word/Excel/PPT templates | F5: Yes | G5: String | H5: Globally unique; lowercase alphanumeric hyphens | I5: Confidential | J5: Development | K5: aws.account_id | L5: Versioned objects; prompt templates committed to GitHub as source of truth and synced to S3 on deploy | M5: 2026-07-01
A6: storage.s3.artifacts_lifecycle_standard_days | B6: 180 | C6: 30 | D6: 180 | E6: Days before artifacts are transitioned from S3 Standard to S3 Glacier Flexible Retrieval | F6: Yes | G6: Integer | H6: 30-3650 | I6: Public | J6: Operations | K6: storage.s3.artifacts_bucket_name | L6: Reduces long-term storage cost by ~80%; aligns to SOW data retention policy | M6: 2026-07-01
A7: storage.s3.versioning_enabled | B7: true | C7: true | D7: true | E7: Enable S3 versioning on the artifacts bucket to protect against accidental deletion | F7: Yes | G7: Boolean | H7: true|false | I7: Public | J7: Operations | K7: storage.s3.artifacts_bucket_name | L7: Required for S3 Object-level audit in CloudTrail and GDPR right-to-erasure version history | M7: 2026-07-01
A8: storage.s3.encryption_key_alias | B8: alias/amatra-isb-s3-artifacts-prod | C8: alias/amatra-isb-s3-artifacts-dev | D8: alias/amatra-isb-s3-artifacts-prod | E8: KMS CMK alias used for SSE-KMS encryption on the artifacts bucket | F8: Yes | G8: String | H8: Valid KMS alias format: alias/[a-zA-Z0-9/_-]+ | I8: Secret | J8: Security Team | K8: security.kms.s3_key_id | L8: Unencrypted PutObject requests denied by bucket policy; annual key rotation enabled | M8: 2026-07-01

Sheet Database
A1: Database Parameters
A2: Parameter Name | B2: Production | C2: Test | D2: DR | E2: Description | F2: Required | G2: Data Type | H2: Validation Rules | I2: Security Level | J2: Owner Team | K2: Dependencies | L2: Notes | M2: Last Updated
A3: database.solution_state_table | B3: AmatraISB-SolutionState-Prod | C3: AmatraISB-SolutionState-Dev | D3: AmatraISB-SolutionState-Prod | E3: DynamoDB table name for tracking solution job status and artifact S3 keys | F3: Yes | G3: String | H3: Alphanumeric hyphens max 255 chars | I3: Confidential | J3: Database Team | K3: aws.region | L3: Table naming follows AmatraISB-{TableName}-{Env} convention from detailed design | M3: 2026-07-01
A4: database.usage_tracking_table | B4: AmatraISB-UsageTracking-Prod | C4: AmatraISB-UsageTracking-Dev | D4: AmatraISB-UsageTracking-Prod | E4: DynamoDB table name for per-user and global monthly generation usage counters | F4: Yes | G4: String | H4: Alphanumeric hyphens max 255 chars | I4: Confidential | J4: Database Team | K4: aws.region | L4: Enforces per-user and global monthly limits; read before every job submission | M4: 2026-07-01
A5: database.billing_mode | B5: PAY_PER_REQUEST | C5: PAY_PER_REQUEST | D5: PAY_PER_REQUEST | E5: DynamoDB capacity billing mode for both tables | F5: Yes | G5: String | H5: PAY_PER_REQUEST|PROVISIONED | I5: Public | J5: Database Team | L5: On-demand selected per SOW; scales automatically with up to 24 concurrent jobs; no reserved capacity | M5: 2026-07-01
A6: database.pitr_enabled | B6: true | C6: false | D6: true | E6: Enable DynamoDB Point-in-Time Recovery on both tables | F6: Yes | G6: Boolean | H6: true|false | I6: Public | J6: Database Team | K6: database.solution_state_table | L6: PITR required in Prod to meet RPO ≤15 min target; disabled in Dev to reduce cost | M6: 2026-07-01
A7: database.ttl_solution_state_days | B7: 365 | C7: 30 | D7: 365 | E7: DynamoDB TTL in days for COMPLETE SolutionState records | F7: Yes | G7: Integer | H7: 1-3653 | I7: Public | J7: Database Team | K7: database.solution_state_table | L7: FAILED records exempt from TTL pending investigation; GDPR right-to-erasure enforced via admin Lambda | M7: 2026-07-01
A8: database.ttl_usage_tracking_days | B8: 365 | C8: 30 | D8: 365 | E8: DynamoDB TTL in days for UsageTracking records | F8: Yes | G8: Integer | H8: 1-3653 | I8: Public | J8: Database Team | K8: database.usage_tracking_table | L8: Supports GDPR right-to-erasure; 365 days sufficient for annual usage reporting | M8: 2026-07-01
A9: database.encryption_key_alias | B9: alias/amatra-isb-dynamodb-prod | C9: alias/amatra-isb-dynamodb-dev | D9: alias/amatra-isb-dynamodb-prod | E9: KMS CMK alias used for DynamoDB at-rest encryption on both tables | F9: Yes | G9: String | H9: Valid KMS alias format: alias/[a-zA-Z0-9/_-]+ | I9: Secret | J9: Security Team | K9: security.kms.dynamodb_key_id | L9: Separate CMK per environment; annual automatic key rotation enabled per SOW | M9: 2026-07-01

Sheet Application
A1: Application Parameters
A2: Parameter Name | B2: Production | C2: Test | D2: DR | E2: Description | F2: Required | G2: Data Type | H2: Validation Rules | I2: Security Level | J2: Owner Team | K2: Dependencies | L2: Notes | M2: Last Updated
A3: application.name | B3: amatra-isb | C3: amatra-isb | D3: amatra-isb | E3: Application identifier used in CloudWatch log group names and Datadog APM service name | F3: Yes | G3: String | H3: Alphanumeric hyphens max 50 chars | I3: Public | J3: Development | K3: solution.name | M3: 2026-07-01
A4: application.log_level | B4: info | C4: debug | D4: info | E4: Lambda function logging verbosity level | F4: Yes | G4: String | H4: debug|info|warn|error | I4: Public | J4: Operations | L4: Set to debug in Dev to aid prompt engineering; info in Prod reduces log volume and CloudWatch cost | M4: 2026-07-01
A5: application.artifact_types | B5: discovery-questionnaire,solution-briefing,statement-of-work,infrastructure-costs,detailed-design,implementation-guide,terraform | C5: discovery-questionnaire,solution-briefing,statement-of-work,infrastructure-costs,detailed-design,implementation-guide,terraform | D5: discovery-questionnaire,solution-briefing,statement-of-work,infrastructure-costs,detailed-design,implementation-guide,terraform | E5: Comma-separated list of the 7 automated artifact types supported by the generation pipeline | F5: Yes | G5: List(String) | H5: Each item must match a registered artifact type in the prompt library | I5: Public | J5: Development | L5: Phase 1 enables first 4 types; Phase 2 enables remaining 3; validated against prompt-library at startup | M5: 2026-07-01
A6: application.api_version | B6: v1 | C6: v1 | D6: v1 | E6: REST API version prefix used in all endpoint paths (/api/v1/) | F6: Yes | G6: String | H6: vN where N is a positive integer | I6: Public | J6: Development | K6: application.name | M6: 2026-07-01
A7: application.presigned_url_ttl_seconds | B7: 86400 | C7: 86400 | D7: 86400 | E7: Expiry time in seconds for S3 presigned artifact download URLs | F7: Yes | G7: Integer | H7: 3600-604800 | I7: Public | J7: Development | K7: storage.s3.artifacts_bucket_name | L7: 24-hour TTL per detailed design; clients must re-request if TTL expires | M7: 2026-07-01
A8: application.max_brief_size_kb | B8: 512 | C8: 512 | D8: 512 | E8: Maximum allowed client brief JSON payload size in kilobytes | F8: Yes | G8: Integer | H8: 64-1024 | I8: Public | J8: Development | L8: Enforced by API Gateway request validator; rejects oversized briefs before Lambda invocation | M8: 2026-07-01

Sheet Monitoring
A1: Monitoring Parameters
A2: Parameter Name | B2: Production | C2: Test | D2: DR | E2: Description | F2: Required | G2: Data Type | H2: Validation Rules | I2: Security Level | J2: Owner Team | K2: Dependencies | L2: Notes | M2: Last Updated
A3: monitoring.cloudwatch.operations_dashboard | B3: amatra-isb-operations-prod | C3: amatra-isb-operations-dev | D3: amatra-isb-operations-prod | E3: CloudWatch dashboard name for real-time async job queue depth and Lambda error rates | F3: Yes | G3: String | H3: Non-empty string max 255 chars | I3: Public | J3: Operations | K3: aws.region | L3: One of 3 CloudWatch dashboards per detailed design; JSON definitions delivered in handover package | M3: 2026-07-01
A4: monitoring.cloudwatch.sla_dashboard | B4: amatra-isb-sla-prod | C4: amatra-isb-sla-dev | D4: amatra-isb-sla-prod | E4: CloudWatch dashboard name for monthly availability percentage and job completion rate vs SLA targets | F4: Yes | G4: String | H4: Non-empty string max 255 chars | I4: Public | J4: Operations | K4: aws.region | L4: Tracks 99.9% availability and ≤60 min job completion SLA; reviewed by VP Engineering weekly | M4: 2026-07-01
A5: monitoring.cloudwatch.quality_dashboard | B5: amatra-isb-quality-prod | C5: amatra-isb-quality-dev | D5: amatra-isb-quality-prod | E5: CloudWatch dashboard name for QA first-pass acceptance rate and Bedrock token consumption | F5: Yes | G5: String | H5: Non-empty string max 255 chars | I5: Public | J5: Operations | K5: aws.region | L5: Tracks ≥90% QA first-pass target and monthly token budget; token P3 alarm fires at 80% consumed | M5: 2026-07-01
A6: monitoring.cloudwatch.log_retention_days | B6: 90 | C6: 30 | D6: 90 | E6: Retention period in days for all Lambda function CloudWatch Log Groups | F6: Yes | G6: Integer | H6: 1-3653 | I6: Public | J6: Operations | L6: 90 days balances cost and investigation window; structured JSON format enables Log Insights queries | M6: 2026-07-01
A7: monitoring.sns.alerts_topic_arn | B7: [sns-alerts-topic-arn] | C7: [sns-alerts-topic-arn] | D7: [sns-alerts-topic-arn] | E7: SNS topic ARN for operational alerts routing to PagerDuty (P1) and Slack (P2) | F7: Yes | G7: String | H7: Valid SNS ARN | I7: Confidential | J7: Operations | K7: aws.region | L7: All CloudWatch alarms route to this topic; subscriptions: PagerDuty P1 / Slack #amatra-isb-ops P2 | M7: 2026-07-01
A8: monitoring.alarm.job_failure_rate_threshold_pct | B8: 5 | C8: 10 | D8: 5 | E8: Async job failure rate percentage threshold that triggers a P1 PagerDuty alert | F8: Yes | G8: Integer | H8: 1-100 | I8: Public | J8: Operations | K8: monitoring.sns.alerts_topic_arn | L8: Evaluated over 5-minute window on Step Functions execution failure rate metric | M8: 2026-07-01
A9: monitoring.alarm.api_5xx_threshold_pct | B9: 1 | C9: 5 | D9: 1 | E9: API Gateway 5xx error rate percentage threshold that triggers a P2 Slack alert | F9: Yes | G9: Integer | H9: 1-100 | I9: Public | J9: Operations | K9: monitoring.sns.alerts_topic_arn | L9: Evaluated over 15-minute window; VP Engineering notified via Slack #amatra-isb-ops | M9: 2026-07-01
A10: monitoring.alarm.bedrock_budget_warning_pct | B10: 80 | C10: 80 | D10: 80 | E10: Bedrock monthly token consumption percentage threshold that triggers a P3 email alert | F10: Yes | G10: Integer | H10: 50-100 | I10: Public | J10: Operations | K10: monitoring.sns.alerts_topic_arn | L10: Email sent to Head of Solutions; triggers Haiku substitution review per detailed design cost model | M10: 2026-07-01
A11: monitoring.alarm.dlq_depth_threshold | B11: 1 | C11: 1 | D11: 1 | E11: SQS DLQ message count threshold that triggers a P1 alert | F11: Yes | G11: Integer | H11: 1-1000 | I11: Public | J11: Operations | K11: monitoring.sns.alerts_topic_arn,integration.sqs.dlq_name | L11: Any DLQ message is P1; evaluated immediately; VP Engineering investigates failed job | M11: 2026-07-01
A12: monitoring.alarm.cognito_auth_failure_pct | B12: 10 | C12: 20 | D12: 10 | E12: Cognito authentication failure rate percentage threshold triggering a P2 alert and GuardDuty review | F12: Yes | G12: Integer | H12: 1-100 | I12: Public | J12: Operations | K12: monitoring.sns.alerts_topic_arn,security.guardduty_enabled | L12: Credential-stuffing detection; automated Lambda remediation suspends Cognito user if GuardDuty confirms | M12: 2026-07-01
A13: monitoring.synthetics.health_check_interval_seconds | B13: 60 | C13: 300 | D13: 60 | E13: CloudWatch Synthetics canary polling interval in seconds for GET /api/v1/health availability measurement | F13: Yes | G13: Integer | H13: 60-3600 | I13: Public | J13: Operations | K13: integration.api_gateway.rest_api_id | L13: Primary SLA measurement signal for 99.9% monthly availability target; runs from us-west-2 | M13: 2026-07-01

Sheet Integration
A1: Integration Parameters
A2: Parameter Name | B2: Production | C2: Test | D2: DR | E2: Description | F2: Required | G2: Data Type | H2: Validation Rules | I2: Security Level | J2: Owner Team | K2: Dependencies | L2: Notes | M2: Last Updated
A3: integration.api_gateway.rest_api_id | B3: [api-gateway-rest-api-id] | C3: [api-gateway-rest-api-id] | D3: [api-gateway-rest-api-id] | E3: API Gateway REST API ID for the platform endpoint | F3: Yes | G3: String | H3: 10-char alphanumeric | I3: Confidential | J3: Integration Team | K3: aws.region | L3: Generated by CloudFormation; referenced by WAF WebACL attachment and custom domain mapping | M3: 2026-07-01
A4: integration.api_gateway.stage_name | B4: prod | C4: dev | D4: prod | E4: API Gateway deployment stage name | F4: Yes | G4: String | H4: Alphanumeric max 128 chars | I4: Public | J4: Integration Team | K4: integration.api_gateway.rest_api_id | M4: 2026-07-01
A5: integration.api_gateway.throttle_burst_rps | B5: 500 | C5: 50 | D5: 500 | E5: API Gateway stage-level burst throttle limit in requests per second | F5: Yes | G5: Integer | H5: 1-10000 | I5: Public | J5: Integration Team | K5: integration.api_gateway.rest_api_id | L5: 500 RPS burst aligned to Lambda reserved concurrency of 500; prevents Lambda starvation | M5: 2026-07-01
A6: integration.api_gateway.throttle_steady_rps | B6: 200 | C6: 20 | D6: 200 | E6: API Gateway stage-level steady-state throttle limit in requests per second | F6: Yes | G6: Integer | H6: 1-10000 | I6: Public | J6: Integration Team | K6: integration.api_gateway.rest_api_id | L6: 200 RPS steady-state supports 120 concurrent users with comfortable headroom | M6: 2026-07-01
A7: integration.api_gateway.custom_domain | B7: [api-custom-domain] | C7: [api-custom-domain-dev] | D7: [api-custom-domain] | E7: Custom domain name for the API Gateway endpoint | F7: Yes | G7: String | H7: Valid FQDN | I7: Confidential | J7: Integration Team | K7: integration.api_gateway.rest_api_id | L7: ACM certificate auto-renews; TLS 1.2+ security policy enforced; DNS TTL 60 s pre-cutover | M7: 2026-07-01
A8: integration.bedrock.sonnet_model_id | B8: anthropic.claude-3-sonnet-20240229-v1:0 | C8: anthropic.claude-3-sonnet-20240229-v1:0 | D8: anthropic.claude-3-sonnet-20240229-v1:0 | E8: Amazon Bedrock model ID for Claude 3 Sonnet used for complex artifact types | F8: Yes | G8: String | H8: Valid Bedrock model ID | I8: Public | J8: Development | K8: aws.region | L8: Used for SoW / detailed design / implementation guide types; ~10M input tokens/month per SOW | M8: 2026-07-01
A9: integration.bedrock.haiku_model_id | B9: anthropic.claude-3-haiku-20240307-v1:0 | C9: anthropic.claude-3-haiku-20240307-v1:0 | D9: anthropic.claude-3-haiku-20240307-v1:0 | E9: Amazon Bedrock model ID for Claude 3 Haiku used for lightweight artifact types | F9: Yes | G9: String | H9: Valid Bedrock model ID | I9: Public | J9: Development | K9: aws.region | L9: Used for discovery questionnaire type; ~60% lower cost than Sonnet per SOW cost model | M9: 2026-07-01
A10: integration.bedrock.max_input_tokens_monthly | B10: 10000000 | C10: 1000000 | D10: 10000000 | E10: Monthly Bedrock input token budget across all artifact generation jobs | F10: Yes | G10: Integer | H10: 100000-100000000 | I10: Public | J10: Development | K10: integration.bedrock.sonnet_model_id | L10: P3 CloudWatch alarm fires at 80% consumed; aligned to SOW scope ~10M input tokens/month | M10: 2026-07-01
A11: integration.bedrock.max_output_tokens_monthly | B11: 5000000 | C11: 500000 | D11: 5000000 | E11: Monthly Bedrock output token budget across all artifact generation jobs | F11: Yes | G11: Integer | H11: 100000-50000000 | I11: Public | J11: Development | K11: integration.bedrock.sonnet_model_id | L11: Aligned to SOW scope ~5M output tokens/month; Haiku substitution reduces cost when budget at 80% | M11: 2026-07-01
A12: integration.bedrock.retry_max_attempts | B12: 3 | C12: 3 | D12: 3 | E12: Maximum Step Functions retry attempts on Bedrock ThrottlingException or ServiceUnavailableException | F12: Yes | G12: Integer | H12: 1-10 | I12: Public | J12: Development | K12: integration.bedrock.sonnet_model_id,integration.bedrock.haiku_model_id | L12: Exponential backoff with 30 s initial interval and rate 2; after 3 failures job marked FAILED | M12: 2026-07-01
A13: integration.bedrock.retry_interval_seconds | B13: 30 | C13: 10 | D13: 30 | E13: Initial retry interval in seconds for Bedrock invocation failures in Step Functions | F13: Yes | G13: Integer | H13: 1-300 | I13: Public | J13: Development | K13: integration.bedrock.retry_max_attempts | M13: 2026-07-01
A14: integration.sqs.job_queue_name | B14: amatra-isb-job-queue-prod | C14: amatra-isb-job-queue-dev | D14: amatra-isb-job-queue-prod | E14: SQS Standard Queue name for async generation job messages | F14: Yes | G14: String | H14: Alphanumeric hyphens max 80 chars | I14: Confidential | J14: Integration Team | K14: aws.region | L14: Visibility timeout 5 min; message retention 4 days; DLQ attached per detailed design | M14: 2026-07-01
A15: integration.sqs.dlq_name | B15: amatra-isb-job-dlq-prod | C15: amatra-isb-job-dlq-dev | D15: amatra-isb-job-dlq-prod | E15: SQS Dead Letter Queue name for failed job messages after max receive attempts | F15: Yes | G15: String | H15: Alphanumeric hyphens max 80 chars | I15: Confidential | J15: Integration Team | K15: integration.sqs.job_queue_name | L15: DLQ depth > 0 triggers P1 SNS alert; messages investigated and replayed manually or via replay Lambda | M15: 2026-07-01
A16: integration.sqs.visibility_timeout_seconds | B16: 300 | C16: 300 | D16: 300 | E16: SQS visibility timeout in seconds for job queue messages | F16: Yes | G16: Integer | H16: 0-43200 | I16: Public | J16: Integration Team | K16: integration.sqs.job_queue_name | L16: Must be >= Step Functions Initiator Lambda timeout to prevent duplicate processing | M16: 2026-07-01
A17: integration.sqs.message_retention_seconds | B17: 345600 | C17: 345600 | D17: 345600 | E17: SQS message retention period in seconds (4 days) | F17: Yes | G17: Integer | H17: 60-1209600 | I17: Public | J17: Integration Team | K17: integration.sqs.job_queue_name | L17: 4 days provides buffer for investigation of stuck jobs; DLQ catches unprocessed messages | M17: 2026-07-01
A18: integration.sqs.max_receive_count | B18: 3 | C18: 3 | D18: 3 | E18: Maximum number of times a message is received before moving to the DLQ | F18: Yes | G18: Integer | H18: 1-1000 | I18: Public | J18: Integration Team | K18: integration.sqs.job_queue_name,integration.sqs.dlq_name | L18: Aligns to Bedrock retry max attempts; after 3 failures message routes to DLQ for triage | M18: 2026-07-01
A19: integration.stepfunctions.state_machine_arn | B19: [step-functions-state-machine-arn] | C19: [step-functions-state-machine-arn] | D19: [step-functions-state-machine-arn] | E19: ARN of the AWS Step Functions Standard Workflow for async generation orchestration | F19: Yes | G19: String | H19: Valid Step Functions ARN | I19: Confidential | J19: Integration Team | K19: aws.region | L19: Supports up to 2000 concurrent executions; 90-day execution history retention per detailed design | M19: 2026-07-01
A20: integration.stepfunctions.execution_history_days | B20: 90 | C20: 30 | D20: 90 | E20: Step Functions execution history retention period in days | F20: Yes | G20: Integer | H20: 1-90 | I20: Public | J20: Integration Team | K20: integration.stepfunctions.state_machine_arn | L20: 90 days supports job audit and replay; CloudTrail provides longer-term audit trail | M20: 2026-07-01
A21: integration.secrets_manager.secret_prefix | B21: amatra/prod | C21: amatra/dev | D21: amatra/prod | E21: Prefix path for all Secrets Manager secrets following convention amatra/{env}/{service}/{secret-name} | F21: Yes | G21: String | H21: Alphanumeric slashes format amatra/{env} | I21: Confidential | J21: Integration Team | K21: aws.region | L21: All 10 initial secrets stored under this prefix; Lambda caches at init to reduce API call costs | M21: 2026-07-01
A22: integration.datadog.api_key | B22: [datadog-api-key] | C22: [datadog-api-key] | D22: [datadog-api-key] | E22: Datadog API key for Lambda layer APM agent telemetry and cold-start profiling | F22: Yes | G22: String | H22: 32-char hex string | I22: Secret | J22: Operations | K22: integration.secrets_manager.secret_prefix | L22: Store in Secrets Manager under amatra/{env}/datadog/api-key; rotate annually; fire-and-forget telemetry | M22: 2026-07-01
A23: integration.github_actions.oidc_role_arn | B23: [github-actions-oidc-role-arn] | C23: [github-actions-oidc-role-arn] | D23: [github-actions-oidc-role-arn] | E23: IAM Role ARN assumed by GitHub Actions via OIDC for CI/CD deployments | F23: Yes | G23: String | H23: Valid IAM Role ARN | I23: Secret | J23: Cloud CoE | K23: aws.account_id | L23: No static AWS credentials stored in GitHub; OIDC token exchange per deploy; Prod requires manual approval | M23: 2026-07-01

Sheet Operations
A1: Operations Parameters
A2: Parameter Name | B2: Production | C2: Test | D2: DR | E2: Description | F2: Required | G2: Data Type | H2: Validation Rules | I2: Security Level | J2: Owner Team | K2: Dependencies | L2: Notes | M2: Last Updated
A3: operations.usage_limit.per_user_monthly_default | B3: 10 | C3: 5 | D3: 10 | E3: Default monthly generation count limit per Amatra internal user | F3: Yes | G3: Integer | H3: 1-1000 | I3: Public | J3: Operations | K3: database.usage_tracking_table | L3: Enforced by pre-authorisation Lambda before each job submission; AmAdmin can override per user | M3: 2026-07-01
A4: operations.usage_limit.global_monthly_default | B4: 240 | C4: 50 | D4: 240 | E4: Default monthly global generation count limit across all users | F4: Yes | G4: Integer | H4: 1-10000 | I4: Public | J4: Operations | K4: database.usage_tracking_table | L4: 240 = 24 engagements/quarter × 10 artifact types; AmAdmin can override; aligned to SOW scope | M4: 2026-07-01
A5: operations.backup.cognito_export_schedule | B5: cron(0 2 * * ? *) | C5: cron(0 2 * * ? *) | D5: cron(0 2 * * ? *) | E5: CloudWatch Events cron expression for nightly Cognito user pool export to S3 | F5: Yes | G5: String | H5: Valid CloudWatch Events cron expression | I5: Public | J5: Operations | K5: storage.s3.artifacts_bucket_name,security.cognito.user_pool_id | L5: Nightly at 02:00 UTC; export encrypted with amatra-s3-artifacts-cmk; ~120 users; RTO ≤30 min restore | M5: 2026-07-01
A6: operations.backup.dynamodb_pitr_window_days | B6: 35 | C6: 7 | D6: 35 | E6: DynamoDB PITR continuous backup window in days | F6: Yes | G6: Integer | H6: 1-35 | I6: Public | J6: Operations | K6: database.pitr_enabled | L6: AWS maximum is 35 days; supports RPO ≤15 min target; restore tested at each phase go-live gate | M6: 2026-07-01
A7: operations.cicd.github_repo | B7: amatra/amatra-isb | C7: amatra/amatra-isb | D7: amatra/amatra-isb | E7: GitHub repository containing all Lambda source code and CloudFormation/SAM templates | F7: Yes | G7: String | H7: Valid GitHub org/repo format | I7: Confidential | J7: Cloud CoE | L7: GitOps model; all infra changes via pull request; no direct console changes to Production | M7: 2026-07-01
A8: operations.cicd.production_approval_required | B8: true | C8: false | D8: true | E8: Require manual GitHub Actions approval gate before deploying to Production environment | F8: Yes | G8: Boolean | H8: true|false | I8: Public | J8: Cloud CoE | K8: operations.cicd.github_repo | L8: Approval action logged to CloudTrail; VP Engineering is designated approver for production deploys | M8: 2026-07-01
A9: operations.cicd.lambda_alias_prod | B9: $PROD | C9: $DEV | D9: $PROD | E9: Lambda function alias name used for production traffic routing in blue-green deployments | F9: Yes | G9: String | H9: Non-empty string max 128 chars | I9: Public | J9: Cloud CoE | K9: compute.lambda.runtime | L9: Blue-green promotion; rollback = revert alias to prior version; target ≤30 min rollback time | M9: 2026-07-01
A10: operations.rollback.trigger_job_failure_pct | B10: 20 | C10: 50 | D10: 20 | E10: Async job failure rate percentage within 4 hours of cutover that triggers automatic rollback | F10: Yes | G10: Integer | H10: 1-100 | I10: Public | J10: Operations | K10: monitoring.alarm.job_failure_rate_threshold_pct | L10: One of 4 rollback triggers per SOW cutover plan; decision authority: vendor PM + VP Engineering | M10: 2026-07-01
A11: operations.rollback.trigger_5xx_pct | B11: 5 | C11: 10 | D11: 5 | E11: API Gateway 5xx error rate percentage within 4 hours of cutover that triggers rollback | F11: Yes | G11: Integer | H11: 1-100 | I11: Public | J11: Operations | K11: monitoring.alarm.api_5xx_threshold_pct | L11: Rollback target ≤30 min; Lambda alias revert via single GitHub Actions workflow step | M11: 2026-07-01
A12: operations.qa.first_pass_target_pct | B12: 90 | C12: 80 | D12: 90 | E12: Target QA first-pass acceptance rate percentage for generated artifacts | F12: Yes | G12: Integer | H12: 1-100 | I12: Public | J12: Operations | K12: application.artifact_types | L12: Phase 2 QA validation layer automates scoring; artifacts below threshold flagged for human review | M12: 2026-07-01
A13: operations.hypercare.phase1_duration_weeks | B13: 8 | C13: 0 | D13: 8 | E13: Duration in weeks of Phase 1 hypercare support period post-MVP go-live (target: 30 Sep 2026) | F13: Yes | G13: Integer | H13: 1-52 | I13: Public | J13: Operations | L13: Business hours 09:00–18:00 CT Mon–Fri; P1 ≤2 h response; P2 next business day; Slack channel | M13: 2026-07-01
A14: operations.hypercare.phase2_duration_weeks | B14: 4 | C14: 0 | D14: 4 | E14: Duration in weeks of Phase 2 hypercare support period post-Phase 2 go-live (target: 15 Dec 2026) | F14: Yes | G14: Integer | H14: 1-52 | I14: Public | J14: Operations | L14: Business hours 09:00–18:00 CT Mon–Fri; P1 ≤2 h response; P2 next business day; Slack channel | M14: 2026-07-01
